Workbook
Name Slicer_Channel: #N/A
Name Slicer_Country: #N/A
Name Slicer_ProductCategory: #N/A
Name Slicer_Region: #N/A
Name Slicer_Salesperson: #N/A

Sheet Dashboard

Sheet Data
A1: OrderID | B1: OrderDate | C1: RequiredDate | D1: Region | E1: Country | F1: City | G1: CustomerSegment | H1: Channel | I1: Salesperson | J1: ProductCategory | K1: SKU | L1: UnitCost | M1: UnitPrice | N1: DiscountPct | O1: Quantity
A2: ORD-2024-275203 | B2: 45362 | C2: 45388 | D2: Africa | E2: Kenya | F2: Kisumu | G2: Corporate | H2: Retail | I2: C. Otieno | J2: Components | K2: CMP-8270 | L2: 279.24 | M2: 608.9 | N2: 0.112 | O2: 9
A3: ORD-2024-358795 | B3: 45588 | C3: 45587 | D3: Africa | E3: Nigeria | F3: Port Harcourt | G3: Education | H3: Online | I3: J. Njeri | J3: Printers | K3: PRN-9322 | L3: 1084.39 | M3: 759.33 | N3: 0.237 | O3: 31
A4: ORD-2023-373538 | B4: 44985 | C4: 45010 | D4: Africa | E4: Kenya | F4: Nairobi | G4: Corporate | H4: Retail | I4: I. Johnson | J4: Networking | K4: NET-9666 | L4: 1460.76 | M4: -30.66 | N4: 0.131 | O4: 12
A5: ORD-2025-168148 | B5: 45745 | C5: 45749 | D5: Africa | E5: Nigeria | F5: Lagos | G5: Non-Profit | H5: Marketplace | I5: G. Dubois | J5: Phones | K5: PHN-4556 | L5: 259.93 | M5: 255.94 | N5: 0.072 | O5: 22
A6: ORD-2023-824839 | B6: 45266 | C6: 45291 | D6: Asia | E6: Japan | F6: Osaka | G6: Consumer | H6: Retail | I6: L. Okafor | J6: Printers | K6: PRN-8041 | L6: 663.03 | M6: 813.51 | N6: 0.102 | O6: 15
A7: ORD-2023-723587 | B7: 44928 | C7: 44931 | D7: Americas | E7: Canada | F7: Toronto | G7: Corporate | H7: Distributor | I7: B. Chen | J7: Laptops | K7: LAP-8555 | L7: 315.87 | M7: 591.68 | N7: 0 | O7: 7
A8: ORD-2024-336584 | B8: 45653 | C8: 45671 | D8: Asia | E8: India | F8: Bengaluru | G8: Small Business | H8: Marketplace | I8: E. Garcia | J8: Monitors | K8: MON-8629 | L8: 586.07 | M8: 845.97 | N8: 0.147 | O8: 4
A9: ORD-2023-112666 | B9: 44941 | C9: 44939 | D9: Africa | E9: Nigeria | F9: Abuja | G9: Education | H9: Online | I9: O. Wang | J9: Printers | K9: PRN-6276 | L9: 28.38 | M9: 47.22 | N9: 0.194 | O9: 18
A10: ORD-2024-589570 | B10: 45416 | C10: 45441 | D10: Africa | E10: Nigeria | F10: Abuja | G10: Non-Profit | H10: Marketplace | I10: O. Wang | J10: Monitors | K10: MON-6892 | L10: 1295.34 | M10: 2530.81 | N10: 0.031 | O10: 6
A11: ORD-2025-997421 | B11: 45798 | C11: 45817 | D11: Americas | E11: Brazil | F11: São Paulo | G11: Non-Profit | H11: Online | I11: A. Patel | J11: Components | K11: CMP-3731 | L11: 1331.38 | M11: 2309.56 | N11: 0.149 | O11: 31
A12: ORD-2024-210687 | B12: 45319 | C12: 45331 | D12: Europe | E12: Germany | F12: Berlin | G12: Corporate | H12: Online | I12: G. Dubois | J12: Accessories | K12: ACC-7938 | L12: 644.17 | M12: 700.12 | N12: 0.006 | O12: 23
A13: ORD-2025-515515 | B13: 45660 | C13: 45680 | D13: Asia | E13: Japan | F13: Osaka | G13: Corporate | H13: Distributor | I13: F. Müller | J13: Phones | K13: PHN-7019 | L13: 908.6 | M13: 691.37 | N13: 0.25 | O13: 20
... A34: ORD-2025-474710 | B34: 45862 | C34: 45875 | D34: Africa | E34: South Africa | F34: Johannesburg | G34: Education | H34: Marketplace | I34: D. Smith | J34: Networking | K34: NET-7966 | L34: 1463.9 | M34: 2633.02 | N34: 0.084 | O34: 4
A35: ORD-2024-629525 | B35: 45400 | C35: 45420 | D35: Europe | E35: United Kingdom | F35: London | G35: Non-Profit | I35: D. Smith | J35: Laptops | K35: LAP-9932 | L35: 645.33 | M35: 1321.85 | N35: 0 | O35: 10
A36: ORD-2024-167215 | B36: 45527 | C36: 45525 | D36: Africa | E36: South Africa | F36: Johannesburg | G36: Education | H36: Retail | I36: E. Garcia | J36: Components | K36: CMP-1559 | L36: 1432.52 | M36: 3036.87 | N36: 0 | O36: 9
A37: ORD-2023-864121 | B37: 45012 | C37: 45038 | D37: Asia | E37: India | F37: Delhi | G37: Non-Profit | H37: Marketplace | I37: J. Njeri | J37: Printers | K37: PRN-4506 | L37: 178.53 | M37: 199.37 | N37: 0.101 | O37: 37
A38: ORD-2024-692673 | B38: 45358 | C38: 45376 | D38: Europe | E38: Germany | F38: Munich | G38: Corporate | H38: Online | I38: B. Chen | J38: Components | K38: CMP-7617 | L38: 712.84 | M38: 927.51 | N38: 0.243 | O38: 27
A39: ORD-2025-718992 | B39: 45832 | C39: 45848 | D39: Asia | E39: China | F39: Shanghai | G39: Enterprise | H39: Direct | I39: N. Brown | J39: Components | K39: CMP-8390 | L39: 757.19 | M39: 1735.41 | N39: 0.136 | O39: 8
A40: ORD-2024-599522 | B40: 45401 | C40: 45418 | D40: Africa | E40: Nigeria | F40: Port Harcourt | G40: Non-Profit | H40: Online | I40: A. Patel | J40: Printers | K40: PRN-7303 | L40: 865.33 | M40: 1395.64 | N40: 0.175 | O40: 13
A41: ORD-2023-651638 | B41: 45094 | C41: 45101 | D41: Americas | E41: USA | F41: San Francisco | G41: Corporate | H41: Retail | I41: I. Johnson | J41: Printers | K41: PRN-6536 | L41: 313.99 | M41: 454.42 | N41: 0.129 | O41: 9
A42: ORD-2024-635626 | B42: 45531 | C42: 45554 | D42: Europe | E42: Germany | F42: Berlin | G42: Small Business | H42: Direct | I42: D. Smith | J42: Monitors | K42: MON-9967 | L42: 1024.01 | M42: 1580.97 | N42: 0.037 | O42: 27
A43: ORD-2024-296582 | B43: 45302 | C43: 45324 | D43: Africa | E43: South Africa | F43: Durban | G43: Consumer | H43: Online | I43: K. Singh | J43: Networking | K43: NET-1412 | L43: 1206.2 | M43: 1759.79 | N43: 0 | O43: 6
A44: ORD-2024-998320 | B44: 45590 | C44: 45610 | D44: Africa | E44: Kenya | F44: Mombasa | G44: Corporate | H44: Direct | I44: H. Kim | J44: Printers | K44: PRN-3143 | L44: 1396.48 | M44: 3204.5 | N44: 0.318 | O44: 14
A45: ORD-2025-820255 | B45: 45806 | C45: 45828 | D45: Europe | E45: Germany | F45: Berlin | G45: Corporate | H45: Direct | I45: A. Patel | J45: Printers | K45: PRN-9787 | L45: 483.47 | M45: 1135.43 | N45: 0.146 | O45: 11
A46: ORD-2024-389336 | B46: 45432 | C46: 45445 | D46: Americas | E46: Canada | F46: Vancouver | G46: Enterprise | H46: Marketplace | I46: K. Singh | J46: Components | K46: CMP-5946 | L46: 675.43 | M46: 996.36 | N46: 0.182 | O46: 22
A47: ORD-2023-308124 | B47: 45035 | C47: 45046 | D47: Asia | E47: India | F47: Delhi | G47: Small Business | H47: Retail | I47: A. Patel | J47: Networking | K47: NET-2062 | L47: 826.55 | M47: 1397.05 | N47: 0.169 | O47: 28
... A77: ORD-2023-722117 | B77: 45187 | C77: 45207 | D77: Asia | E77: India | F77: Delhi | G77: Small Business | H77: Direct | I77: B. Chen | J77: Components | K77: CMP-1009 | L77: 825.64 | M77: 1108.43 | N77: 0.114 | O77: 7
A78: ORD-2024-446699 | B78: 45532 | C78: 45560 | D78: Americas | E78: Brazil | F78: Rio de Janeiro | G78: Non-Profit | H78: Online | J78: Accessories | K78: ACC-4490 | L78: 1394.65 | M78: 3144.1 | N78: 0.134 | O78: 13
A79: ORD-2024-451005 | B79: 45473 | C79: 45471 | D79: Americas | E79: Brazil | F79: Rio de Janeiro | G79: Small Business | H79: Direct | I79: L. Okafor | J79: Accessories | K79: ACC-9162 | L79: 1112.98 | M79: 2095.73 | N79: 0.072 | O79: 17
A80: ORD-2023-290279 | B80: 45091 | C80: 45093 | D80: Europe | E80: United Kingdom | F80: Manchester | G80: Non-Profit | H80: Direct | I80: K. Singh | J80: Components | K80: CMP-5820 | L80: 357.36 | M80: 703.62 | N80: 0.257 | O80: 20
A81: ORD-2024-192263 | B81: 45617 | C81: 45647 | D81: Europe | E81: France | F81: Marseille | G81: Small Business | H81: Direct | I81: I. Johnson | J81: Monitors | K81: MON-7943 | L81: 1122.68 | M81: 1997.19 | N81: 0.186 | O81: 3
A82: ORD-2023-159379 | B82: 44965 | C82: 44968 | D82: Africa | E82: South Africa | F82: Cape Town | G82: Corporate | H82: Direct | I82: M. Rossi | J82: Networking | K82: NET-5018 | L82: 1410.05 | M82: 2763.95 | N82: 0.161 | O82: 26
A83: ORD-2023-343322 | B83: 45157 | C83: 45181 | D83: Americas | E83: Canada | F83: Vancouver | G83: Enterprise | H83: Retail | I83: I. Johnson | J83: Printers | K83: PRN-9669 | L83: 1183.95 | M83: 1503.53 | N83: 0.241 | O83: 16
A84: ORD-2025-114382 | B84: 45791 | C84: 45801 | D84: Europe | E84: France | F84: Paris | G84: Small Business | H84: Marketplace | I84: K. Singh | J84: Components | K84: CMP-2865 | L84: 170.39 | M84: 388.04 | N84: 0.084 | O84: 15
A85: ORD-2025-488349 | B85: 45770 | C85: 45769 | D85: Americas | E85: USA | F85: San Francisco | G85: Non-Profit | H85: Distributor | I85: D. Smith | J85: Monitors | K85: MON-3371 | L85: 23.24 | M85: 44.57 | N85: 0.215 | O85: 15
A86: ORD-2025-330203 | B86: 45741 | C86: 45764 | D86: Europe | E86: United Kingdom | F86: London | G86: Consumer | H86: Retail | I86: H. Kim | J86: Networking | K86: NET-7166 | L86: 1421.19 | M86: 1808.26 | N86: 0.104 | O86: 13
A87: ORD-2023-841426 | B87: 45282 | C87: 45283 | D87: Africa | E87: South Africa | F87: Cape Town | G87: Non-Profit | H87: Marketplace | I87: D. Smith | J87: Components | K87: CMP-4531 | L87: 1186.18 | M87: 1285.09 | N87: 0.07 | O87: 11
A88: ORD-2024-594592 | B88: 45388 | C88: 45407 | D88: Asia | E88: China | F88: Shanghai | G88: Corporate | H88: Retail | I88: K. Singh | J88: Components | K88: CMP-8196 | L88: 1366.48 | M88: 1678.14 | N88: 0.154 | O88: 10
A89: ORD-2025-863978 | B89: 45876 | C89: 45888 | D89: Africa | E89: Kenya | F89: Nakuru | G89: Corporate | I89: M. Rossi | J89: Components | K89: CMP-2854 | L89: 601.51 | M89: 679.35 | N89: 0.188 | O89: 3
A90: ORD-2024-604471 | B90: 45312 | C90: 45316 | D90: Asia | E90: India | F90: Delhi | G90: Consumer | H90: Direct | I90: C. Otieno | J90: Monitors | K90: MON-8973 | L90: 523.7 | M90: 1109.92 | N90: 0.03 | O90: 11
A91: ORD-2023-258768 | B91: 45106 | C91: 45109 | D91: Asia | E91: Japan | F91: Nagoya | G91: Education | H91: Marketplace | I91: F. Müller | J91: Monitors | K91: MON-2990 | L91: 55.65 | M91: 83.57 | N91: 0.066 | O91: 8
A92: ORD-2025-626047 | B92: 45775 | C92: 45792 | D92: Asia | E92: Japan | F92: Nagoya | G92: Education | H92: Direct | I92: N. Brown | J92: Networking | K92: NET-1966 | L92: 691.19 | M92: 1284.3 | N92: 0.074 | O92: 7
A93: ORD-2025-526752 | B93: 45817 | C93: 45833 | D93: Asia | E93: India | F93: Hyderabad | G93: Enterprise | H93: Distributor | I93: M. Rossi | J93: Phones | K93: PHN-3482 | L93: 527.33 | M93: 911.72 | N93: 0.144 | O93: 25
A94: ORD-2023-374486 | B94: 45101 | C94: 45100 | D94: Americas | E94: Brazil | F94: Rio de Janeiro | G94: Non-Profit | H94: Retail | I94: E. Garcia | J94: Printers | K94: PRN-6490 | L94: 804.01 | M94: 1405.07 | N94: 0.096 | O94: 8
A95: ORD-2024-997336 | B95: 45569 | C95: 45598 | D95: Africa | E95: Nigeria | F95: Abuja | G95: Corporate | H95: Distributor | I95: F. Müller | J95: Accessories | K95: ACC-9038 | L95: 412.09 | M95: 968.94 | N95: 0.099 | O95: 23
A96: ORD-2025-725646 | B96: 45910 | C96: 45930 | D96: Africa | E96: Kenya | F96: Mombasa | G96: Corporate | H96: Direct | I96: L. Okafor | J96: Phones | K96: PHN-6954 | L96: 1009.48 | M96: 1088.81 | N96: 0.16 | O96: 6
A97: ORD-2023-868734 | B97: 45022 | C97: 45043 | D97: Europe | E97: United Kingdom | F97: Manchester | G97: Enterprise | H97: Distributor | I97: I. Johnson | J97: Printers | K97: PRN-8970 | L97: 1084.79 | M97: 2484.99 | N97: 0.034 | O97: 18
A98: ORD-2025-262491 | B98: 45870 | C98: 45885 | D98: Asia | E98: India | G98: Enterprise | H98: Direct | I98: O. Wang | J98: Monitors | K98: MON-1822 | L98: 24.44 | M98: 28.69 | N98: 0.146 | O98: 6
A99: ORD-2024-638884 | B99: 45440 | C99: 45438 | D99: Africa | E99: Nigeria | F99: Abuja | G99: Enterprise | H99: Online | I99: F. Müller | J99: Accessories | K99: ACC-5177 | L99: 1227.08 | M99: 1896.62 | N99: 0 | O99: 18
A100: ORD-2025-541501 | B100: 45860 | C100: 45887 | D100: Asia | E100: China | F100: Shenzhen | G100: Non-Profit | H100: Marketplace | I100: M. Rossi | J100: Networking | K100: NET-1804 | L100: 547.32 | M100: 419.17 | N100: 0.092 | O100: 14
A101: ORD-2023-422918 | B101: 44985 | C101: 45005 | D101: Europe | E101: Germany | F101: Berlin | G101: Small Business | H101: Direct | I101: H. Kim | J101: Laptops | K101: LAP-3679 | L101: 1200.78 | M101: 2001.17 | N101: 0.292 | O101: 18
A102: ORD-2025-328504 | B102: 45684 | C102: 45703 | D102: Asia | E102: China | F102: Shenzhen | G102: Non-Profit | H102: Direct | I102: L. Okafor | J102: Phones | K102: PHN-8368 | L102: 1253.22 | M102: 3104.71 | N102: 0 | O102: 17
A103: ORD-2024-851883 | B103: 45304 | C103: 45313 | D103: Asia | E103: India | F103: Mumbai | G103: Enterprise | H103: Marketplace | I103: J. Njeri | J103: Components | K103: CMP-8141 | L103: 313.6 | M103: 334.28 | N103: 0.14 | O103: 22
A104: ORD-2025-662997 | B104: 45747 | C104: 45751 | D104: Africa | E104: Kenya | F104: Nakuru | G104: Corporate | H104: Direct | I104: C. Otieno | J104: Laptops | K104: LAP-7136 | L104: 862.08 | M104: 1952.83 | N104: 0 | O104: 7
A105: ORD-2024-478165 | B105: 45631 | C105: 45654 | D105: Americas | E105: Canada | F105: Vancouver | G105: Corporate | H105: Direct | I105: F. Müller | J105: Accessories | K105: ACC-2386 | L105: 107.03 | M105: 242.29 | N105: 0.18 | O105: 30
A106: ORD-2024-771210 | B106: 45549 | C106: 45570 | D106: Asia | E106: China | F106: Shanghai | G106: Small Business | H106: Online | I106: H. Kim | J106: Laptops | K106: LAP-5150 | L106: 1405.56 | M106: 2968.87 | N106: 0.169 | O106: 5
A107: ORD-2024-155337 | B107: 45433 | C107: 45439 | D107: Africa | E107: South Africa | F107: Johannesburg | G107: Non-Profit | H107: Online | I107: M. Rossi | J107: Components | K107: CMP-8101 | L107: 1157.51 | M107: 1394.3 | N107: 0.278 | O107: 12
A108: ORD-2023-251563 | B108: 45057 | C108: 45084 | D108: Africa | E108: Kenya | F108: Mombasa | G108: Corporate | H108: Online | I108: J. Njeri | J108: Phones | K108: PHN-8970 | L108: 12.85 | M108: 15.41 | N108: 0.137 | O108: 39
A109: ORD-2024-286833 | B109: 45518 | C109: 45539 | D109: Europe | E109: United Kingdom | F109: Manchester | G109: Non-Profit | H109: Online | I109: J. Njeri | J109: Phones | K109: PHN-2341 | L109: 1138.8 | M109: 2250.81 | N109: 0.123 | O109: 12
A110: ORD-2024-792558 | B110: 45581 | C110: 45604 | D110: Asia | E110: Japan | F110: Osaka | G110: Small Business | H110: Retail | I110: J. Njeri | J110: Networking | K110: NET-6387 | L110: 82.14 | M110: 166.04 | N110: 0 | O110: 10
... A121: ORD-2025-956101 | B121: 45847 | C121: 45856 | D121: Americas | E121: Canada | F121: Vancouver | G121: Education | H121: Distributor | I121: I. Johnson | J121: Laptops | K121: LAP-2218 | L121: 57.96 | M121: 88.51 | N121: 0.043 | O121: 7
A122: ORD-2025-184082 | B122: 45827 | C122: 45850 | D122: Europe | E122: United Kingdom | G122: Non-Profit | H122: Direct | J122: Networking | K122: NET-6370 | L122: 801.24 | M122: 1959.09 | N122: 0.123 | O122: 23
A123: ORD-2023-576840 | B123: 45249 | C123: 45273 | D123: Europe | E123: France | F123: Lyon | G123: Non-Profit | H123: Direct | I123: H. Kim | J123: Monitors | K123: MON-3745 | L123: 1297.42 | M123: 2742.97 | N123: 0.069 | O123: 9
A124: ORD-2023-178249 | B124: 45289 | C124: 45311 | D124: Africa | E124: Kenya | F124: Kisumu | G124: Corporate | H124: Direct | I124: L. Okafor | J124: Phones | K124: PHN-7924 | L124: 1395.49 | M124: 1679.42 | N124: 0.203 | O124: 12
A125: ORD-2024-588972 | B125: 45598 | C125: 45625 | D125: Americas | E125: Brazil | F125: Brasília | G125: Small Business | H125: Direct | I125: I. Johnson | J125: Networking | K125: NET-8561 | L125: 1363.51 | M125: 1433.9 | N125: 0.057 | O125: 8
A126: ORD-2023-603238 | B126: 45159 | C126: 45173 | D126: Americas | E126: Canada | F126: Montreal | G126: Education | H126: Distributor | I126: F. Müller | J126: Components | K126: CMP-2136 | L126: 178.19 | M126: 284.43 | N126: 0.089 | O126: 8
A127: ORD-2023-883066 | B127: 45150 | C127: 45175 | D127: Asia | E127: China | F127: Shanghai | G127: Small Business | H127: Retail | I127: B. Chen | J127: Components | K127: CMP-6352 | L127: 950.77 | M127: 694.78 | N127: 0.084 | O127: 14
A128: ORD-2024-584090 | B128: 45450 | C128: 45469 | D128: Europe | E128: Germany | F128: Berlin | G128: Non-Profit | H128: Marketplace | I128: M. Rossi | J128: Components | K128: CMP-2040 | L128: 1064.32 | M128: 1848.39 | N128: 0.073 | O128: 38
A129: ORD-2025-537785 | B129: 45874 | C129: 45883 | D129: Europe | E129: United Kingdom | F129: London | G129: Non-Profit | H129: Direct | I129: E. Garcia | J129: Components | K129: CMP-6346 | L129: 41.76 | M129: 45.19 | N129: 0.179 | O129: 23
A130: ORD-2024-605518 | B130: 45442 | C130: 45456 | D130: Americas | E130: USA | F130: San Francisco | G130: Small Business | H130: Retail | I130: F. Müller | J130: Phones | K130: PHN-4356 | L130: 157.78 | M130: 361.1 | N130: 0.187 | O130: 9
A131: ORD-2023-521818 | B131: 44948 | C131: 44956 | D131: Americas | E131: USA | F131: San Francisco | G131: Small Business | H131: Online | I131: A. Patel | J131: Networking | K131: NET-4155 | L131: 413.52 | M131: 1004.34 | N131: 0.111 | O131: 18
A132: ORD-2025-650719 | B132: 45700 | C132: 45716 | D132: Americas | E132: Brazil | F132: São Paulo | G132: Non-Profit | H132: Direct | I132: B. Chen | J132: Monitors | K132: MON-5179 | L132: 414.95 | M132: 1027.73 | N132: 0.063 | O132: 8
A133: ORD-2025-501927 | B133: 45719 | C133: 45740 | D133: Africa | E133: Nigeria | F133: Abuja | G133: Enterprise | H133: Direct | I133: H. Kim | J133: Accessories | K133: ACC-4056 | L133: 555.95 | M133: 468.09 | N133: 0.142 | O133: 11
A134: ORD-2023-430904 | B134: 44953 | C134: 44957 | D134: Europe | E134: United Kingdom | F134: Manchester | G134: Enterprise | H134: Online | I134: N. Brown | J134: Laptops | K134: LAP-9782 | L134: 941.2 | M134: 668.02 | N134: 0.22 | O134: 16
... A187: ORD-2023-399631 | B187: 45099 | C187: 45128 | D187: Europe | E187: France | F187: Lyon | G187: Corporate | H187: Retail | I187: J. Njeri | J187: Accessories | K187: ACC-3385 | L187: 734.34 | M187: 887.9 | N187: 0.025 | O187: 12
A188: ORD-2025-542939 | B188: 45670 | C188: 45696 | D188: Europe | E188: France | F188: Paris | G188: Non-Profit | I188: E. Garcia | J188: Monitors | K188: MON-1593 | L188: 594.74 | M188: 1020.69 | N188: 0.211 | O188: 6
A189: ORD-2023-521818 | B189: 44955 | C189: 44985 | D189: Asia | E189: India | F189: Bengaluru | G189: Non-Profit | H189: Retail | I189: B. Chen | J189: Accessories | K189: ACC-4631 | L189: 1262.1 | M189: 1395.53 | N189: 0.233 | O189: 25
A190: ORD-2023-825836 | B190: 45126 | C190: 45138 | D190: Americas | E190: Brazil | F190: Rio de Janeiro | G190: Corporate | H190: Retail | I190: C. Otieno | J190: Monitors | K190: MON-7869 | L190: 1334.64 | M190: 2273.42 | N190: 0.118 | O190: 14
A191: ORD-2024-503082 | B191: 45431 | C191: 45451 | D191: Americas | E191: Brazil | F191: Brasília | G191: Small Business | H191: Retail | I191: E. Garcia | J191: Monitors | K191: MON-4271 | L191: 1075.9 | M191: 1242.15 | N191: 0.012 | O191: 7
A192: ORD-2024-760799 | B192: 45325 | C192: 45341 | D192: Asia | E192: China | F192: Shenzhen | G192: Small Business | H192: Online | I192: H. Kim | J192: Laptops | K192: LAP-5531 | L192: 993.75 | M192: 1310.29 | N192: 0.215 | O192: 19
A193: ORD-2023-197661 | B193: 45146 | C193: 45160 | D193: Europe | E193: United Kingdom | F193: Birmingham | G193: Non-Profit | H193: Direct | I193: N. Brown | J193: Monitors | K193: MON-7511 | L193: 446.69 | M193: 967.25 | N193: 0.094 | O193: 10
A194: ORD-2024-212990 | B194: 45516 | C194: 45538 | D194: Americas | E194: USA | F194: Austin | G194: Consumer | H194: Distributor | I194: I. Johnson | J194: Laptops | K194: LAP-7979 | L194: 797.8 | M194: 886.22 | N194: 0.236 | O194: 36
A195: ORD-2023-925146 | B195: 45214 | C195: 45243 | D195: Asia | E195: China | F195: Shenzhen | G195: Non-Profit | H195: Distributor | I195: J. Njeri | J195: Printers | K195: PRN-4983 | L195: 986.44 | M195: 790.61 | N195: 0.072 | O195: 6
A196: ORD-2023-177794 | B196: 45050 | C196: 45072 | D196: Americas | E196: USA | F196: San Francisco | G196: Enterprise | H196: Online | I196: J. Njeri | J196: Networking | K196: NET-5941 | L196: 249.71 | M196: 361.33 | N196: 0.094 | O196: 12
A197: ORD-2024-444710 | B197: 45557 | C197: 45566 | D197: Americas | E197: Brazil | F197: São Paulo | G197: Non-Profit | H197: Online | I197: K. Singh | J197: Monitors | K197: MON-6341 | L197: 1378.8 | M197: 1952.04 | N197: 0.159 | O197: 19
A198: ORD-2024-668926 | B198: 45588 | C198: 45610 | D198: Asia | E198: Japan | F198: Osaka | G198: Non-Profit | H198: Direct | I198: B. Chen | J198: Phones | K198: PHN-9789 | L198: 1406.4 | M198: 1564.76 | N198: 0.185 | O198: 17
A199: ORD-2024-968374 | B199: 45333 | C199: 45354 | D199: Africa | E199: Kenya | F199: Kisumu | G199: Enterprise | H199: Online | I199: B. Chen | J199: Phones | K199: PHN-5082 | L199: 516.86 | M199: 852.54 | N199: 0.051 | O199: 14
A200: ORD-2023-575584 | B200: 44956 | C200: 44978 | D200: Europe | E200: Germany | F200: Munich | G200: Small Business | H200: Marketplace | I200: G. Dubois | J200: Networking | K200: NET-3460 | L200: 1142.88 | M200: 1465.29 | N200: 0.186 | O200: 7
... A236: ORD-2023-946143 | B236: 44999 | C236: 45015 | D236: Africa | E236: South Africa | F236: Cape Town | G236: Consumer | H236: Distributor | I236: K. Singh | J236: Components | K236: CMP-8230 | L236: 1309.77 | M236: 1589.07 | N236: 0.102 | O236: 10
A237: ORD-2024-281211 | B237: 45302 | C237: 45324 | D237: Asia | E237: Japan | F237: Nagoya | G237: Small Business | H237: Online | J237: Printers | K237: PRN-7816 | L237: 1237.68 | M237: 1432.8 | N237: 0.068 | O237: 13
A238: ORD-2024-805860 | B238: 45548 | C238: 45567 | D238: Africa | E238: Kenya | F238: Mombasa | G238: Small Business | H238: Retail | I238: M. Rossi | J238: Phones | K238: PHN-8804 | L238: 1338.99 | M238: 1765.76 | N238: 0.126 | O238: 24
A239: ORD-2025-132174 | B239: 45855 | C239: 45861 | D239: Americas | E239: Canada | F239: Vancouver | G239: Consumer | H239: Online | I239: H. Kim | J239: Components | K239: CMP-8851 | L239: 1364.89 | M239: 2757.54 | N239: 0.172 | O239: 61
A240: ORD-2023-964434 | B240: 45258 | C240: 45267 | D240: Asia | E240: India | F240: Delhi | G240: Enterprise | H240: Marketplace | I240: L. Okafor | J240: Phones | K240: PHN-2447 | L240: 699.33 | M240: 873.75 | N240: 0.235 | O240: 10
A241: ORD-2024-897622 | B241: 45381 | C241: 45406 | D241: Americas | E241: USA | F241: Austin | G241: Non-Profit | H241: Online | I241: G. Dubois | J241: Laptops | K241: LAP-2846 | L241: 160.82 | M241: 258.52 | N241: 0.13 | O241: 17
A242: ORD-2023-517216 | B242: 45188 | C242: 45207 | D242: Asia | E242: India | F242: Bengaluru | G242: Education | H242: Direct | I242: J. Njeri | J242: Printers | K242: PRN-5005 | L242: 385.32 | M242: 606.76 | N242: 0.086 | O242: 8
A243: ORD-2025-509940 | B243: 45793 | C243: 45804 | D243: Asia | E243: China | F243: Beijing | G243: Enterprise | H243: Online | I243: F. Müller | J243: Phones | K243: PHN-3800 | L243: 918.12 | M243: 1337.69 | N243: 0.095 | O243: 8
A244: ORD-2025-646342 | B244: 45871 | C244: 45877 | D244: Asia | E244: Japan | F244: Osaka | G244: Consumer | H244: Direct | I244: N. Brown | J244: Laptops | K244: LAP-4828 | L244: 1225.94 | M244: 1793.08 | N244: 0.136 | O244: 22
A245: ORD-2024-866535 | B245: 45630 | C245: 45638 | D245: Europe | E245: Germany | F245: Frankfurt | G245: Enterprise | H245: Marketplace | I245: B. Chen | J245: Printers | K245: PRN-5492 | L245: 72.06 | M245: 122.74 | N245: 0.238 | O245: 8
A246: ORD-2023-747341 | B246: 45035 | C246: 45044 | D246: Americas | E246: Brazil | F246: Rio de Janeiro | G246: Corporate | H246: Distributor | I246: M. Rossi | J246: Phones | K246: PHN-7132 | L246: 1013.54 | M246: 927.93 | N246: 0.175 | O246: 16
...

Sheet Brief
A1: Assignment
A2: Excel Mastery Assignment: Sales Operations & Analytics
A4: Overview:
A5: You are an analyst for a multi-regional electronics distributor. The 'Data' sheet contains 632 rows and 15 columns of transactional data with intentional data-quality issues.
A6: Your job is to clean, enrich, analyze, and present insights via a dynamic dashboard.
A8: Part A — Data Cleaning & Preparation:
A9: 1) Create a staging table where you:
A10: • Remove exact duplicate rows (define and document your duplicate criteria).
A11: • Fix data types (dates as Dates, numeric fields as numbers).
A12: • Handle missing values for City, Salesperson, and Channel using reasonable business logic (document your approach).
A13: • Flag and correct suspicious UnitPrice values (e.g., negative prices) and discounts (e.g., > 30%).
A14: • Ensure RequiredDate is not earlier than OrderDate; where it is, impute a corrected RequiredDate (explain your rule).
... A67: 15) Ensure your dashboard responds to slicers without broken references.

Sheet Staging_Table(Part A(1))
A1: OrderID | B1: Duplicate | C1: OrderDate | D1: RequiredDate | E1: FlaggedRequiredDate | F1: FixedRequiredDate | G1: LeadTimeDays | H1: Region | I1: Country | J1: City | K1: FixedCity | L1: CustomerSegment | M1: Channel | N1: FixedChannel | O1: Salesperson | P1: FixedSalesperson | Q1: ProductCategory | R1: SKU | S1: UnitCost | T1: UnitPrice | U1: AbsoluteUnitPrice | V1: DiscountPct | W1: Discount Fixed | X1: Quantity
A2: ORD-2023-723587 | B2: =IF(COUNTIF($A$2:A2,A2)=1,"Original","Duplicate") -> Original | C2: 44928 | D2: 44931 | E2: =IF(D2<C2,"Invalid","Valid") -> Valid | F2: =IF(D2>C2,D2,WORKDAY(C2,5)) -> 44931 | G2: =F2-C2 -> 3 | H2: Americas | I2: Canada | J2: Toronto | K2: =IF(J2="", "Unknown", J2) -> Toronto | L2: Corporate | M2: Distributor | N2: =IF(M2="", "Unknown", M2) -> Distributor | O2: B. Chen | P2: =IF(O2="","Unassigned",O2) -> B. Chen | Q2: Laptops | R2: LAP-8555 | S2: 315.87 | T2: 591.68 | U2: =IF(T2>0,T2,S2*1.2) -> 591.68 | V2: 0 | W2: =IF(V2<0.3,V2,0.3) -> 0 | X2: 7
A3: ORD-2023-689428 | B3: =IF(COUNTIF($A$2:A3,A3)=1,"Original","Duplicate") -> Original | C3: 44933 | D3: 44956 | E3: =IF(D3<C3,"Invalid","Valid") -> Valid | F3: =IF(D3>C3,D3,WORKDAY(C3,5)) -> 44956 | G3: =F3-C3 -> 23 | H3: Africa | I3: South Africa | J3: Cape Town | K3: =IF(J3="", "Unknown", J3) -> Cape Town | L3: Consumer | M3: Online | N3: =IF(M3="", "Unknown", M3) -> Online | O3: A. Patel | P3: =IF(O3="","Unassigned",O3) -> A. Patel | Q3: Printers | R3: PRN-4787 | S3: 299.02 | T3: 724.7 | U3: =IF(T3>0,T3,S3*1.2) -> 724.7 | V3: 0.14 | W3: =IF(V3<0.3,V3,0.3) -> 0.14 | X3: 5
A4: ORD-2023-884192 | B4: =IF(COUNTIF($A$2:A4,A4)=1,"Original","Duplicate") -> Original | C4: 44936 | D4: 44955 | E4: =IF(D4<C4,"Invalid","Valid") -> Valid | F4: =IF(D4>C4,D4,WORKDAY(C4,5)) -> 44955 | G4: =F4-C4 -> 19 | H4: Europe | I4: France | J4: Lyon | K4: =IF(J4="", "Unknown", J4) -> Lyon | L4: Non-Profit | M4: Direct | N4: =IF(M4="", "Unknown", M4) -> Direct | O4: D. Smith | P4: =IF(O4="","Unassigned",O4) -> D. Smith | Q4: Laptops | R4: LAP-4551 | S4: 401.66 | T4: 772.09 | U4: =IF(T4>0,T4,S4*1.2) -> 772.09 | V4: 0.089 | W4: =IF(V4<0.3,V4,0.3) -> 0.089 | X4: 14
A5: ORD-2023-700699 | B5: =IF(COUNTIF($A$2:A5,A5)=1,"Original","Duplicate") -> Original | C5: 44938 | D5: 44952 | E5: =IF(D5<C5,"Invalid","Valid") -> Valid | F5: =IF(D5>C5,D5,WORKDAY(C5,5)) -> 44952 | G5: =F5-C5 -> 14 | H5: Asia | I5: China | J5: Shenzhen | K5: =IF(J5="", "Unknown", J5) -> Shenzhen | L5: Non-Profit | M5: Retail | N5: =IF(M5="", "Unknown", M5) -> Retail | O5: M. Rossi | P5: =IF(O5="","Unassigned",O5) -> M. Rossi | Q5: Printers | R5: PRN-1641 | S5: 1083.09 | T5: 1425.87 | U5: =IF(T5>0,T5,S5*1.2) -> 1425.87 | V5: 0 | W5: =IF(V5<0.3,V5,0.3) -> 0 | X5: 8
A6: ORD-2023-382017 | B6: =IF(COUNTIF($A$2:A6,A6)=1,"Original","Duplicate") -> Original | C6: 44939 | D6: 44945 | E6: =IF(D6<C6,"Invalid","Valid") -> Valid | F6: =IF(D6>C6,D6,WORKDAY(C6,5)) -> 44945 | G6: =F6-C6 -> 6 | H6: Americas | I6: USA | J6: Chicago | K6: =IF(J6="", "Unknown", J6) -> Chicago | L6: Corporate | M6: Direct | N6: =IF(M6="", "Unknown", M6) -> Direct | O6: H. Kim | P6: =IF(O6="","Unassigned",O6) -> H. Kim | Q6: Phones | R6: PHN-3159 | S6: 833.57 | T6: 881.57 | U6: =IF(T6>0,T6,S6*1.2) -> 881.57 | V6: 0.057 | W6: =IF(V6<0.3,V6,0.3) -> 0.057 | X6: 18
A7: ORD-2023-112666 | B7: =IF(COUNTIF($A$2:A7,A7)=1,"Original","Duplicate") -> Original | C7: 44941 | D7: 44939 | E7: =IF(D7<C7,"Invalid","Valid") -> Invalid | F7: =IF(D7>C7,D7,WORKDAY(C7,5)) -> 44946 | G7: =F7-C7 -> 5 | H7: Africa | I7: Nigeria | J7: Abuja | K7: =IF(J7="", "Unknown", J7) -> Abuja | L7: Education | M7: Online | N7: =IF(M7="", "Unknown", M7) -> Online | O7: O. Wang | P7: =IF(O7="","Unassigned",O7) -> O. Wang | Q7: Printers | R7: PRN-6276 | S7: 28.38 | T7: 47.22 | U7: =IF(T7>0,T7,S7*1.2) -> 47.22 | V7: 0.194 | W7: =IF(V7<0.3,V7,0.3) -> 0.194 | X7: 18
A8: ORD-2023-780206 | B8: =IF(COUNTIF($A$2:A8,A8)=1,"Original","Duplicate") -> Original | C8: 44945 | D8: 44960 | E8: =IF(D8<C8,"Invalid","Valid") -> Valid | F8: =IF(D8>C8,D8,WORKDAY(C8,5)) -> 44960 | G8: =F8-C8 -> 15 | H8: Europe | I8: United Kingdom | J8: London | K8: =IF(J8="", "Unknown", J8) -> London | L8: Enterprise | M8: Distributor | N8: =IF(M8="", "Unknown", M8) -> Distributor | O8: G. Dubois | P8: =IF(O8="","Unassigned",O8) -> G. Dubois | Q8: Accessories | R8: ACC-3645 | S8: 873.06 | T8: 2101.55 | U8: =IF(T8>0,T8,S8*1.2) -> 2101.55 | V8: 0.066 | W8: =IF(V8<0.3,V8,0.3) -> 0.066 | X8: 10
A9: ORD-2023-586275 | B9: =IF(COUNTIF($A$2:A9,A9)=1,"Original","Duplicate") -> Original | C9: 44946 | D9: 44960 | E9: =IF(D9<C9,"Invalid","Valid") -> Valid | F9: =IF(D9>C9,D9,WORKDAY(C9,5)) -> 44960 | G9: =F9-C9 -> 14 | H9: Africa | I9: Kenya | J9: Kisumu | K9: =IF(J9="", "Unknown", J9) -> Kisumu | L9: Corporate | M9: Retail | N9: =IF(M9="", "Unknown", M9) -> Retail | O9: M. Rossi | P9: =IF(O9="","Unassigned",O9) -> M. Rossi | Q9: Networking | R9: NET-6036 | S9: 884.36 | T9: 1545.34 | U9: =IF(T9>0,T9,S9*1.2) -> 1545.34 | V9: 0.243 | W9: =IF(V9<0.3,V9,0.3) -> 0.243 | X9: 41
A10: ORD-2023-521818 | B10: =IF(COUNTIF($A$2:A10,A10)=1,"Original","Duplicate") -> Original | C10: 44948 | D10: 44956 | E10: =IF(D10<C10,"Invalid","Valid") -> Valid | F10: =IF(D10>C10,D10,WORKDAY(C10,5)) -> 44956 | G10: =F10-C10 -> 8 | H10: Americas | I10: USA | J10: San Francisco | K10: =IF(J10="", "Unknown", J10) -> San Francisco | L10: Small Business | M10: Online | N10: =IF(M10="", "Unknown", M10) -> Online | O10: A. Patel | P10: =IF(O10="","Unassigned",O10) -> A. Patel | Q10: Networking | R10: NET-4155 | S10: 413.52 | T10: 1004.34 | U10: =IF(T10>0,T10,S10*1.2) -> 1004.34 | V10: 0.111 | W10: =IF(V10<0.3,V10,0.3) -> 0.111 | X10: 18
A11: ORD-2023-613317 | B11: =IF(COUNTIF($A$2:A11,A11)=1,"Original","Duplicate") -> Original | C11: 44948 | D11: 44947 | E11: =IF(D11<C11,"Invalid","Valid") -> Invalid | F11: =IF(D11>C11,D11,WORKDAY(C11,5)) -> 44953 | G11: =F11-C11 -> 5 | H11: Europe | I11: Germany | J11: Munich | K11: =IF(J11="", "Unknown", J11) -> Munich | L11: Corporate | M11: Direct | N11: =IF(M11="", "Unknown", M11) -> Direct | O11: F. Müller | P11: =IF(O11="","Unassigned",O11) -> F. Müller | Q11: Monitors | R11: MON-2537 | S11: 150.86 | T11: 346.96 | U11: =IF(T11>0,T11,S11*1.2) -> 346.96 | V11: 0.196 | W11: =IF(V11<0.3,V11,0.3) -> 0.196 | X11: 8
A12: ORD-2023-811823 | B12: =IF(COUNTIF($A$2:A12,A12)=1,"Original","Duplicate") -> Original | C12: 44952 | D12: 44972 | E12: =IF(D12<C12,"Invalid","Valid") -> Valid | F12: =IF(D12>C12,D12,WORKDAY(C12,5)) -> 44972 | G12: =F12-C12 -> 20 | H12: Europe | I12: Germany | J12: Berlin | K12: =IF(J12="", "Unknown", J12) -> Berlin | L12: Small Business | M12: Online | N12: =IF(M12="", "Unknown", M12) -> Online | O12: O. Wang | P12: =IF(O12="","Unassigned",O12) -> O. Wang | Q12: Networking | R12: NET-8787 | S12: 492.62 | T12: 366.7 | U12: =IF(T12>0,T12,S12*1.2) -> 366.7 | V12: 0.089 | W12: =IF(V12<0.3,V12,0.3) -> 0.089 | X12: 10
A13: ORD-2023-430904 | B13: =IF(COUNTIF($A$2:A13,A13)=1,"Original","Duplicate") -> Original | C13: 44953 | D13: 44957 | E13: =IF(D13<C13,"Invalid","Valid") -> Valid | F13: =IF(D13>C13,D13,WORKDAY(C13,5)) -> 44957 | G13: =F13-C13 -> 4 | H13: Europe | I13: United Kingdom | J13: Manchester | K13: =IF(J13="", "Unknown", J13) -> Manchester | L13: Enterprise | M13: Online | N13: =IF(M13="", "Unknown", M13) -> Online | O13: N. Brown | P13: =IF(O13="","Unassigned",O13) -> N. Brown | Q13: Laptops | R13: LAP-9782 | S13: 941.2 | T13: 668.02 | U13: =IF(T13>0,T13,S13*1.2) -> 668.02 | V13: 0.22 | W13: =IF(V13<0.3,V13,0.3) -> 0.22 | X13: 16
... A128: ORD-2023-292714 | B128: =IF(COUNTIF($A$2:A128,A128)=1,"Original","Duplicate") -> Original | C128: 45117 | D128: 45139 | E128: =IF(D128<C128,"Invalid","Valid") -> Valid | F128: =IF(D128>C128,D128,WORKDAY(C128,5)) -> 45139 | G128: =F128-C128 -> 22 | H128: Europe | I128: France | J128: Marseille | K128: =IF(J128="", "Unknown", J128) -> Marseille | L128: Consumer | M128: Marketplace | N128: =IF(M128="", "Unknown", M128) -> Marketplace | O128: B. Chen | P128: =IF(O128="","Unassigned",O128) -> B. Chen | Q128: Printers | R128: PRN-1504 | S128: 1303.56 | T128: 1791.37 | U128: =IF(T128>0,T128,S128*1.2) -> 1791.37 | V128: 0.126 | W128: =IF(V128<0.3,V128,0.3) -> 0.126 | X128: 22
A129: ORD-2023-825084 | B129: =IF(COUNTIF($A$2:A129,A129)=1,"Original","Duplicate") -> Original | C129: 45121 | D129: 45128 | E129: =IF(D129<C129,"Invalid","Valid") -> Valid | F129: =IF(D129>C129,D129,WORKDAY(C129,5)) -> 45128 | G129: =F129-C129 -> 7 | H129: Africa | I129: South Africa | J129: Durban | K129: =IF(J129="", "Unknown", J129) -> Durban | L129: Enterprise | M129: Marketplace | N129: =IF(M129="", "Unknown", M129) -> Marketplace | P129: =IF(O129="","Unassigned",O129) -> Unassigned | Q129: Monitors | R129: MON-1018 | S129: 620.74 | T129: 1330.07 | U129: =IF(T129>0,T129,S129*1.2) -> 1330.07 | V129: 0.299 | W129: =IF(V129<0.3,V129,0.3) -> 0.299 | X129: 28
A130: ORD-2023-479747 | B130: =IF(COUNTIF($A$2:A130,A130)=1,"Original","Duplicate") -> Original | C130: 45121 | D130: 45121 | E130: =IF(D130<C130,"Invalid","Valid") -> Valid | F130: =IF(D130>C130,D130,WORKDAY(C130,5)) -> 45128 | G130: =F130-C130 -> 7 | H130: Africa | I130: Nigeria | J130: Lagos | K130: =IF(J130="", "Unknown", J130) -> Lagos | L130: Education | M130: Retail | N130: =IF(M130="", "Unknown", M130) -> Retail | O130: I. Johnson | P130: =IF(O130="","Unassigned",O130) -> I. Johnson | Q130: Accessories | R130: ACC-5334 | S130: 956.38 | T130: 1454.22 | U130: =IF(T130>0,T130,S130*1.2) -> 1454.22 | V130: 0.039 | W130: =IF(V130<0.3,V130,0.3) -> 0.039 | X130: 19
A131: ORD-2023-569862 | B131: =IF(COUNTIF($A$2:A131,A131)=1,"Original","Duplicate") -> Original | C131: 45123 | D131: 45151 | E131: =IF(D131<C131,"Invalid","Valid") -> Valid | F131: =IF(D131>C131,D131,WORKDAY(C131,5)) -> 45151 | G131: =F131-C131 -> 28 | H131: Europe | I131: United Kingdom | J131: Manchester | K131: =IF(J131="", "Unknown", J131) -> Manchester | L131: Non-Profit | M131: Online | N131: =IF(M131="", "Unknown", M131) -> Online | O131: J. Njeri | P131: =IF(O131="","Unassigned",O131) -> J. Njeri | Q131: Laptops | R131: LAP-1178 | S131: 1039.03 | T131: 2545.81 | U131: =IF(T131>0,T131,S131*1.2) -> 2545.81 | V131: 0.216 | W131: =IF(V131<0.3,V131,0.3) -> 0.216 | X131: 21
A132: ORD-2023-369150 | B132: =IF(COUNTIF($A$2:A132,A132)=1,"Original","Duplicate") -> Original | C132: 45125 | D132: 45148 | E132: =IF(D132<C132,"Invalid","Valid") -> Valid | F132: =IF(D132>C132,D132,WORKDAY(C132,5)) -> 45148 | G132: =F132-C132 -> 23 | H132: Africa | I132: South Africa | J132: Johannesburg | K132: =IF(J132="", "Unknown", J132) -> Johannesburg | L132: Small Business | M132: Retail | N132: =IF(M132="", "Unknown", M132) -> Retail | O132: L. Okafor | P132: =IF(O132="","Unassigned",O132) -> L. Okafor | Q132: Components | R132: CMP-8659 | S132: 1271.56 | T132: 995.47 | U132: =IF(T132>0,T132,S132*1.2) -> 995.47 | V132: 0.192 | W132: =IF(V132<0.3,V132,0.3) -> 0.192 | X132: 13
A133: ORD-2023-594700 | B133: =IF(COUNTIF($A$2:A133,A133)=1,"Original","Duplicate") -> Original | C133: 45125 | D133: 45129 | E133: =IF(D133<C133,"Invalid","Valid") -> Valid | F133: =IF(D133>C133,D133,WORKDAY(C133,5)) -> 45129 | G133: =F133-C133 -> 4 | H133: Americas | I133: Brazil | J133: São Paulo | K133: =IF(J133="", "Unknown", J133) -> São Paulo | L133: Consumer | M133: Direct | N133: =IF(M133="", "Unknown", M133) -> Direct | O133: F. Müller | P133: =IF(O133="","Unassigned",O133) -> F. Müller | Q133: Networking | R133: NET-1699 | S133: 1269.55 | T133: 2071.1 | U133: =IF(T133>0,T133,S133*1.2) -> 2071.1 | V133: 0.129 | W133: =IF(V133<0.3,V133,0.3) -> 0.129 | X133: 22
A134: ORD-2023-825836 | B134: =IF(COUNTIF($A$2:A134,A134)=1,"Original","Duplicate") -> Original | C134: 45126 | D134: 45138 | E134: =IF(D134<C134,"Invalid","Valid") -> Valid | F134: =IF(D134>C134,D134,WORKDAY(C134,5)) -> 45138 | G134: =F134-C134 -> 12 | H134: Americas | I134: Brazil | J134: Rio de Janeiro | K134: =IF(J134="", "Unknown", J134) -> Rio de Janeiro | L134: Corporate | M134: Retail | N134: =IF(M134="", "Unknown", M134) -> Retail | O134: C. Otieno | P134: =IF(O134="","Unassigned",O134) -> C. Otieno | Q134: Monitors | R134: MON-7869 | S134: 1334.64 | T134: 2273.42 | U134: =IF(T134>0,T134,S134*1.2) -> 2273.42 | V134: 0.118 | W134: =IF(V134<0.3,V134,0.3) -> 0.118 | X134: 14
A135: ORD-2023-109927 | B135: =IF(COUNTIF($A$2:A135,A135)=1,"Original","Duplicate") -> Original | C135: 45129 | D135: 45128 | E135: =IF(D135<C135,"Invalid","Valid") -> Invalid | F135: =IF(D135>C135,D135,WORKDAY(C135,5)) -> 45135 | G135: =F135-C135 -> 6 | H135: Asia | I135: India | J135: Delhi | K135: =IF(J135="", "Unknown", J135) -> Delhi | L135: Small Business | M135: Distributor | N135: =IF(M135="", "Unknown", M135) -> Distributor | O135: E. Garcia | P135: =IF(O135="","Unassigned",O135) -> E. Garcia | Q135: Printers | R135: PRN-2301 | S135: 946.99 | T135: 2132.19 | U135: =IF(T135>0,T135,S135*1.2) -> 2132.19 | V135: 0.165 | W135: =IF(V135<0.3,V135,0.3) -> 0.165 | X135: 7
A136: ORD-2023-369160 | B136: =IF(COUNTIF($A$2:A136,A136)=1,"Original","Duplicate") -> Original | C136: 45131 | D136: 45151 | E136: =IF(D136<C136,"Invalid","Valid") -> Valid | F136: =IF(D136>C136,D136,WORKDAY(C136,5)) -> 45151 | G136: =F136-C136 -> 20 | H136: Americas | I136: Canada | J136: Montreal | K136: =IF(J136="", "Unknown", J136) -> Montreal | L136: Education | M136: Direct | N136: =IF(M136="", "Unknown", M136) -> Direct | O136: C. Otieno | P136: =IF(O136="","Unassigned",O136) -> C. Otieno | Q136: Monitors | R136: MON-3307 | S136: 1082.38 | T136: 1766.55 | U136: =IF(T136>0,T136,S136*1.2) -> 1766.55 | V136: 0.164 | W136: =IF(V136<0.3,V136,0.3) -> 0.164 | X136: 20
A137: ORD-2023-261081 | B137: =IF(COUNTIF($A$2:A137,A137)=1,"Original","Duplicate") -> Original | C137: 45131 | D137: 45157 | E137: =IF(D137<C137,"Invalid","Valid") -> Valid | F137: =IF(D137>C137,D137,WORKDAY(C137,5)) -> 45157 | G137: =F137-C137 -> 26 | H137: Africa | I137: Kenya | J137: Nairobi | K137: =IF(J137="", "Unknown", J137) -> Nairobi | L137: Enterprise | M137: Distributor | N137: =IF(M137="", "Unknown", M137) -> Distributor | O137: M. Rossi | P137: =IF(O137="","Unassigned",O137) -> M. Rossi | Q137: Accessories | R137: ACC-1238 | S137: 661.45 | T137: 1634.86 | U137: =IF(T137>0,T137,S137*1.2) -> 1634.86 | V137: 0.565 | W137: =IF(V137<0.3,V137,0.3) -> 0.3 | X137: 24
A138: ORD-2023-660608 | B138: =IF(COUNTIF($A$2:A138,A138)=1,"Original","Duplicate") -> Original | C138: 45132 | D138: 45148 | E138: =IF(D138<C138,"Invalid","Valid") -> Valid | F138: =IF(D138>C138,D138,WORKDAY(C138,5)) -> 45148 | G138: =F138-C138 -> 16 | H138: Africa | I138: Nigeria | J138: Port Harcourt | K138: =IF(J138="", "Unknown", J138) -> Port Harcourt | L138: Corporate | M138: Distributor | N138: =IF(M138="", "Unknown", M138) -> Distributor | O138: I. Johnson | P138: =IF(O138="","Unassigned",O138) -> I. Johnson | Q138: Accessories | R138: ACC-8178 | S138: 506.83 | T138: 441.74 | U138: =IF(T138>0,T138,S138*1.2) -> 441.74 | V138: 0.24 | W138: =IF(V138<0.3,V138,0.3) -> 0.24 | X138: 9
A139: ORD-2023-912395 | B139: =IF(COUNTIF($A$2:A139,A139)=1,"Original","Duplicate") -> Original | C139: 45133 | D139: 45163 | E139: =IF(D139<C139,"Invalid","Valid") -> Valid | F139: =IF(D139>C139,D139,WORKDAY(C139,5)) -> 45163 | G139: =F139-C139 -> 30 | H139: Americas | I139: USA | J139: New York | K139: =IF(J139="", "Unknown", J139) -> New York | L139: Consumer | M139: Retail | N139: =IF(M139="", "Unknown", M139) -> Retail | O139: M. Rossi | P139: =IF(O139="","Unassigned",O139) -> M. Rossi | Q139: Accessories | R139: ACC-7078 | S139: 1261.48 | T139: 1643.18 | U139: =IF(T139>0,T139,S139*1.2) -> 1643.18 | V139: 0.151 | W139: =IF(V139<0.3,V139,0.3) -> 0.151 | X139: 23
A140: ORD-2023-290237 | B140: =IF(COUNTIF($A$2:A140,A140)=1,"Original","Duplicate") -> Original | C140: 45137 | D140: 45145 | E140: =IF(D140<C140,"Invalid","Valid") -> Valid | F140: =IF(D140>C140,D140,WORKDAY(C140,5)) -> 45145 | G140: =F140-C140 -> 8 | H140: Asia | I140: Japan | J140: Nagoya | K140: =IF(J140="", "Unknown", J140) -> Nagoya | L140: Education | M140: Marketplace | N140: =IF(M140="", "Unknown", M140) -> Marketplace | O140: A. Patel | P140: =IF(O140="","Unassigned",O140) -> A. Patel | Q140: Networking | R140: NET-1645 | S140: 1352.44 | T140: 2698.01 | U140: =IF(T140>0,T140,S140*1.2) -> 2698.01 | V140: 0.131 | W140: =IF(V140<0.3,V140,0.3) -> 0.131 | X140: 13
A141: ORD-2023-451931 | B141: =IF(COUNTIF($A$2:A141,A141)=1,"Original","Duplicate") -> Original | C141: 45137 | D141: 45157 | E141: =IF(D141<C141,"Invalid","Valid") -> Valid | F141: =IF(D141>C141,D141,WORKDAY(C141,5)) -> 45157 | G141: =F141-C141 -> 20 | H141: Europe | I141: France | J141: Paris | K141: =IF(J141="", "Unknown", J141) -> Paris | L141: Enterprise | M141: Marketplace | N141: =IF(M141="", "Unknown", M141) -> Marketplace | O141: G. Dubois | P141: =IF(O141="","Unassigned",O141) -> G. Dubois | Q141: Networking | R141: NET-5423 | S141: 1418.51 | T141: 2789.61 | U141: =IF(T141>0,T141,S141*1.2) -> 2789.61 | V141: 0.171 | W141: =IF(V141<0.3,V141,0.3) -> 0.171 | X141: 8
... A145: ORD-2023-548934 | B145: =IF(COUNTIF($A$2:A145,A145)=1,"Original","Duplicate") -> Original | C145: 45141 | D145: 45168 | E145: =IF(D145<C145,"Invalid","Valid") -> Valid | F145: =IF(D145>C145,D145,WORKDAY(C145,5)) -> 45168 | G145: =F145-C145 -> 27 | H145: Asia | I145: China | J145: Shanghai | K145: =IF(J145="", "Unknown", J145) -> Shanghai | L145: Consumer | M145: Distributor | N145: =IF(M145="", "Unknown", M145) -> Distributor | O145: N. Brown | P145: =IF(O145="","Unassigned",O145) -> N. Brown | Q145: Monitors | R145: MON-3773 | S145: 226.04 | T145: 545.72 | U145: =IF(T145>0,T145,S145*1.2) -> 545.72 | V145: 0.151 | W145: =IF(V145<0.3,V145,0.3) -> 0.151 | X145: 11
A146: ORD-2023-630430 | B146: =IF(COUNTIF($A$2:A146,A146)=1,"Original","Duplicate") -> Original | C146: 45142 | D146: 45162 | E146: =IF(D146<C146,"Invalid","Valid") -> Valid | F146: =IF(D146>C146,D146,WORKDAY(C146,5)) -> 45162 | G146: =F146-C146 -> 20 | H146: Americas | I146: Brazil | J146: Brasília | K146: =IF(J146="", "Unknown", J146) -> Brasília | L146: Non-Profit | M146: Direct | N146: =IF(M146="", "Unknown", M146) -> Direct | P146: =IF(O146="","Unassigned",O146) -> Unassigned | Q146: Networking | R146: NET-9125 | S146: 582.88 | T146: 1044.14 | U146: =IF(T146>0,T146,S146*1.2) -> 1044.14 | V146: 0.216 | W146: =IF(V146<0.3,V146,0.3) -> 0.216 | X146: 10
A147: ORD-2023-197661 | B147: =IF(COUNTIF($A$2:A147,A147)=1,"Original","Duplicate") -> Original | C147: 45146 | D147: 45160 | E147: =IF(D147<C147,"Invalid","Valid") -> Valid | F147: =IF(D147>C147,D147,WORKDAY(C147,5)) -> 45160 | G147: =F147-C147 -> 14 | H147: Europe | I147: United Kingdom | J147: Birmingham | K147: =IF(J147="", "Unknown", J147) -> Birmingham | L147: Non-Profit | M147: Direct | N147: =IF(M147="", "Unknown", M147) -> Direct | O147: N. Brown | P147: =IF(O147="","Unassigned",O147) -> N. Brown | Q147: Monitors | R147: MON-7511 | S147: 446.69 | T147: 967.25 | U147: =IF(T147>0,T147,S147*1.2) -> 967.25 | V147: 0.094 | W147: =IF(V147<0.3,V147,0.3) -> 0.094 | X147: 10
A148: ORD-2023-867175 | B148: =IF(COUNTIF($A$2:A148,A148)=1,"Original","Duplicate") -> Original | C148: 45148 | D148: 45153 | E148: =IF(D148<C148,"Invalid","Valid") -> Valid | F148: =IF(D148>C148,D148,WORKDAY(C148,5)) -> 45153 | G148: =F148-C148 -> 5 | H148: Americas | I148: Brazil | J148: São Paulo | K148: =IF(J148="", "Unknown", J148) -> São Paulo | L148: Education | M148: Direct | N148: =IF(M148="", "Unknown", M148) -> Direct | O148: G. Dubois | P148: =IF(O148="","Unassigned",O148) -> G. Dubois | Q148: Networking | R148: NET-2894 | S148: 1307.52 | T148: 1921.65 | U148: =IF(T148>0,T148,S148*1.2) -> 1921.65 | V148: 0.123 | W148: =IF(V148<0.3,V148,0.3) -> 0.123 | X148: 13
A149: ORD-2023-883066 | B149: =IF(COUNTIF($A$2:A149,A149)=1,"Original","Duplicate") -> Original | C149: 45150 | D149: 45175 | E149: =IF(D149<C149,"Invalid","Valid") -> Valid | F149: =IF(D149>C149,D149,WORKDAY(C149,5)) -> 45175 | G149: =F149-C149 -> 25 | H149: Asia | I149: China | J149: Shanghai | K149: =IF(J149="", "Unknown", J149) -> Shanghai | L149: Small Business | M149: Retail | N149: =IF(M149="", "Unknown", M149) -> Retail | O149: B. Chen | P149: =IF(O149="","Unassigned",O149) -> B. Chen | Q149: Components | R149: CMP-6352 | S149: 950.77 | T149: 694.78 | U149: =IF(T149>0,T149,S149*1.2) -> 694.78 | V149: 0.084 | W149: =IF(V149<0.3,V149,0.3) -> 0.084 | X149: 14
A150: ORD-2023-133848 | B150: =IF(COUNTIF($A$2:A150,A150)=1,"Original","Duplicate") -> Original | C150: 45153 | D150: 45176 | E150: =IF(D150<C150,"Invalid","Valid") -> Valid | F150: =IF(D150>C150,D150,WORKDAY(C150,5)) -> 45176 | G150: =F150-C150 -> 23 | H150: Americas | I150: USA | J150: New York | K150: =IF(J150="", "Unknown", J150) -> New York | L150: Enterprise | M150: Online | N150: =IF(M150="", "Unknown", M150) -> Online | O150: K. Singh | P150: =IF(O150="","Unassigned",O150) -> K. Singh | Q150: Phones | R150: PHN-2013 | S150: 590.33 | T150: 973.04 | U150: =IF(T150>0,T150,S150*1.2) -> 973.04 | V150: 0 | W150: =IF(V150<0.3,V150,0.3) -> 0 | X150: 26
A151: ORD-2023-274037 | B151: =IF(COUNTIF($A$2:A151,A151)=1,"Original","Duplicate") -> Original | C151: 45153 | D151: 45163 | E151: =IF(D151<C151,"Invalid","Valid") -> Valid | F151: =IF(D151>C151,D151,WORKDAY(C151,5)) -> 45163 | G151: =F151-C151 -> 10 | H151: Africa | I151: Kenya | J151: Nairobi | K151: =IF(J151="", "Unknown", J151) -> Nairobi | L151: Small Business | M151: Retail | N151: =IF(M151="", "Unknown", M151) -> Retail | O151: N. Brown | P151: =IF(O151="","Unassigned",O151) -> N. Brown | Q151: Phones | R151: PHN-1234 | S151: 91.85 | T151: 111.29 | U151: =IF(T151>0,T151,S151*1.2) -> 111.29 | V151: 0 | W151: =IF(V151<0.3,V151,0.3) -> 0 | X151: 6
A152: ORD-2023-525643 | B152: =IF(COUNTIF($A$2:A152,A152)=1,"Original","Duplicate") -> Original | C152: 45155 | D152: 45172 | E152: =IF(D152<C152,"Invalid","Valid") -> Valid | F152: =IF(D152>C152,D152,WORKDAY(C152,5)) -> 45172 | G152: =F152-C152 -> 17 | H152: Africa | I152: South Africa | J152: Durban | K152: =IF(J152="", "Unknown", J152) -> Durban | L152: Enterprise | M152: Retail | N152: =IF(M152="", "Unknown", M152) -> Retail | O152: A. Patel | P152: =IF(O152="","Unassigned",O152) -> A. Patel | Q152: Phones | R152: PHN-8072 | S152: 676.37 | T152: 1276.67 | U152: =IF(T152>0,T152,S152*1.2) -> 1276.67 | V152: 0.066 | W152: =IF(V152<0.3,V152,0.3) -> 0.066 | X152: 10
A153: ORD-2023-749324 | B153: =IF(COUNTIF($A$2:A153,A153)=1,"Original","Duplicate") -> Original | C153: 45157 | D153: 45176 | E153: =IF(D153<C153,"Invalid","Valid") -> Valid | F153: =IF(D153>C153,D153,WORKDAY(C153,5)) -> 45176 | G153: =F153-C153 -> 19 | H153: Africa | I153: South Africa | J153: Johannesburg | K153: =IF(J153="", "Unknown", J153) -> Johannesburg | L153: Enterprise | M153: Retail | N153: =IF(M153="", "Unknown", M153) -> Retail | O153: D. Smith | P153: =IF(O153="","Unassigned",O153) -> D. Smith | Q153: Monitors | R153: MON-2296 | S153: 494.61 | T153: 605.23 | U153: =IF(T153>0,T153,S153*1.2) -> 605.23 | V153: 0.204 | W153: =IF(V153<0.3,V153,0.3) -> 0.204 | X153: 18
A154: ORD-2023-343322 | B154: =IF(COUNTIF($A$2:A154,A154)=1,"Original","Duplicate") -> Original | C154: 45157 | D154: 45181 | E154: =IF(D154<C154,"Invalid","Valid") -> Valid | F154: =IF(D154>C154,D154,WORKDAY(C154,5)) -> 45181 | G154: =F154-C154 -> 24 | H154: Americas | I154: Canada | J154: Vancouver | K154: =IF(J154="", "Unknown", J154) -> Vancouver | L154: Enterprise | M154: Retail | N154: =IF(M154="", "Unknown", M154) -> Retail | O154: I. Johnson | P154: =IF(O154="","Unassigned",O154) -> I. Johnson | Q154: Printers | R154: PRN-9669 | S154: 1183.95 | T154: 1503.53 | U154: =IF(T154>0,T154,S154*1.2) -> 1503.53 | V154: 0.241 | W154: =IF(V154<0.3,V154,0.3) -> 0.241 | X154: 16
A155: ORD-2023-334213 | B155: =IF(COUNTIF($A$2:A155,A155)=1,"Original","Duplicate") -> Original | C155: 45157 | D155: 45161 | E155: =IF(D155<C155,"Invalid","Valid") -> Valid | F155: =IF(D155>C155,D155,WORKDAY(C155,5)) -> 45161 | G155: =F155-C155 -> 4 | H155: Africa | I155: Nigeria | J155: Abuja | K155: =IF(J155="", "Unknown", J155) -> Abuja | L155: Small Business | M155: Online | N155: =IF(M155="", "Unknown", M155) -> Online | O155: J. Njeri | P155: =IF(O155="","Unassigned",O155) -> J. Njeri | Q155: Monitors | R155: MON-5517 | S155: 790.63 | T155: 1382.31 | U155: =IF(T155>0,T155,S155*1.2) -> 1382.31 | V155: 0.101 | W155: =IF(V155<0.3,V155,0.3) -> 0.101 | X155: 7
A156: ORD-2023-603238 | B156: =IF(COUNTIF($A$2:A156,A156)=1,"Original","Duplicate") -> Original | C156: 45159 | D156: 45173 | E156: =IF(D156<C156,"Invalid","Valid") -> Valid | F156: =IF(D156>C156,D156,WORKDAY(C156,5)) -> 45173 | G156: =F156-C156 -> 14 | H156: Americas | I156: Canada | J156: Montreal | K156: =IF(J156="", "Unknown", J156) -> Montreal | L156: Education | M156: Distributor | N156: =IF(M156="", "Unknown", M156) -> Distributor | O156: F. Müller | P156: =IF(O156="","Unassigned",O156) -> F. Müller | Q156: Components | R156: CMP-2136 | S156: 178.19 | T156: 284.43 | U156: =IF(T156>0,T156,S156*1.2) -> 284.43 | V156: 0.089 | W156: =IF(V156<0.3,V156,0.3) -> 0.089 | X156: 8
A157: ORD-2023-375011 | B157: =IF(COUNTIF($A$2:A157,A157)=1,"Original","Duplicate") -> Original | C157: 45161 | D157: 45191 | E157: =IF(D157<C157,"Invalid","Valid") -> Valid | F157: =IF(D157>C157,D157,WORKDAY(C157,5)) -> 45191 | G157: =F157-C157 -> 30 | H157: Europe | I157: United Kingdom | J157: London | K157: =IF(J157="", "Unknown", J157) -> London | L157: Consumer | M157: Distributor | N157: =IF(M157="", "Unknown", M157) -> Distributor | O157: O. Wang | P157: =IF(O157="","Unassigned",O157) -> O. Wang | Q157: Accessories | R157: ACC-1492 | S157: 209.81 | T157: 523 | U157: =IF(T157>0,T157,S157*1.2) -> 523 | V157: 0.059 | W157: =IF(V157<0.3,V157,0.3) -> 0.059 | X157: 15
A158: ORD-2023-640022 | B158: =IF(COUNTIF($A$2:A158,A158)=1,"Original","Duplicate") -> Original | C158: 45162 | D158: 45189 | E158: =IF(D158<C158,"Invalid","Valid") -> Valid | F158: =IF(D158>C158,D158,WORKDAY(C158,5)) -> 45189 | G158: =F158-C158 -> 27 | H158: Africa | I158: South Africa | J158: Durban | K158: =IF(J158="", "Unknown", J158) -> Durban | L158: Small Business | M158: Marketplace | N158: =IF(M158="", "Unknown", M158) -> Marketplace | O158: M. Rossi | P158: =IF(O158="","Unassigned",O158) -> M. Rossi | Q158: Printers | R158: PRN-4732 | S158: 1399.64 | T158: 3342.11 | U158: =IF(T158>0,T158,S158*1.2) -> 3342.11 | V158: 0 | W158: =IF(V158<0.3,V158,0.3) -> 0 | X158: 10
... A171: ORD-2023-517216 | B171: =IF(COUNTIF($A$2:A171,A171)=1,"Original","Duplicate") -> Original | C171: 45188 | D171: 45207 | E171: =IF(D171<C171,"Invalid","Valid") -> Valid | F171: =IF(D171>C171,D171,WORKDAY(C171,5)) -> 45207 | G171: =F171-C171 -> 19 | H171: Asia | I171: India | J171: Bengaluru | K171: =IF(J171="", "Unknown", J171) -> Bengaluru | L171: Education | M171: Direct | N171: =IF(M171="", "Unknown", M171) -> Direct | O171: J. Njeri | P171: =IF(O171="","Unassigned",O171) -> J. Njeri | Q171: Printers | R171: PRN-5005 | S171: 385.32 | T171: 606.76 | U171: =IF(T171>0,T171,S171*1.2) -> 606.76 | V171: 0.086 | W171: =IF(V171<0.3,V171,0.3) -> 0.086 | X171: 8
A172: ORD-2023-842820 | B172: =IF(COUNTIF($A$2:A172,A172)=1,"Original","Duplicate") -> Original | C172: 45189 | D172: 45197 | E172: =IF(D172<C172,"Invalid","Valid") -> Valid | F172: =IF(D172>C172,D172,WORKDAY(C172,5)) -> 45197 | G172: =F172-C172 -> 8 | H172: Asia | I172: India | K172: =IF(J172="", "Unknown", J172) -> Unknown | L172: Corporate | N172: =IF(M172="", "Unknown", M172) -> Unknown | O172: B. Chen | P172: =IF(O172="","Unassigned",O172) -> B. Chen | Q172: Accessories | R172: ACC-1375 | S172: 1362.06 | T172: 3398.37 | U172: =IF(T172>0,T172,S172*1.2) -> 3398.37 | V172: 0.157 | W172: =IF(V172<0.3,V172,0.3) -> 0.157 | X172: 11
A173: ORD-2023-450877 | B173: =IF(COUNTIF($A$2:A173,A173)=1,"Original","Duplicate") -> Original | C173: 45190 | D173: 45209 | E173: =IF(D173<C173,"Invalid","Valid") -> Valid | F173: =IF(D173>C173,D173,WORKDAY(C173,5)) -> 45209 | G173: =F173-C173 -> 19 | H173: Asia | I173: Japan | J173: Tokyo | K173: =IF(J173="", "Unknown", J173) -> Tokyo | L173: Education | M173: Online | N173: =IF(M173="", "Unknown", M173) -> Online | O173: D. Smith | P173: =IF(O173="","Unassigned",O173) -> D. Smith | Q173: Components | R173: CMP-5211 | S173: 845.63 | T173: 2062.12 | U173: =IF(T173>0,T173,S173*1.2) -> 2062.12 | V173: 0.134 | W173: =IF(V173<0.3,V173,0.3) -> 0.134 | X173: 5
A174: ORD-2023-271918 | B174: =IF(COUNTIF($A$2:A174,A174)=1,"Original","Duplicate") -> Original | C174: 45194 | D174: 45201 | E174: =IF(D174<C174,"Invalid","Valid") -> Valid | F174: =IF(D174>C174,D174,WORKDAY(C174,5)) -> 45201 | G174: =F174-C174 -> 7 | H174: Americas | I174: USA | J174: New York | K174: =IF(J174="", "Unknown", J174) -> New York | L174: Education | M174: Marketplace | N174: =IF(M174="", "Unknown", M174) -> Marketplace | O174: I. Johnson | P174: =IF(O174="","Unassigned",O174) -> I. Johnson | Q174: Accessories | R174: ACC-3551 | S174: 145.58 | T174: 228.15 | U174: =IF(T174>0,T174,S174*1.2) -> 228.15 | V174: 0.204 | W174: =IF(V174<0.3,V174,0.3) -> 0.204 | X174: 5
A175: ORD-2023-132101 | B175: =IF(COUNTIF($A$2:A175,A175)=1,"Original","Duplicate") -> Original | C175: 45194 | D175: 45208 | E175: =IF(D175<C175,"Invalid","Valid") -> Valid | F175: =IF(D175>C175,D175,WORKDAY(C175,5)) -> 45208 | G175: =F175-C175 -> 14 | H175: Americas | I175: USA | J175: New York | K175: =IF(J175="", "Unknown", J175) -> New York | L175: Small Business | M175: Marketplace | N175: =IF(M175="", "Unknown", M175) -> Marketplace | O175: J. Njeri | P175: =IF(O175="","Unassigned",O175) -> J. Njeri | Q175: Laptops | R175: LAP-6750 | S175: 1279.56 | T175: 3083.8 | U175: =IF(T175>0,T175,S175*1.2) -> 3083.8 | V175: 0.106 | W175: =IF(V175<0.3,V175,0.3) -> 0.106 | X175: 5
A176: ORD-2023-619385 | B176: =IF(COUNTIF($A$2:A176,A176)=1,"Original","Duplicate") -> Original | C176: 45199 | D176: 45202 | E176: =IF(D176<C176,"Invalid","Valid") -> Valid | F176: =IF(D176>C176,D176,WORKDAY(C176,5)) -> 45202 | G176: =F176-C176 -> 3 | H176: Asia | I176: China | J176: Beijing | K176: =IF(J176="", "Unknown", J176) -> Beijing | L176: Non-Profit | M176: Retail | N176: =IF(M176="", "Unknown", M176) -> Retail | O176: J. Njeri | P176: =IF(O176="","Unassigned",O176) -> J. Njeri | Q176: Laptops | R176: LAP-5763 | S176: 1019.36 | T176: 972.91 | U176: =IF(T176>0,T176,S176*1.2) -> 972.91 | V176: 0.147 | W176: =IF(V176<0.3,V176,0.3) -> 0.147 | X176: 17
A177: ORD-2023-568013 | B177: =IF(COUNTIF($A$2:A177,A177)=1,"Original","Duplicate") -> Original | C177: 45199 | D177: 45229 | E177: =IF(D177<C177,"Invalid","Valid") -> Valid | F177: =IF(D177>C177,D177,WORKDAY(C177,5)) -> 45229 | G177: =F177-C177 -> 30 | H177: Asia | I177: Japan | J177: Tokyo | K177: =IF(J177="", "Unknown", J177) -> Tokyo | L177: Enterprise | M177: Online | N177: =IF(M177="", "Unknown", M177) -> Online | O177: D. Smith | P177: =IF(O177="","Unassigned",O177) -> D. Smith | Q177: Printers | R177: PRN-1786 | S177: 649.13 | T177: 975.43 | U177: =IF(T177>0,T177,S177*1.2) -> 975.43 | V177: 0.157 | W177: =IF(V177<0.3,V177,0.3) -> 0.157 | X177: 27
A178: ORD-2023-302041 | B178: =IF(COUNTIF($A$2:A178,A178)=1,"Original","Duplicate") -> Original | C178: 45203 | D178: 45228 | E178: =IF(D178<C178,"Invalid","Valid") -> Valid | F178: =IF(D178>C178,D178,WORKDAY(C178,5)) -> 45228 | G178: =F178-C178 -> 25 | H178: Americas | I178: USA | J178: San Francisco | K178: =IF(J178="", "Unknown", J178) -> San Francisco | L178: Small Business | M178: Distributor | N178: =IF(M178="", "Unknown", M178) -> Distributor | O178: O. Wang | P178: =IF(O178="","Unassigned",O178) -> O. Wang | Q178: Accessories | R178: ACC-5079 | S178: 1239.84 | T178: 1482.75 | U178: =IF(T178>0,T178,S178*1.2) -> 1482.75 | V178: 0.067 | W178: =IF(V178<0.3,V178,0.3) -> 0.067 | X178: 4
A179: ORD-2023-474313 | B179: =IF(COUNTIF($A$2:A179,A179)=1,"Original","Duplicate") -> Original | C179: 45204 | D179: 45205 | E179: =IF(D179<C179,"Invalid","Valid") -> Valid | F179: =IF(D179>C179,D179,WORKDAY(C179,5)) -> 45205 | G179: =F179-C179 -> 1 | H179: Asia | I179: India | J179: Bengaluru | K179: =IF(J179="", "Unknown", J179) -> Bengaluru | L179: Non-Profit | M179: Online | N179: =IF(M179="", "Unknown", M179) -> Online | O179: I. Johnson | P179: =IF(O179="","Unassigned",O179) -> I. Johnson | Q179: Components | R179: CMP-4807 | S179: 1470.26 | T179: 2562.55 | U179: =IF(T179>0,T179,S179*1.2) -> 2562.55 | V179: 0.173 | W179: =IF(V179<0.3,V179,0.3) -> 0.173 | X179: 9
A180: ORD-2023-166668 | B180: =IF(COUNTIF($A$2:A180,A180)=1,"Original","Duplicate") -> Original | C180: 45204 | D180: 45230 | E180: =IF(D180<C180,"Invalid","Valid") -> Valid | F180: =IF(D180>C180,D180,WORKDAY(C180,5)) -> 45230 | G180: =F180-C180 -> 26 | H180: Asia | I180: China | J180: Shanghai | K180: =IF(J180="", "Unknown", J180) -> Shanghai | L180: Consumer | N180: =IF(M180="", "Unknown", M180) -> Unknown | O180: J. Njeri | P180: =IF(O180="","Unassigned",O180) -> J. Njeri | Q180: Printers | R180: PRN-6520 | S180: 649.91 | T180: 1360.12 | U180: =IF(T180>0,T180,S180*1.2) -> 1360.12 | V180: 0.194 | W180: =IF(V180<0.3,V180,0.3) -> 0.194 | X180: 9
A181: ORD-2023-304451 | B181: =IF(COUNTIF($A$2:A181,A181)=1,"Original","Duplicate") -> Original | C181: 45206 | D181: 45222 | E181: =IF(D181<C181,"Invalid","Valid") -> Valid | F181: =IF(D181>C181,D181,WORKDAY(C181,5)) -> 45222 | G181: =F181-C181 -> 16 | H181: Asia | I181: India | J181: Hyderabad | K181: =IF(J181="", "Unknown", J181) -> Hyderabad | L181: Consumer | M181: Retail | N181: =IF(M181="", "Unknown", M181) -> Retail | O181: G. Dubois | P181: =IF(O181="","Unassigned",O181) -> G. Dubois | Q181: Monitors | R181: MON-7602 | S181: 906.81 | T181: 1395.56 | U181: =IF(T181>0,T181,S181*1.2) -> 1395.56 | V181: 0.185 | W181: =IF(V181<0.3,V181,0.3) -> 0.185 | X181: 6
A182: ORD-2023-368449 | B182: =IF(COUNTIF($A$2:A182,A182)=1,"Original","Duplicate") -> Original | C182: 45208 | D182: 45225 | E182: =IF(D182<C182,"Invalid","Valid") -> Valid | F182: =IF(D182>C182,D182,WORKDAY(C182,5)) -> 45225 | G182: =F182-C182 -> 17 | H182: Asia | I182: China | J182: Shanghai | K182: =IF(J182="", "Unknown", J182) -> Shanghai | L182: Consumer | M182: Marketplace | N182: =IF(M182="", "Unknown", M182) -> Marketplace | O182: C. Otieno | P182: =IF(O182="","Unassigned",O182) -> C. Otieno | Q182: Components | R182: CMP-2096 | S182: 1132.03 | T182: 2137.21 | U182: =IF(T182>0,T182,S182*1.2) -> 2137.21 | V182: 0.357 | W182: =IF(V182<0.3,V182,0.3) -> 0.3 | X182: 35
A183: ORD-2023-502205 | B183: =IF(COUNTIF($A$2:A183,A183)=1,"Original","Duplicate") -> Original | C183: 45208 | D183: 45210 | E183: =IF(D183<C183,"Invalid","Valid") -> Valid | F183: =IF(D183>C183,D183,WORKDAY(C183,5)) -> 45210 | G183: =F183-C183 -> 2 | H183: Africa | I183: Nigeria | J183: Port Harcourt | K183: =IF(J183="", "Unknown", J183) -> Port Harcourt | L183: Education | M183: Marketplace | N183: =IF(M183="", "Unknown", M183) -> Marketplace | O183: K. Singh | P183: =IF(O183="","Unassigned",O183) -> K. Singh | Q183: Networking | R183: NET-8856 | S183: 391.16 | T183: 902.47 | U183: =IF(T183>0,T183,S183*1.2) -> 902.47 | V183: 0.004 | W183: =IF(V183<0.3,V183,0.3) -> 0.004 | X183: 12
A184: ORD-2023-888140 | B184: =IF(COUNTIF($A$2:A184,A184)=1,"Original","Duplicate") -> Original | C184: 45210 | D184: 45212 | E184: =IF(D184<C184,"Invalid","Valid") -> Valid | F184: =IF(D184>C184,D184,WORKDAY(C184,5)) -> 45212 | G184: =F184-C184 -> 2 | H184: Americas | I184: Brazil | J184: Brasília | K184: =IF(J184="", "Unknown", J184) -> Brasília | L184: Consumer | M184: Distributor | N184: =IF(M184="", "Unknown", M184) -> Distributor | P184: =IF(O184="","Unassigned",O184) -> Unassigned | Q184: Accessories | R184: ACC-3567 | S184: 715.94 | T184: 550.07 | U184: =IF(T184>0,T184,S184*1.2) -> 550.07 | V184: 0.14 | W184: =IF(V184<0.3,V184,0.3) -> 0.14 | X184: 16
A185: ORD-2023-623293 | B185: =IF(COUNTIF($A$2:A185,A185)=1,"Original","Duplicate") -> Original | C185: 45211 | D185: 45228 | E185: =IF(D185<C185,"Invalid","Valid") -> Valid | F185: =IF(D185>C185,D185,WORKDAY(C185,5)) -> 45228 | G185: =F185-C185 -> 17 | H185: Asia | I185: Japan | J185: Nagoya | K185: =IF(J185="", "Unknown", J185) -> Nagoya | L185: Non-Profit | M185: Direct | N185: =IF(M185="", "Unknown", M185) -> Direct | O185: H. Kim | P185: =IF(O185="","Unassigned",O185) -> H. Kim | Q185: Phones | R185: PHN-8478 | S185: 1102.19 | T185: 1711.16 | U185: =IF(T185>0,T185,S185*1.2) -> 1711.16 | V185: 0.151 | W185: =IF(V185<0.3,V185,0.3) -> 0.151 | X185: 10
A186: ORD-2023-925146 | B186: =IF(COUNTIF($A$2:A186,A186)=1,"Original","Duplicate") -> Original | C186: 45214 | D186: 45243 | E186: =IF(D186<C186,"Invalid","Valid") -> Valid | F186: =IF(D186>C186,D186,WORKDAY(C186,5)) -> 45243 | G186: =F186-C186 -> 29 | H186: Asia | I186: China | J186: Shenzhen | K186: =IF(J186="", "Unknown", J186) -> Shenzhen | L186: Non-Profit | M186: Distributor | N186: =IF(M186="", "Unknown", M186) -> Distributor | O186: J. Njeri | P186: =IF(O186="","Unassigned",O186) -> J. Njeri | Q186: Printers | R186: PRN-4983 | S186: 986.44 | T186: 790.61 | U186: =IF(T186>0,T186,S186*1.2) -> 790.61 | V186: 0.072 | W186: =IF(V186<0.3,V186,0.3) -> 0.072 | X186: 6
A187: ORD-2023-378104 | B187: =IF(COUNTIF($A$2:A187,A187)=1,"Original","Duplicate") -> Original | C187: 45217 | D187: 45219 | E187: =IF(D187<C187,"Invalid","Valid") -> Valid | F187: =IF(D187>C187,D187,WORKDAY(C187,5)) -> 45219 | G187: =F187-C187 -> 2 | H187: Africa | I187: Kenya | J187: Kisumu | K187: =IF(J187="", "Unknown", J187) -> Kisumu | L187: Consumer | M187: Retail | N187: =IF(M187="", "Unknown", M187) -> Retail | O187: J. Njeri | P187: =IF(O187="","Unassigned",O187) -> J. Njeri | Q187: Phones | R187: PHN-8891 | S187: 774.12 | T187: 908.3 | U187: =IF(T187>0,T187,S187*1.2) -> 908.3 | V187: 0 | W187: =IF(V187<0.3,V187,0.3) -> 0 | X187: 30
A188: ORD-2023-667815 | B188: =IF(COUNTIF($A$2:A188,A188)=1,"Original","Duplicate") -> Original | C188: 45220 | D188: 45239 | E188: =IF(D188<C188,"Invalid","Valid") -> Valid | F188: =IF(D188>C188,D188,WORKDAY(C188,5)) -> 45239 | G188: =F188-C188 -> 19 | H188: Europe | I188: United Kingdom | J188: London | K188: =IF(J188="", "Unknown", J188) -> London | L188: Non-Profit | M188: Direct | N188: =IF(M188="", "Unknown", M188) -> Direct | O188: A. Patel | P188: =IF(O188="","Unassigned",O188) -> A. Patel | Q188: Accessories | R188: ACC-8557 | S188: 1142.48 | T188: 2105.53 | U188: =IF(T188>0,T188,S188*1.2) -> 2105.53 | V188: 0.207 | W188: =IF(V188<0.3,V188,0.3) -> 0.207 | X188: 14
A189: ORD-2023-659070 | B189: =IF(COUNTIF($A$2:A189,A189)=1,"Original","Duplicate") -> Original | C189: 45220 | D189: 45220 | E189: =IF(D189<C189,"Invalid","Valid") -> Valid | F189: =IF(D189>C189,D189,WORKDAY(C189,5)) -> 45226 | G189: =F189-C189 -> 6 | H189: Europe | I189: United Kingdom | J189: Manchester | K189: =IF(J189="", "Unknown", J189) -> Manchester | L189: Enterprise | M189: Distributor | N189: =IF(M189="", "Unknown", M189) -> Distributor | O189: J. Njeri | P189: =IF(O189="","Unassigned",O189) -> J. Njeri | Q189: Monitors | R189: MON-8697 | S189: 384.19 | T189: 278.35 | U189: =IF(T189>0,T189,S189*1.2) -> 278.35 | V189: 0.056 | W189: =IF(V189<0.3,V189,0.3) -> 0.056 | X189: 10
A190: ORD-2023-163610 | B190: =IF(COUNTIF($A$2:A190,A190)=1,"Original","Duplicate") -> Original | C190: 45221 | D190: 45246 | E190: =IF(D190<C190,"Invalid","Valid") -> Valid | F190: =IF(D190>C190,D190,WORKDAY(C190,5)) -> 45246 | G190: =F190-C190 -> 25 | H190: Americas | I190: Canada | J190: Toronto | K190: =IF(J190="", "Unknown", J190) -> Toronto | L190: Small Business | M190: Marketplace | N190: =IF(M190="", "Unknown", M190) -> Marketplace | O190: I. Johnson | P190: =IF(O190="","Unassigned",O190) -> I. Johnson | Q190: Laptops | R190: LAP-9024 | S190: 1373.31 | T190: 3154.14 | U190: =IF(T190>0,T190,S190*1.2) -> 3154.14 | V190: 0.2 | W190: =IF(V190<0.3,V190,0.3) -> 0.2 | X190: 11
A191: ORD-2023-597666 | B191: =IF(COUNTIF($A$2:A191,A191)=1,"Original","Duplicate") -> Original | C191: 45224 | D191: 45254 | E191: =IF(D191<C191,"Invalid","Valid") -> Valid | F191: =IF(D191>C191,D191,WORKDAY(C191,5)) -> 45254 | G191: =F191-C191 -> 30 | H191: Europe | I191: France | J191: Paris | K191: =IF(J191="", "Unknown", J191) -> Paris | L191: Enterprise | M191: Distributor | N191: =IF(M191="", "Unknown", M191) -> Distributor | O191: C. Otieno | P191: =IF(O191="","Unassigned",O191) -> C. Otieno | Q191: Phones | R191: PHN-5938 | S191: 287.85 | T191: 602.92 | U191: =IF(T191>0,T191,S191*1.2) -> 602.92 | V191: 0.222 | W191: =IF(V191<0.3,V191,0.3) -> 0.222 | X191: 11
A192: ORD-2023-406606 | B192: =IF(COUNTIF($A$2:A192,A192)=1,"Original","Duplicate") -> Original | C192: 45224 | D192: 45227 | E192: =IF(D192<C192,"Invalid","Valid") -> Valid | F192: =IF(D192>C192,D192,WORKDAY(C192,5)) -> 45227 | G192: =F192-C192 -> 3 | H192: Americas | I192: Brazil | J192: Brasília | K192: =IF(J192="", "Unknown", J192) -> Brasília | L192: Corporate | M192: Distributor | N192: =IF(M192="", "Unknown", M192) -> Distributor | O192: L. Okafor | P192: =IF(O192="","Unassigned",O192) -> L. Okafor | Q192: Accessories | R192: ACC-2867 | S192: 509.31 | T192: 1145.9 | U192: =IF(T192>0,T192,S192*1.2) -> 1145.9 | V192: 0.057 | W192: =IF(V192<0.3,V192,0.3) -> 0.057 | X192: 8
A193: ORD-2023-835226 | B193: =IF(COUNTIF($A$2:A193,A193)=1,"Original","Duplicate") -> Original | C193: 45225 | D193: 45235 | E193: =IF(D193<C193,"Invalid","Valid") -> Valid | F193: =IF(D193>C193,D193,WORKDAY(C193,5)) -> 45235 | G193: =F193-C193 -> 10 | H193: Africa | I193: South Africa | J193: Cape Town | K193: =IF(J193="", "Unknown", J193) -> Cape Town | L193: Non-Profit | M193: Online | N193: =IF(M193="", "Unknown", M193) -> Online | O193: I. Johnson | P193: =IF(O193="","Unassigned",O193) -> I. Johnson | Q193: Laptops | R193: LAP-7320 | S193: 20.38 | T193: 42.56 | U193: =IF(T193>0,T193,S193*1.2) -> 42.56 | V193: 0.072 | W193: =IF(V193<0.3,V193,0.3) -> 0.072 | X193: 11
A194: ORD-2023-211715 | B194: =IF(COUNTIF($A$2:A194,A194)=1,"Original","Duplicate") -> Original | C194: 45229 | D194: 45244 | E194: =IF(D194<C194,"Invalid","Valid") -> Valid | F194: =IF(D194>C194,D194,WORKDAY(C194,5)) -> 45244 | G194: =F194-C194 -> 15 | H194: Asia | I194: India | J194: Bengaluru | K194: =IF(J194="", "Unknown", J194) -> Bengaluru | L194: Corporate | M194: Online | N194: =IF(M194="", "Unknown", M194) -> Online | O194: F. Müller | P194: =IF(O194="","Unassigned",O194) -> F. Müller | Q194: Laptops | R194: LAP-2378 | S194: 953.46 | T194: 2066.75 | U194: =IF(T194>0,T194,S194*1.2) -> 2066.75 | V194: 0.138 | W194: =IF(V194<0.3,V194,0.3) -> 0.138 | X194: 5
A195: ORD-2023-842488 | B195: =IF(COUNTIF($A$2:A195,A195)=1,"Original","Duplicate") -> Original | C195: 45230 | D195: 45232 | E195: =IF(D195<C195,"Invalid","Valid") -> Valid | F195: =IF(D195>C195,D195,WORKDAY(C195,5)) -> 45232 | G195: =F195-C195 -> 2 | H195: Africa | I195: Kenya | J195: Kisumu | K195: =IF(J195="", "Unknown", J195) -> Kisumu | L195: Education | M195: Retail | N195: =IF(M195="", "Unknown", M195) -> Retail | O195: O. Wang | P195: =IF(O195="","Unassigned",O195) -> O. Wang | Q195: Accessories | R195: ACC-4124 | S195: 867.89 | T195: 1349.94 | U195: =IF(T195>0,T195,S195*1.2) -> 1349.94 | V195: 0.184 | W195: =IF(V195<0.3,V195,0.3) -> 0.184 | X195: 10
A196: ORD-2023-653343 | B196: =IF(COUNTIF($A$2:A196,A196)=1,"Original","Duplicate") -> Original | C196: 45240 | D196: 45258 | E196: =IF(D196<C196,"Invalid","Valid") -> Valid | F196: =IF(D196>C196,D196,WORKDAY(C196,5)) -> 45258 | G196: =F196-C196 -> 18 | H196: Americas | I196: Brazil | J196: Brasília | K196: =IF(J196="", "Unknown", J196) -> Brasília | L196: Education | M196: Marketplace | N196: =IF(M196="", "Unknown", M196) -> Marketplace | O196: L. Okafor | P196: =IF(O196="","Unassigned",O196) -> L. Okafor | Q196: Accessories | R196: ACC-5260 | S196: 388.51 | T196: 776.46 | U196: =IF(T196>0,T196,S196*1.2) -> 776.46 | V196: 0.157 | W196: =IF(V196<0.3,V196,0.3) -> 0.157 | X196: 12
... A200: ORD-2023-561823 | B200: =IF(COUNTIF($A$2:A200,A200)=1,"Original","Duplicate") -> Original | C200: 45249 | D200: 45272 | E200: =IF(D200<C200,"Invalid","Valid") -> Valid | F200: =IF(D200>C200,D200,WORKDAY(C200,5)) -> 45272 | G200: =F200-C200 -> 23 | H200: Asia | I200: India | J200: Delhi | K200: =IF(J200="", "Unknown", J200) -> Delhi | L200: Small Business | M200: Direct | N200: =IF(M200="", "Unknown", M200) -> Direct | O200: C. Otieno | P200: =IF(O200="","Unassigned",O200) -> C. Otieno | Q200: Networking | R200: NET-2460 | S200: 1349.04 | T200: 2636.6 | U200: =IF(T200>0,T200,S200*1.2) -> 2636.6 | V200: 0.114 | W200: =IF(V200<0.3,V200,0.3) -> 0.114 | X200: 14
A201: ORD-2023-455933 | B201: =IF(COUNTIF($A$2:A201,A201)=1,"Original","Duplicate") -> Original | C201: 45249 | D201: 45279 | E201: =IF(D201<C201,"Invalid","Valid") -> Valid | F201: =IF(D201>C201,D201,WORKDAY(C201,5)) -> 45279 | G201: =F201-C201 -> 30 | H201: Asia | I201: Japan | J201: Nagoya | K201: =IF(J201="", "Unknown", J201) -> Nagoya | L201: Consumer | M201: Retail | N201: =IF(M201="", "Unknown", M201) -> Retail | P201: =IF(O201="","Unassigned",O201) -> Unassigned | Q201: Phones | R201: PHN-9184 | S201: 807.11 | T201: 1853.86 | U201: =IF(T201>0,T201,S201*1.2) -> 1853.86 | V201: 0.139 | W201: =IF(V201<0.3,V201,0.3) -> 0.139 | X201: 8
A202: ORD-2023-975863 | B202: =IF(COUNTIF($A$2:A202,A202)=1,"Original","Duplicate") -> Original | C202: 45250 | D202: 45265 | E202: =IF(D202<C202,"Invalid","Valid") -> Valid | F202: =IF(D202>C202,D202,WORKDAY(C202,5)) -> 45265 | G202: =F202-C202 -> 15 | H202: Asia | I202: Japan | J202: Tokyo | K202: =IF(J202="", "Unknown", J202) -> Tokyo | L202: Enterprise | M202: Retail | N202: =IF(M202="", "Unknown", M202) -> Retail | O202: L. Okafor | P202: =IF(O202="","Unassigned",O202) -> L. Okafor | Q202: Networking | R202: NET-3033 | S202: 354.24 | T202: 249.87 | U202: =IF(T202>0,T202,S202*1.2) -> 249.87 | V202: 0 | W202: =IF(V202<0.3,V202,0.3) -> 0 | X202: 6
A203: ORD-2023-964434 | B203: =IF(COUNTIF($A$2:A203,A203)=1,"Original","Duplicate") -> Original | C203: 45258 | D203: 45267 | E203: =IF(D203<C203,"Invalid","Valid") -> Valid | F203: =IF(D203>C203,D203,WORKDAY(C203,5)) -> 45267 | G203: =F203-C203 -> 9 | H203: Asia | I203: India | J203: Delhi | K203: =IF(J203="", "Unknown", J203) -> Delhi | L203: Enterprise | M203: Marketplace | N203: =IF(M203="", "Unknown", M203) -> Marketplace | O203: L. Okafor | P203: =IF(O203="","Unassigned",O203) -> L. Okafor | Q203: Phones | R203: PHN-2447 | S203: 699.33 | T203: 873.75 | U203: =IF(T203>0,T203,S203*1.2) -> 873.75 | V203: 0.235 | W203: =IF(V203<0.3,V203,0.3) -> 0.235 | X203: 10
A204: ORD-2023-825495 | B204: =IF(COUNTIF($A$2:A204,A204)=1,"Original","Duplicate") -> Original | C204: 45260 | D204: 45259 | E204: =IF(D204<C204,"Invalid","Valid") -> Invalid | F204: =IF(D204>C204,D204,WORKDAY(C204,5)) -> 45267 | G204: =F204-C204 -> 7 | H204: Africa | I204: South Africa | J204: Durban | K204: =IF(J204="", "Unknown", J204) -> Durban | L204: Small Business | M204: Marketplace | N204: =IF(M204="", "Unknown", M204) -> Marketplace | O204: E. Garcia | P204: =IF(O204="","Unassigned",O204) -> E. Garcia | Q204: Laptops | R204: LAP-1525 | S204: 275.56 | T204: 630.72 | U204: =IF(T204>0,T204,S204*1.2) -> 630.72 | V204: 0.107 | W204: =IF(V204<0.3,V204,0.3) -> 0.107 | X204: 23
A205: ORD-2023-191563 | B205: =IF(COUNTIF($A$2:A205,A205)=1,"Original","Duplicate") -> Original | C205: 45260 | D205: 45270 | E205: =IF(D205<C205,"Invalid","Valid") -> Valid | F205: =IF(D205>C205,D205,WORKDAY(C205,5)) -> 45270 | G205: =F205-C205 -> 10 | H205: Europe | I205: Germany | J205: Munich | K205: =IF(J205="", "Unknown", J205) -> Munich | L205: Small Business | M205: Direct | N205: =IF(M205="", "Unknown", M205) -> Direct | O205: F. Müller | P205: =IF(O205="","Unassigned",O205) -> F. Müller | Q205: Laptops | R205: LAP-4899 | S205: 174.74 | T205: 415.96 | U205: =IF(T205>0,T205,S205*1.2) -> 415.96 | V205: 0.125 | W205: =IF(V205<0.3,V205,0.3) -> 0.125 | X205: 21
A206: ORD-2023-573146 | B206: =IF(COUNTIF($A$2:A206,A206)=1,"Original","Duplicate") -> Original | C206: 45261 | D206: 45278 | E206: =IF(D206<C206,"Invalid","Valid") -> Valid | F206: =IF(D206>C206,D206,WORKDAY(C206,5)) -> 45278 | G206: =F206-C206 -> 17 | H206: Asia | I206: Japan | J206: Nagoya | K206: =IF(J206="", "Unknown", J206) -> Nagoya | L206: Small Business | M206: Direct | N206: =IF(M206="", "Unknown", M206) -> Direct | O206: N. Brown | P206: =IF(O206="","Unassigned",O206) -> N. Brown | Q206: Laptops | R206: LAP-3604 | S206: 1495.79 | T206: 2783.12 | U206: =IF(T206>0,T206,S206*1.2) -> 2783.12 | V206: 0.02 | W206: =IF(V206<0.3,V206,0.3) -> 0.02 | X206: 5
A207: ORD-2023-212701 | B207: =IF(COUNTIF($A$2:A207,A207)=1,"Original","Duplicate") -> Original | C207: 45262 | D207: 45276 | E207: =IF(D207<C207,"Invalid","Valid") -> Valid | F207: =IF(D207>C207,D207,WORKDAY(C207,5)) -> 45276 | G207: =F207-C207 -> 14 | H207: Europe | I207: Germany | J207: Frankfurt | K207: =IF(J207="", "Unknown", J207) -> Frankfurt | L207: Education | M207: Direct | N207: =IF(M207="", "Unknown", M207) -> Direct | O207: N. Brown | P207: =IF(O207="","Unassigned",O207) -> N. Brown | Q207: Monitors | R207: MON-4278 | S207: 879.08 | T207: 1093.39 | U207: =IF(T207>0,T207,S207*1.2) -> 1093.39 | V207: 0.113 | W207: =IF(V207<0.3,V207,0.3) -> 0.113 | X207: 17
A208: ORD-2023-239789 | B208: =IF(COUNTIF($A$2:A208,A208)=1,"Original","Duplicate") -> Original | C208: 45263 | D208: 45286 | E208: =IF(D208<C208,"Invalid","Valid") -> Valid | F208: =IF(D208>C208,D208,WORKDAY(C208,5)) -> 45286 | G208: =F208-C208 -> 23 | H208: Americas | I208: Brazil | J208: Rio de Janeiro | K208: =IF(J208="", "Unknown", J208) -> Rio de Janeiro | L208: Education | M208: Retail | N208: =IF(M208="", "Unknown", M208) -> Retail | O208: O. Wang | P208: =IF(O208="","Unassigned",O208) -> O. Wang | Q208: Phones | R208: PHN-4644 | S208: 1303.11 | T208: 1145.67 | U208: =IF(T208>0,T208,S208*1.2) -> 1145.67 | V208: 0.184 | W208: =IF(V208<0.3,V208,0.3) -> 0.184 | X208: 13
A209: ORD-2023-581799 | B209: =IF(COUNTIF($A$2:A209,A209)=1,"Original","Duplicate") -> Original | C209: 45265 | D209: 45272 | E209: =IF(D209<C209,"Invalid","Valid") -> Valid | F209: =IF(D209>C209,D209,WORKDAY(C209,5)) -> 45272 | G209: =F209-C209 -> 7 | H209: Americas | I209: Brazil | J209: Brasília | K209: =IF(J209="", "Unknown", J209) -> Brasília | L209: Corporate | M209: Direct | N209: =IF(M209="", "Unknown", M209) -> Direct | O209: F. Müller | P209: =IF(O209="","Unassigned",O209) -> F. Müller | Q209: Phones | R209: PHN-6506 | S209: 307.43 | T209: 495.19 | U209: =IF(T209>0,T209,S209*1.2) -> 495.19 | V209: 0 | W209: =IF(V209<0.3,V209,0.3) -> 0 | X209: 42
A210: ORD-2023-824839 | B210: =IF(COUNTIF($A$2:A210,A210)=1,"Original","Duplicate") -> Original | C210: 45266 | D210: 45291 | E210: =IF(D210<C210,"Invalid","Valid") -> Valid | F210: =IF(D210>C210,D210,WORKDAY(C210,5)) -> 45291 | G210: =F210-C210 -> 25 | H210: Asia | I210: Japan | J210: Osaka | K210: =IF(J210="", "Unknown", J210) -> Osaka | L210: Consumer | M210: Retail | N210: =IF(M210="", "Unknown", M210) -> Retail | O210: L. Okafor | P210: =IF(O210="","Unassigned",O210) -> L. Okafor | Q210: Printers | R210: PRN-8041 | S210: 663.03 | T210: 813.51 | U210: =IF(T210>0,T210,S210*1.2) -> 813.51 | V210: 0.102 | W210: =IF(V210<0.3,V210,0.3) -> 0.102 | X210: 15
A211: ORD-2023-596758 | B211: =IF(COUNTIF($A$2:A211,A211)=1,"Original","Duplicate") -> Original | C211: 45267 | D211: 45265 | E211: =IF(D211<C211,"Invalid","Valid") -> Invalid | F211: =IF(D211>C211,D211,WORKDAY(C211,5)) -> 45274 | G211: =F211-C211 -> 7 | H211: Asia | I211: Japan | J211: Tokyo | K211: =IF(J211="", "Unknown", J211) -> Tokyo | L211: Non-Profit | M211: Marketplace | N211: =IF(M211="", "Unknown", M211) -> Marketplace | O211: H. Kim | P211: =IF(O211="","Unassigned",O211) -> H. Kim | Q211: Printers | R211: PRN-8175 | S211: 1097.59 | T211: 845.55 | U211: =IF(T211>0,T211,S211*1.2) -> 845.55 | V211: 0.184 | W211: =IF(V211<0.3,V211,0.3) -> 0.184 | X211: 6
A212: ORD-2023-961864 | B212: =IF(COUNTIF($A$2:A212,A212)=1,"Original","Duplicate") -> Original | C212: 45267 | D212: 45293 | E212: =IF(D212<C212,"Invalid","Valid") -> Valid | F212: =IF(D212>C212,D212,WORKDAY(C212,5)) -> 45293 | G212: =F212-C212 -> 26 | H212: Europe | I212: Germany | J212: Frankfurt | K212: =IF(J212="", "Unknown", J212) -> Frankfurt | L212: Enterprise | M212: Distributor | N212: =IF(M212="", "Unknown", M212) -> Distributor | O212: E. Garcia | P212: =IF(O212="","Unassigned",O212) -> E. Garcia | Q212: Components | R212: CMP-1940 | S212: 1071.99 | T212: 2397.3 | U212: =IF(T212>0,T212,S212*1.2) -> 2397.3 | V212: 0.062 | W212: =IF(V212<0.3,V212,0.3) -> 0.062 | X212: 18
A213: ORD-2023-674887 | B213: =IF(COUNTIF($A$2:A213,A213)=1,"Original","Duplicate") -> Original | C213: 45276 | D213: 45279 | E213: =IF(D213<C213,"Invalid","Valid") -> Valid | F213: =IF(D213>C213,D213,WORKDAY(C213,5)) -> 45279 | G213: =F213-C213 -> 3 | H213: Asia | I213: China | J213: Beijing | K213: =IF(J213="", "Unknown", J213) -> Beijing | L213: Education | M213: Retail | N213: =IF(M213="", "Unknown", M213) -> Retail | O213: A. Patel | P213: =IF(O213="","Unassigned",O213) -> A. Patel | Q213: Accessories | R213: ACC-9644 | S213: 1415.05 | T213: 1972.38 | U213: =IF(T213>0,T213,S213*1.2) -> 1972.38 | V213: 0 | W213: =IF(V213<0.3,V213,0.3) -> 0 | X213: 12
... A217: ORD-2023-431328 | B217: =IF(COUNTIF($A$2:A217,A217)=1,"Original","Duplicate") -> Original | C217: 45280 | D217: 45305 | E217: =IF(D217<C217,"Invalid","Valid") -> Valid | F217: =IF(D217>C217,D217,WORKDAY(C217,5)) -> 45305 | G217: =F217-C217 -> 25 | H217: Asia | I217: India | J217: Mumbai | K217: =IF(J217="", "Unknown", J217) -> Mumbai | L217: Non-Profit | M217: Marketplace | N217: =IF(M217="", "Unknown", M217) -> Marketplace | O217: L. Okafor | P217: =IF(O217="","Unassigned",O217) -> L. Okafor | Q217: Monitors | R217: MON-1572 | S217: 1085.61 | T217: 1246.41 | U217: =IF(T217>0,T217,S217*1.2) -> 1246.41 | V217: 0.113 | W217: =IF(V217<0.3,V217,0.3) -> 0.113 | X217: 7
A218: ORD-2023-208944 | B218: =IF(COUNTIF($A$2:A218,A218)=1,"Original","Duplicate") -> Original | C218: 45281 | D218: 45297 | E218: =IF(D218<C218,"Invalid","Valid") -> Valid | F218: =IF(D218>C218,D218,WORKDAY(C218,5)) -> 45297 | G218: =F218-C218 -> 16 | H218: Africa | I218: Nigeria | K218: =IF(J218="", "Unknown", J218) -> Unknown | L218: Corporate | M218: Marketplace | N218: =IF(M218="", "Unknown", M218) -> Marketplace | O218: K. Singh | P218: =IF(O218="","Unassigned",O218) -> K. Singh | Q218: Components | R218: CMP-4792 | S218: 932.61 | T218: 1982.98 | U218: =IF(T218>0,T218,S218*1.2) -> 1982.98 | V218: 0.144 | W218: =IF(V218<0.3,V218,0.3) -> 0.144 | X218: 16
A219: ORD-2023-841426 | B219: =IF(COUNTIF($A$2:A219,A219)=1,"Original","Duplicate") -> Original | C219: 45282 | D219: 45283 | E219: =IF(D219<C219,"Invalid","Valid") -> Valid | F219: =IF(D219>C219,D219,WORKDAY(C219,5)) -> 45283 | G219: =F219-C219 -> 1 | H219: Africa | I219: South Africa | J219: Cape Town | K219: =IF(J219="", "Unknown", J219) -> Cape Town | L219: Non-Profit | M219: Marketplace | N219: =IF(M219="", "Unknown", M219) -> Marketplace | O219: D. Smith | P219: =IF(O219="","Unassigned",O219) -> D. Smith | Q219: Components | R219: CMP-4531 | S219: 1186.18 | T219: 1285.09 | U219: =IF(T219>0,T219,S219*1.2) -> 1285.09 | V219: 0.07 | W219: =IF(V219<0.3,V219,0.3) -> 0.07 | X219: 11
A220: ORD-2023-249805 | B220: =IF(COUNTIF($A$2:A220,A220)=1,"Original","Duplicate") -> Original | C220: 45282 | D220: 45307 | E220: =IF(D220<C220,"Invalid","Valid") -> Valid | F220: =IF(D220>C220,D220,WORKDAY(C220,5)) -> 45307 | G220: =F220-C220 -> 25 | H220: Asia | I220: India | J220: Hyderabad | K220: =IF(J220="", "Unknown", J220) -> Hyderabad | L220: Small Business | M220: Retail | N220: =IF(M220="", "Unknown", M220) -> Retail | O220: A. Patel | P220: =IF(O220="","Unassigned",O220) -> A. Patel | Q220: Components | R220: CMP-1555 | S220: 1346.81 | T220: 978.09 | U220: =IF(T220>0,T220,S220*1.2) -> 978.09 | V220: 0.159 | W220: =IF(V220<0.3,V220,0.3) -> 0.159 | X220: 17
A221: ORD-2023-967239 | B221: =IF(COUNTIF($A$2:A221,A221)=1,"Original","Duplicate") -> Original | C221: 45284 | D221: 45292 | E221: =IF(D221<C221,"Invalid","Valid") -> Valid | F221: =IF(D221>C221,D221,WORKDAY(C221,5)) -> 45292 | G221: =F221-C221 -> 8 | H221: Americas | I221: Brazil | J221: São Paulo | K221: =IF(J221="", "Unknown", J221) -> São Paulo | L221: Education | M221: Direct | N221: =IF(M221="", "Unknown", M221) -> Direct | O221: C. Otieno | P221: =IF(O221="","Unassigned",O221) -> C. Otieno | Q221: Phones | R221: PHN-3014 | S221: 526.49 | T221: 496.2 | U221: =IF(T221>0,T221,S221*1.2) -> 496.2 | V221: 0 | W221: =IF(V221<0.3,V221,0.3) -> 0 | X221: 14
A222: ORD-2023-580751 | B222: =IF(COUNTIF($A$2:A222,A222)=1,"Original","Duplicate") -> Original | C222: 45284 | D222: 45304 | E222: =IF(D222<C222,"Invalid","Valid") -> Valid | F222: =IF(D222>C222,D222,WORKDAY(C222,5)) -> 45304 | G222: =F222-C222 -> 20 | H222: Asia | I222: Japan | J222: Nagoya | K222: =IF(J222="", "Unknown", J222) -> Nagoya | L222: Education | M222: Direct | N222: =IF(M222="", "Unknown", M222) -> Direct | O222: B. Chen | P222: =IF(O222="","Unassigned",O222) -> B. Chen | Q222: Laptops | R222: LAP-1946 | S222: 625.37 | T222: 1319.04 | U222: =IF(T222>0,T222,S222*1.2) -> 1319.04 | V222: 0.074 | W222: =IF(V222<0.3,V222,0.3) -> 0.074 | X222: 8
A223: ORD-2023-813340 | B223: =IF(COUNTIF($A$2:A223,A223)=1,"Original","Duplicate") -> Original | C223: 45286 | D223: 45294 | E223: =IF(D223<C223,"Invalid","Valid") -> Valid | F223: =IF(D223>C223,D223,WORKDAY(C223,5)) -> 45294 | G223: =F223-C223 -> 8 | H223: Europe | I223: France | J223: Lyon | K223: =IF(J223="", "Unknown", J223) -> Lyon | L223: Small Business | M223: Retail | N223: =IF(M223="", "Unknown", M223) -> Retail | O223: M. Rossi | P223: =IF(O223="","Unassigned",O223) -> M. Rossi | Q223: Laptops | R223: LAP-2942 | S223: 492.75 | T223: 731.29 | U223: =IF(T223>0,T223,S223*1.2) -> 731.29 | V223: 0.058 | W223: =IF(V223<0.3,V223,0.3) -> 0.058 | X223: 6
A224: ORD-2023-974506 | B224: =IF(COUNTIF($A$2:A224,A224)=1,"Original","Duplicate") -> Original | C224: 45288 | D224: 45292 | E224: =IF(D224<C224,"Invalid","Valid") -> Valid | F224: =IF(D224>C224,D224,WORKDAY(C224,5)) -> 45292 | G224: =F224-C224 -> 4 | H224: Africa | I224: South Africa | J224: Cape Town | K224: =IF(J224="", "Unknown", J224) -> Cape Town | L224: Education | M224: Distributor | N224: =IF(M224="", "Unknown", M224) -> Distributor | O224: A. Patel | P224: =IF(O224="","Unassigned",O224) -> A. Patel | Q224: Printers | R224: PRN-1654 | S224: 1141.8 | T224: 2318.74 | U224: =IF(T224>0,T224,S224*1.2) -> 2318.74 | V224: 0.107 | W224: =IF(V224<0.3,V224,0.3) -> 0.107 | X224: 32
A225: ORD-2023-178249 | B225: =IF(COUNTIF($A$2:A225,A225)=1,"Original","Duplicate") -> Original | C225: 45289 | D225: 45311 | E225: =IF(D225<C225,"Invalid","Valid") -> Valid | F225: =IF(D225>C225,D225,WORKDAY(C225,5)) -> 45311 | G225: =F225-C225 -> 22 | H225: Africa | I225: Kenya | J225: Kisumu | K225: =IF(J225="", "Unknown", J225) -> Kisumu | L225: Corporate | M225: Direct | N225: =IF(M225="", "Unknown", M225) -> Direct | O225: L. Okafor | P225: =IF(O225="","Unassigned",O225) -> L. Okafor | Q225: Phones | R225: PHN-7924 | S225: 1395.49 | T225: 1679.42 | U225: =IF(T225>0,T225,S225*1.2) -> 1679.42 | V225: 0.203 | W225: =IF(V225<0.3,V225,0.3) -> 0.203 | X225: 12
A226: ORD-2023-808024 | B226: =IF(COUNTIF($A$2:A226,A226)=1,"Original","Duplicate") -> Original | C226: 45290 | D226: 45299 | E226: =IF(D226<C226,"Invalid","Valid") -> Valid | F226: =IF(D226>C226,D226,WORKDAY(C226,5)) -> 45299 | G226: =F226-C226 -> 9 | H226: Europe | I226: France | J226: Marseille | K226: =IF(J226="", "Unknown", J226) -> Marseille | L226: Consumer | M226: Marketplace | N226: =IF(M226="", "Unknown", M226) -> Marketplace | O226: L. Okafor | P226: =IF(O226="","Unassigned",O226) -> L. Okafor | Q226: Accessories | R226: ACC-6594 | S226: 861.1 | T226: 1224.72 | U226: =IF(T226>0,T226,S226*1.2) -> 1224.72 | V226: 0.174 | W226: =IF(V226<0.3,V226,0.3) -> 0.174 | X226: 24
A227: ORD-2024-921935 | B227: =IF(COUNTIF($A$2:A227,A227)=1,"Original","Duplicate") -> Original | C227: 45292 | D227: 45318 | E227: =IF(D227<C227,"Invalid","Valid") -> Valid | F227: =IF(D227>C227,D227,WORKDAY(C227,5)) -> 45318 | G227: =F227-C227 -> 26 | H227: Europe | I227: United Kingdom | J227: Manchester | K227: =IF(J227="", "Unknown", J227) -> Manchester | L227: Education | M227: Distributor | N227: =IF(M227="", "Unknown", M227) -> Distributor | O227: D. Smith | P227: =IF(O227="","Unassigned",O227) -> D. Smith | Q227: Accessories | R227: ACC-3103 | S227: 657.45 | T227: 1325.96 | U227: =IF(T227>0,T227,S227*1.2) -> 1325.96 | V227: 0.167 | W227: =IF(V227<0.3,V227,0.3) -> 0.167 | X227: 21
A228: ORD-2024-719055 | B228: =IF(COUNTIF($A$2:A228,A228)=1,"Original","Duplicate") -> Original | C228: 45293 | D228: 45292 | E228: =IF(D228<C228,"Invalid","Valid") -> Invalid | F228: =IF(D228>C228,D228,WORKDAY(C228,5)) -> 45300 | G228: =F228-C228 -> 7 | H228: Americas | I228: USA | J228: Chicago | K228: =IF(J228="", "Unknown", J228) -> Chicago | L228: Education | M228: Marketplace | N228: =IF(M228="", "Unknown", M228) -> Marketplace | O228: B. Chen | P228: =IF(O228="","Unassigned",O228) -> B. Chen | Q228: Networking | R228: NET-4554 | S228: 404.77 | T228: 433.88 | U228: =IF(T228>0,T228,S228*1.2) -> 433.88 | V228: 0.215 | W228: =IF(V228<0.3,V228,0.3) -> 0.215 | X228: 22
A229: ORD-2024-105586 | B229: =IF(COUNTIF($A$2:A229,A229)=1,"Original","Duplicate") -> Original | C229: 45293 | D229: 45306 | E229: =IF(D229<C229,"Invalid","Valid") -> Valid | F229: =IF(D229>C229,D229,WORKDAY(C229,5)) -> 45306 | G229: =F229-C229 -> 13 | H229: Asia | I229: Japan | J229: Nagoya | K229: =IF(J229="", "Unknown", J229) -> Nagoya | L229: Small Business | M229: Marketplace | N229: =IF(M229="", "Unknown", M229) -> Marketplace | O229: G. Dubois | P229: =IF(O229="","Unassigned",O229) -> G. Dubois | Q229: Networking | R229: NET-1893 | S229: 1219.06 | T229: 2738.69 | U229: =IF(T229>0,T229,S229*1.2) -> 2738.69 | V229: 0.076 | W229: =IF(V229<0.3,V229,0.3) -> 0.076 | X229: 16
A230: ORD-2024-355095 | B230: =IF(COUNTIF($A$2:A230,A230)=1,"Original","Duplicate") -> Original | C230: 45293 | D230: 45293 | E230: =IF(D230<C230,"Invalid","Valid") -> Valid | F230: =IF(D230>C230,D230,WORKDAY(C230,5)) -> 45300 | G230: =F230-C230 -> 7 | H230: Americas | I230: Canada | J230: Vancouver | K230: =IF(J230="", "Unknown", J230) -> Vancouver | L230: Education | M230: Direct | N230: =IF(M230="", "Unknown", M230) -> Direct | O230: A. Patel | P230: =IF(O230="","Unassigned",O230) -> A. Patel | Q230: Laptops | R230: LAP-3581 | S230: 444.41 | T230: 754.24 | U230: =IF(T230>0,T230,S230*1.2) -> 754.24 | V230: 0.207 | W230: =IF(V230<0.3,V230,0.3) -> 0.207 | X230: 32
... A233: ORD-2024-296582 | B233: =IF(COUNTIF($A$2:A233,A233)=1,"Original","Duplicate") -> Original | C233: 45302 | D233: 45324 | E233: =IF(D233<C233,"Invalid","Valid") -> Valid | F233: =IF(D233>C233,D233,WORKDAY(C233,5)) -> 45324 | G233: =F233-C233 -> 22 | H233: Africa | I233: South Africa | J233: Durban | K233: =IF(J233="", "Unknown", J233) -> Durban | L233: Consumer | M233: Online | N233: =IF(M233="", "Unknown", M233) -> Online | O233: K. Singh | P233: =IF(O233="","Unassigned",O233) -> K. Singh | Q233: Networking | R233: NET-1412 | S233: 1206.2 | T233: 1759.79 | U233: =IF(T233>0,T233,S233*1.2) -> 1759.79 | V233: 0 | W233: =IF(V233<0.3,V233,0.3) -> 0 | X233: 6
A234: ORD-2024-281211 | B234: =IF(COUNTIF($A$2:A234,A234)=1,"Original","Duplicate") -> Original | C234: 45302 | D234: 45324 | E234: =IF(D234<C234,"Invalid","Valid") -> Valid | F234: =IF(D234>C234,D234,WORKDAY(C234,5)) -> 45324 | G234: =F234-C234 -> 22 | H234: Asia | I234: Japan | J234: Nagoya | K234: =IF(J234="", "Unknown", J234) -> Nagoya | L234: Small Business | M234: Online | N234: =IF(M234="", "Unknown", M234) -> Online | P234: =IF(O234="","Unassigned",O234) -> Unassigned | Q234: Printers | R234: PRN-7816 | S234: 1237.68 | T234: 1432.8 | U234: =IF(T234>0,T234,S234*1.2) -> 1432.8 | V234: 0.068 | W234: =IF(V234<0.3,V234,0.3) -> 0.068 | X234: 13
A235: ORD-2024-999607 | B235: =IF(COUNTIF($A$2:A235,A235)=1,"Original","Duplicate") -> Original | C235: 45303 | D235: 45320 | E235: =IF(D235<C235,"Invalid","Valid") -> Valid | F235: =IF(D235>C235,D235,WORKDAY(C235,5)) -> 45320 | G235: =F235-C235 -> 17 | H235: Americas | I235: USA | J235: Chicago | K235: =IF(J235="", "Unknown", J235) -> Chicago | L235: Education | M235: Distributor | N235: =IF(M235="", "Unknown", M235) -> Distributor | O235: A. Patel | P235: =IF(O235="","Unassigned",O235) -> A. Patel | Q235: Printers | R235: PRN-8604 | S235: 493.76 | T235: 625.04 | U235: =IF(T235>0,T235,S235*1.2) -> 625.04 | V235: 0.258 | W235: =IF(V235<0.3,V235,0.3) -> 0.258 | X235: 10
A236: ORD-2024-153053 | B236: =IF(COUNTIF($A$2:A236,A236)=1,"Original","Duplicate") -> Original | C236: 45303 | D236: 45320 | E236: =IF(D236<C236,"Invalid","Valid") -> Valid | F236: =IF(D236>C236,D236,WORKDAY(C236,5)) -> 45320 | G236: =F236-C236 -> 17 | H236: Asia | I236: India | J236: Hyderabad | K236: =IF(J236="", "Unknown", J236) -> Hyderabad | L236: Small Business | M236: Direct | N236: =IF(M236="", "Unknown", M236) -> Direct | O236: B. Chen | P236: =IF(O236="","Unassigned",O236) -> B. Chen | Q236: Components | R236: CMP-5138 | S236: 310.02 | T236: 619.51 | U236: =IF(T236>0,T236,S236*1.2) -> 619.51 | V236: 0.042 | W236: =IF(V236<0.3,V236,0.3) -> 0.042 | X236: 4
A237: ORD-2024-851883 | B237: =IF(COUNTIF($A$2:A237,A237)=1,"Original","Duplicate") -> Original | C237: 45304 | D237: 45313 | E237: =IF(D237<C237,"Invalid","Valid") -> Valid | F237: =IF(D237>C237,D237,WORKDAY(C237,5)) -> 45313 | G237: =F237-C237 -> 9 | H237: Asia | I237: India | J237: Mumbai | K237: =IF(J237="", "Unknown", J237) -> Mumbai | L237: Enterprise | M237: Marketplace | N237: =IF(M237="", "Unknown", M237) -> Marketplace | O237: J. Njeri | P237: =IF(O237="","Unassigned",O237) -> J. Njeri | Q237: Components | R237: CMP-8141 | S237: 313.6 | T237: 334.28 | U237: =IF(T237>0,T237,S237*1.2) -> 334.28 | V237: 0.14 | W237: =IF(V237<0.3,V237,0.3) -> 0.14 | X237: 22
...

Sheet Part A (2&3)
A1: OrderID | B1: Duplicate | C1: OrderDate | D1: FixedRequiredDate | E1: LeadTimeDays | F1: Region | G1: Country | H1: City | I1: CustomerSegment | J1: Channel | K1: Salesperson | L1: ProductCategory | M1: SKU | N1: UnitCost | O1: UnitPrice | P1: DiscountPct | Q1: Quantity | R1: GrossRevenue | S1: CostofGoods | T1: GrossProfit | U1: MarginPct | V1: OrderDateNew | W1: OrderDateNew | X1: Quarters | Y1: RegionHierachy | Z1: ProductCategory | AA1: PriceBand | AB1: CohortStart | AC1: MonthsSinceStart | AE1: Category | AF1: Value | AG1: Percentile | AJ1: CohortStart
A2: ORD-2023-723587 | B2: =IF(COUNTIF($A$2:A2,A2)=1,"Original","Duplicate") -> Original | C2: 44928 | D2: 44931 | E2: =D2-C2 -> 3 | F2: Americas | G2: Canada | H2: Toronto | I2: Corporate | J2: Distributor | K2: B. Chen | L2: Laptops | M2: LAP-8555 | N2: 315.87 | O2: 591.68 | P2: 0 | Q2: 7 | R2: =(O2*Q2)*(1-P2) -> 4141.76 | S2: =N2*Q2 -> 2211.09 | T2: =R2-S2 -> 1930.67 | U2: =IF(R2=0,0,T2/R2) -> 0.46614724 | V2: =TEXT(C2,"MMM-YYYY") -> Jan-2023 | W2: =DATEVALUE(V2) -> 44927 | X2: ="Q"&ROUNDUP(MONTH(C2)/3,0)&"-"&YEAR(C2) -> Q1-2023 | Y2: =_xlfn.CONCAT(F2," ","→"," ",G2," ","→"," ",H2) -> Americas → Canada → Toronto | Z2: =TRIM(L2) -> Laptops | AA2: {=_xlfn.IFS(O2<=$AF$2,"Low",AND(O2>$AF$2,O2<$AF$3),"Medium",O2>=$AF$3,"High")} -> Low | AB2: =_xlfn.MINIFS($W$2:$W$632,$G$2:$G$632,G2) -> 44927 | AC2: {=(YEAR(W2:W632) - YEAR(AB2:AB632))*12 + (MONTH(W2:W632) - MONTH(AB2:AB632))} -> 0 | AE2: Low | AF2: =_xlfn.PERCENTILE.INC($O$2:$O$632,0.33) -> 824.755 | AG2: 0.33 | AJ2: =_xlfn.MINIFS($W$2:$W$632,$G$2:$G$632,G2) -> 44927
A3: ORD-2023-689428 | B3: =IF(COUNTIF($A$2:A3,A3)=1,"Original","Duplicate") -> Original | C3: 44933 | D3: 44956 | E3: =D3-C3 -> 23 | F3: Africa | G3: South Africa | H3: Cape Town | I3: Consumer | J3: Online | K3: A. Patel | L3: Printers | M3: PRN-4787 | N3: 299.02 | O3: 724.7 | P3: 0.14 | Q3: 5 | R3: =(O3*Q3)*(1-P3) -> 3116.21 | S3: =N3*Q3 -> 1495.1 | T3: =R3-S3 -> 1621.11 | U3: =IF(R3=0,0,T3/R3) -> 0.52021847 | V3: =TEXT(C3,"MMM-YYYY") -> Jan-2023 | W3: =DATEVALUE(V3) -> 44927 | X3: ="Q"&ROUNDUP(MONTH(C3)/3,0)&"-"&YEAR(C3) -> Q1-2023 | Y3: =_xlfn.CONCAT(F3," ","→"," ",G3," ","→"," ",H3) -> Africa → South Africa → Cape Town | Z3: =TRIM(L3) -> Printers | AA3: {=_xlfn.IFS(O3<=$AF$2,"Low",AND(O3>$AF$2,O3<$AF$3),"Medium",O3>=$AF$3,"High")} -> Low | AB3: =_xlfn.MINIFS($W$2:$W$632,$G$2:$G$632,G3) -> 44927 | AC3: 0 | AE3: High | AF3: =_xlfn.PERCENTILE.INC($O$2:$O$632,0.66) -> 1623.856 | AG3: 0.66 | AJ3: =_xlfn.MINIFS($W$2:$W$632,$G$2:$G$632,G3) -> 44927
A4: ORD-2023-884192 | B4: =IF(COUNTIF($A$2:A4,A4)=1,"Original","Duplicate") -> Original | C4: 44936 | D4: 44955 | E4: =D4-C4 -> 19 | F4: Europe | G4: France | H4: Lyon | I4: Non-Profit | J4: Direct | K4: D. Smith | L4: Laptops | M4: LAP-4551 | N4: 401.66 | O4: 772.09 | P4: 0.089 | Q4: 14 | R4: =(O4*Q4)*(1-P4) -> 9847.2359 | S4: =N4*Q4 -> 5623.24 | T4: =R4-S4 -> 4223.9959 | U4: =IF(R4=0,0,T4/R4) -> 0.42895244 | V4: =TEXT(C4,"MMM-YYYY") -> Jan-2023 | W4: =DATEVALUE(V4) -> 44927 | X4: ="Q"&ROUNDUP(MONTH(C4)/3,0)&"-"&YEAR(C4) -> Q1-2023 | Y4: =_xlfn.CONCAT(F4," ","→"," ",G4," ","→"," ",H4) -> Europe → France → Lyon | Z4: =TRIM(L4) -> Laptops | AA4: {=_xlfn.IFS(O4<=$AF$2,"Low",AND(O4>$AF$2,O4<$AF$3),"Medium",O4>=$AF$3,"High")} -> Low | AB4: =_xlfn.MINIFS($W$2:$W$632,$G$2:$G$632,G4) -> 44927 | AC4: 0 | AJ4: =_xlfn.MINIFS($W$2:$W$632,$G$2:$G$632,G4) -> 44927
A5: ORD-2023-700699 | B5: =IF(COUNTIF($A$2:A5,A5)=1,"Original","Duplicate") -> Original | C5: 44938 | D5: 44952 | E5: =D5-C5 -> 14 | F5: Asia | G5: China | H5: Shenzhen | I5: Non-Profit | J5: Retail | K5: M. Rossi | L5: Printers | M5: PRN-1641 | N5: 1083.09 | O5: 1425.87 | P5: 0 | Q5: 8 | R5: =(O5*Q5)*(1-P5) -> 11406.96 | S5: =N5*Q5 -> 8664.72 | T5: =R5-S5 -> 2742.24 | U5: =IF(R5=0,0,T5/R5) -> 0.2404006 | V5: =TEXT(C5,"MMM-YYYY") -> Jan-2023 | W5: =DATEVALUE(V5) -> 44927 | X5: ="Q"&ROUNDUP(MONTH(C5)/3,0)&"-"&YEAR(C5) -> Q1-2023 | Y5: =_xlfn.CONCAT(F5," ","→"," ",G5," ","→"," ",H5) -> Asia → China → Shenzhen | Z5: =TRIM(L5) -> Printers | AA5: {=_xlfn.IFS(O5<=$AF$2,"Low",AND(O5>$AF$2,O5<$AF$3),"Medium",O5>=$AF$3,"High")} -> Medium | AB5: =_xlfn.MINIFS($W$2:$W$632,$G$2:$G$632,G5) -> 44927 | AC5: 0 | AJ5: =_xlfn.MINIFS($W$2:$W$632,$G$2:$G$632,G5) -> 44927
A6: ORD-2023-382017 | B6: =IF(COUNTIF($A$2:A6,A6)=1,"Original","Duplicate") -> Original | C6: 44939 | D6: 44945 | E6: =D6-C6 -> 6 | F6: Americas | G6: USA | H6: Chicago | I6: Corporate | J6: Direct | K6: H. Kim | L6: Phones | M6: PHN-3159 | N6: 833.57 | O6: 881.57 | P6: 0.057 | Q6: 18 | R6: =(O6*Q6)*(1-P6) -> 14963.769 | S6: =N6*Q6 -> 15004.26 | T6: =R6-S6 -> -40.49082 | U6: =IF(R6=0,0,T6/R6) -> -0.0027059239 | V6: =TEXT(C6,"MMM-YYYY") -> Jan-2023 | W6: =DATEVALUE(V6) -> 44927 | X6: ="Q"&ROUNDUP(MONTH(C6)/3,0)&"-"&YEAR(C6) -> Q1-2023 | Y6: =_xlfn.CONCAT(F6," ","→"," ",G6," ","→"," ",H6) -> Americas → USA → Chicago | Z6: =TRIM(L6) -> Phones | AA6: {=_xlfn.IFS(O6<=$AF$2,"Low",AND(O6>$AF$2,O6<$AF$3),"Medium",O6>=$AF$3,"High")} -> Medium | AB6: =_xlfn.MINIFS($W$2:$W$632,$G$2:$G$632,G6) -> 44927 | AC6: 0 | AJ6: =_xlfn.MINIFS($W$2:$W$632,$G$2:$G$632,G6) -> 44927
A7: ORD-2023-112666 | B7: =IF(COUNTIF($A$2:A7,A7)=1,"Original","Duplicate") -> Original | C7: 44941 | D7: 44946 | E7: =D7-C7 -> 5 | F7: Africa | G7: Nigeria | H7: Abuja | I7: Education | J7: Online | K7: O. Wang | L7: Printers | M7: PRN-6276 | N7: 28.38 | O7: 47.22 | P7: 0.194 | Q7: 18 | R7: =(O7*Q7)*(1-P7) -> 685.06776 | S7: =N7*Q7 -> 510.84 | T7: =R7-S7 -> 174.22776 | U7: =IF(R7=0,0,T7/R7) -> 0.25432194 | V7: =TEXT(C7,"MMM-YYYY") -> Jan-2023 | W7: =DATEVALUE(V7) -> 44927 | X7: ="Q"&ROUNDUP(MONTH(C7)/3,0)&"-"&YEAR(C7) -> Q1-2023 | Y7: =_xlfn.CONCAT(F7," ","→"," ",G7," ","→"," ",H7) -> Africa → Nigeria → Abuja | Z7: =TRIM(L7) -> Printers | AA7: {=_xlfn.IFS(O7<=$AF$2,"Low",AND(O7>$AF$2,O7<$AF$3),"Medium",O7>=$AF$3,"High")} -> Low | AB7: =_xlfn.MINIFS($W$2:$W$632,$G$2:$G$632,G7) -> 44927 | AC7: 0 | AJ7: =_xlfn.MINIFS($W$2:$W$632,$G$2:$G$632,G7) -> 44927
A8: ORD-2023-780206 | B8: =IF(COUNTIF($A$2:A8,A8)=1,"Original","Duplicate") -> Original | C8: 44945 | D8: 44960 | E8: =D8-C8 -> 15 | F8: Europe | G8: United Kingdom | H8: London | I8: Enterprise | J8: Distributor | K8: G. Dubois | L8: Accessories | M8: ACC-3645 | N8: 873.06 | O8: 2101.55 | P8: 0.066 | Q8: 10 | R8: =(O8*Q8)*(1-P8) -> 19628.477 | S8: =N8*Q8 -> 8730.6 | T8: =R8-S8 -> 10897.877 | U8: =IF(R8=0,0,T8/R8) -> 0.55520747 | V8: =TEXT(C8,"MMM-YYYY") -> Jan-2023 | W8: =DATEVALUE(V8) -> 44927 | X8: ="Q"&ROUNDUP(MONTH(C8)/3,0)&"-"&YEAR(C8) -> Q1-2023 | Y8: =_xlfn.CONCAT(F8," ","→"," ",G8," ","→"," ",H8) -> Europe → United Kingdom → London | Z8: =TRIM(L8) -> Accessories | AA8: {=_xlfn.IFS(O8<=$AF$2,"Low",AND(O8>$AF$2,O8<$AF$3),"Medium",O8>=$AF$3,"High")} -> High | AB8: =_xlfn.MINIFS($W$2:$W$632,$G$2:$G$632,G8) -> 44927 | AC8: 0 | AJ8: =_xlfn.MINIFS($W$2:$W$632,$G$2:$G$632,G8) -> 44927
A9: ORD-2023-586275 | B9: =IF(COUNTIF($A$2:A9,A9)=1,"Original","Duplicate") -> Original | C9: 44946 | D9: 44960 | E9: =D9-C9 -> 14 | F9: Africa | G9: Kenya | H9: Kisumu | I9: Corporate | J9: Retail | K9: M. Rossi | L9: Networking | M9: NET-6036 | N9: 884.36 | O9: 1545.34 | P9: 0.243 | Q9: 41 | R9: =(O9*Q9)*(1-P9) -> 47962.718 | S9: =N9*Q9 -> 36258.76 | T9: =R9-S9 -> 11703.958 | U9: =IF(R9=0,0,T9/R9) -> 0.24402199 | V9: =TEXT(C9,"MMM-YYYY") -> Jan-2023 | W9: =DATEVALUE(V9) -> 44927 | X9: ="Q"&ROUNDUP(MONTH(C9)/3,0)&"-"&YEAR(C9) -> Q1-2023 | Y9: =_xlfn.CONCAT(F9," ","→"," ",G9," ","→"," ",H9) -> Africa → Kenya → Kisumu | Z9: =TRIM(L9) -> Networking | AA9: {=_xlfn.IFS(O9<=$AF$2,"Low",AND(O9>$AF$2,O9<$AF$3),"Medium",O9>=$AF$3,"High")} -> Medium | AB9: =_xlfn.MINIFS($W$2:$W$632,$G$2:$G$632,G9) -> 44927 | AC9: 0 | AJ9: =_xlfn.MINIFS($W$2:$W$632,$G$2:$G$632,G9) -> 44927
A10: ORD-2023-521818 | B10: =IF(COUNTIF($A$2:A10,A10)=1,"Original","Duplicate") -> Original | C10: 44948 | D10: 44956 | E10: =D10-C10 -> 8 | F10: Americas | G10: USA | H10: San Francisco | I10: Small Business | J10: Online | K10: A. Patel | L10: Networking | M10: NET-4155 | N10: 413.52 | O10: 1004.34 | P10: 0.111 | Q10: 18 | R10: =(O10*Q10)*(1-P10) -> 16071.449 | S10: =N10*Q10 -> 7443.36 | T10: =R10-S10 -> 8628.0887 | U10: =IF(R10=0,0,T10/R10) -> 0.53685818 | V10: =TEXT(C10,"MMM-YYYY") -> Jan-2023 | W10: =DATEVALUE(V10) -> 44927 | X10: ="Q"&ROUNDUP(MONTH(C10)/3,0)&"-"&YEAR(C10) -> Q1-2023 | Y10: =_xlfn.CONCAT(F10," ","→"," ",G10," ","→"," ",H10) -> Americas → USA → San Francisco | Z10: =TRIM(L10) -> Networking | AA10: {=_xlfn.IFS(O10<=$AF$2,"Low",AND(O10>$AF$2,O10<$AF$3),"Medium",O10>=$AF$3,"High")} -> Medium | AB10: =_xlfn.MINIFS($W$2:$W$632,$G$2:$G$632,G10) -> 44927 | AC10: 0 | AJ10: =_xlfn.MINIFS($W$2:$W$632,$G$2:$G$632,G10) -> 44927
A11: ORD-2023-613317 | B11: =IF(COUNTIF($A$2:A11,A11)=1,"Original","Duplicate") -> Original | C11: 44948 | D11: 44953 | E11: =D11-C11 -> 5 | F11: Europe | G11: Germany | H11: Munich | I11: Corporate | J11: Direct | K11: F. Müller | L11: Monitors | M11: MON-2537 | N11: 150.86 | O11: 346.96 | P11: 0.196 | Q11: 8 | R11: =(O11*Q11)*(1-P11) -> 2231.6467 | S11: =N11*Q11 -> 1206.88 | T11: =R11-S11 -> 1024.7667 | U11: =IF(R11=0,0,T11/R11) -> 0.45919756 | V11: =TEXT(C11,"MMM-YYYY") -> Jan-2023 | W11: =DATEVALUE(V11) -> 44927 | X11: ="Q"&ROUNDUP(MONTH(C11)/3,0)&"-"&YEAR(C11) -> Q1-2023 | Y11: =_xlfn.CONCAT(F11," ","→"," ",G11," ","→"," ",H11) -> Europe → Germany → Munich | Z11: =TRIM(L11) -> Monitors | AA11: {=_xlfn.IFS(O11<=$AF$2,"Low",AND(O11>$AF$2,O11<$AF$3),"Medium",O11>=$AF$3,"High")} -> Low | AB11: =_xlfn.MINIFS($W$2:$W$632,$G$2:$G$632,G11) -> 44927 | AC11: 0 | AJ11: =_xlfn.MINIFS($W$2:$W$632,$G$2:$G$632,G11) -> 44927
A12: ORD-2023-811823 | B12: =IF(COUNTIF($A$2:A12,A12)=1,"Original","Duplicate") -> Original | C12: 44952 | D12: 44972 | E12: =D12-C12 -> 20 | F12: Europe | G12: Germany | H12: Berlin | I12: Small Business | J12: Online | K12: O. Wang | L12: Networking | M12: NET-8787 | N12: 492.62 | O12: 366.7 | P12: 0.089 | Q12: 10 | R12: =(O12*Q12)*(1-P12) -> 3340.637 | S12: =N12*Q12 -> 4926.2 | T12: =R12-S12 -> -1585.563 | U12: =IF(R12=0,0,T12/R12) -> -0.47462894 | V12: =TEXT(C12,"MMM-YYYY") -> Jan-2023 | W12: =DATEVALUE(V12) -> 44927 | X12: ="Q"&ROUNDUP(MONTH(C12)/3,0)&"-"&YEAR(C12) -> Q1-2023 | Y12: =_xlfn.CONCAT(F12," ","→"," ",G12," ","→"," ",H12) -> Europe → Germany → Berlin | Z12: =TRIM(L12) -> Networking | AA12: {=_xlfn.IFS(O12<=$AF$2,"Low",AND(O12>$AF$2,O12<$AF$3),"Medium",O12>=$AF$3,"High")} -> Low | AB12: =_xlfn.MINIFS($W$2:$W$632,$G$2:$G$632,G12) -> 44927 | AC12: 0 | AJ12: =_xlfn.MINIFS($W$2:$W$632,$G$2:$G$632,G12) -> 44927
A13: ORD-2023-430904 | B13: =IF(COUNTIF($A$2:A13,A13)=1,"Original","Duplicate") -> Original | C13: 44953 | D13: 44957 | E13: =D13-C13 -> 4 | F13: Europe | G13: United Kingdom | H13: Manchester | I13: Enterprise | J13: Online | K13: N. Brown | L13: Laptops | M13: LAP-9782 | N13: 941.2 | O13: 668.02 | P13: 0.22 | Q13: 16 | R13: =(O13*Q13)*(1-P13) -> 8336.8896 | S13: =N13*Q13 -> 15059.2 | T13: =R13-S13 -> -6722.3104 | U13: =IF(R13=0,0,T13/R13) -> -0.80633314 | V13: =TEXT(C13,"MMM-YYYY") -> Jan-2023 | W13: =DATEVALUE(V13) -> 44927 | X13: ="Q"&ROUNDUP(MONTH(C13)/3,0)&"-"&YEAR(C13) -> Q1-2023 | Y13: =_xlfn.CONCAT(F13," ","→"," ",G13," ","→"," ",H13) -> Europe → United Kingdom → Manchester | Z13: =TRIM(L13) -> Laptops | AA13: {=_xlfn.IFS(O13<=$AF$2,"Low",AND(O13>$AF$2,O13<$AF$3),"Medium",O13>=$AF$3,"High")} -> Low | AB13: =_xlfn.MINIFS($W$2:$W$632,$G$2:$G$632,G13) -> 44927 | AC13: 0 | AJ13: =_xlfn.MINIFS($W$2:$W$632,$G$2:$G$632,G13) -> 44927
A14: ORD-2023-856322 | B14: =IF(COUNTIF($A$2:A14,A14)=1,"Original","Duplicate") -> Original | C14: 44955 | D14: 44963 | E14: =D14-C14 -> 8 | F14: Americas | G14: Brazil | H14: Brasília | I14: Corporate | J14: Marketplace | K14: D. Smith | L14: Monitors | M14: MON-7207 | N14: 41.84 | O14: 86.2 | P14: 0.226 | Q14: 27 | R14: =(O14*Q14)*(1-P14) -> 1801.4076 | S14: =N14*Q14 -> 1129.68 | T14: =R14-S14 -> 671.7276 | U14: =IF(R14=0,0,T14/R14) -> 0.3728904 | V14: =TEXT(C14,"MMM-YYYY") -> Jan-2023 | W14: =DATEVALUE(V14) -> 44927 | X14: ="Q"&ROUNDUP(MONTH(C14)/3,0)&"-"&YEAR(C14) -> Q1-2023 | Y14: =_xlfn.CONCAT(F14," ","→"," ",G14," ","→"," ",H14) -> Americas → Brazil → Brasília | Z14: =TRIM(L14) -> Monitors | AA14: {=_xlfn.IFS(O14<=$AF$2,"Low",AND(O14>$AF$2,O14<$AF$3),"Medium",O14>=$AF$3,"High")} -> Low | AB14: =_xlfn.MINIFS($W$2:$W$632,$G$2:$G$632,G14) -> 44927 | AC14: 0 | AJ14: =_xlfn.MINIFS($W$2:$W$632,$G$2:$G$632,G14) -> 44927
A15: ORD-2023-575584 | B15: =IF(COUNTIF($A$2:A15,A15)=1,"Original","Duplicate") -> Original | C15: 44956 | D15: 44978 | E15: =D15-C15 -> 22 | F15: Europe | G15: Germany | H15: Munich | I15: Small Business | J15: Marketplace | K15: G. Dubois | L15: Networking | M15: NET-3460 | N15: 1142.88 | O15: 1465.29 | P15: 0.186 | Q15: 7 | R15: =(O15*Q15)*(1-P15) -> 8349.2224 | S15: =N15*Q15 -> 8000.16 | T15: =R15-S15 -> 349.06242 | U15: =IF(R15=0,0,T15/R15) -> 0.041807776 | V15: =TEXT(C15,"MMM-YYYY") -> Jan-2023 | W15: =DATEVALUE(V15) -> 44927 | X15: ="Q"&ROUNDUP(MONTH(C15)/3,0)&"-"&YEAR(C15) -> Q1-2023 | Y15: =_xlfn.CONCAT(F15," ","→"," ",G15," ","→"," ",H15) -> Europe → Germany → Munich | Z15: =TRIM(L15) -> Networking | AA15: {=_xlfn.IFS(O15<=$AF$2,"Low",AND(O15>$AF$2,O15<$AF$3),"Medium",O15>=$AF$3,"High")} -> Medium | AB15: =_xlfn.MINIFS($W$2:$W$632,$G$2:$G$632,G15) -> 44927 | AC15: 0 | AJ15: =_xlfn.MINIFS($W$2:$W$632,$G$2:$G$632,G15) -> 44927
... A35: ORD-2023-276806 | B35: =IF(COUNTIF($A$2:A35,A35)=1,"Original","Duplicate") -> Original | C35: 44989 | D35: 45009 | E35: =D35-C35 -> 20 | F35: Americas | G35: Canada | H35: Montreal | I35: Consumer | J35: Distributor | K35: I. Johnson | L35: Laptops | M35: LAP-6160 | N35: 481.71 | O35: 912.45 | P35: 0.203 | Q35: 24 | R35: =(O35*Q35)*(1-P35) -> 17453.344 | S35: =N35*Q35 -> 11561.04 | T35: =R35-S35 -> 5892.3036 | U35: =IF(R35=0,0,T35/R35) -> 0.33760314 | V35: =TEXT(C35,"MMM-YYYY") -> Mar-2023 | W35: =DATEVALUE(V35) -> 44986 | X35: ="Q"&ROUNDUP(MONTH(C35)/3,0)&"-"&YEAR(C35) -> Q1-2023 | Y35: =_xlfn.CONCAT(F35," ","→"," ",G35," ","→"," ",H35) -> Americas → Canada → Montreal | Z35: =TRIM(L35) -> Laptops | AA35: {=_xlfn.IFS(O35<=$AF$2,"Low",AND(O35>$AF$2,O35<$AF$3),"Medium",O35>=$AF$3,"High")} -> Medium | AB35: =_xlfn.MINIFS($W$2:$W$632,$G$2:$G$632,G35) -> 44927 | AC35: 2 | AJ35: =_xlfn.MINIFS($W$2:$W$632,$G$2:$G$632,G35) -> 44927
A36: ORD-2023-854471 | B36: =IF(COUNTIF($A$2:A36,A36)=1,"Original","Duplicate") -> Original | C36: 44991 | D36: 45020 | E36: =D36-C36 -> 29 | F36: Asia | G36: China | H36: Beijing | I36: Small Business | J36: Direct | K36: C. Otieno | L36: Monitors | M36: MON-2073 | N36: 1126.29 | O36: 2050.87 | P36: 0.064 | Q36: 7 | R36: =(O36*Q36)*(1-P36) -> 13437.3 | S36: =N36*Q36 -> 7884.03 | T36: =R36-S36 -> 5553.2702 | U36: =IF(R36=0,0,T36/R36) -> 0.41327277 | V36: =TEXT(C36,"MMM-YYYY") -> Mar-2023 | W36: =DATEVALUE(V36) -> 44986 | X36: ="Q"&ROUNDUP(MONTH(C36)/3,0)&"-"&YEAR(C36) -> Q1-2023 | Y36: =_xlfn.CONCAT(F36," ","→"," ",G36," ","→"," ",H36) -> Asia → China → Beijing | Z36: =TRIM(L36) -> Monitors | AA36: {=_xlfn.IFS(O36<=$AF$2,"Low",AND(O36>$AF$2,O36<$AF$3),"Medium",O36>=$AF$3,"High")} -> High | AB36: =_xlfn.MINIFS($W$2:$W$632,$G$2:$G$632,G36) -> 44927 | AC36: 2
A37: ORD-2023-949710 | B37: =IF(COUNTIF($A$2:A37,A37)=1,"Original","Duplicate") -> Original | C37: 44992 | D37: 45017 | E37: =D37-C37 -> 25 | F37: Africa | G37: Kenya | H37: Nairobi | I37: Consumer | J37: Marketplace | K37: D. Smith | L37: Printers | M37: PRN-7049 | N37: 1024.1 | O37: 918.19 | P37: 0.189 | Q37: 10 | R37: =(O37*Q37)*(1-P37) -> 7446.5209 | S37: =N37*Q37 -> 10241 | T37: =R37-S37 -> -2794.4791 | U37: =IF(R37=0,0,T37/R37) -> -0.37527312 | V37: =TEXT(C37,"MMM-YYYY") -> Mar-2023 | W37: =DATEVALUE(V37) -> 44986 | X37: ="Q"&ROUNDUP(MONTH(C37)/3,0)&"-"&YEAR(C37) -> Q1-2023 | Y37: =_xlfn.CONCAT(F37," ","→"," ",G37," ","→"," ",H37) -> Africa → Kenya → Nairobi | Z37: =TRIM(L37) -> Printers | AA37: {=_xlfn.IFS(O37<=$AF$2,"Low",AND(O37>$AF$2,O37<$AF$3),"Medium",O37>=$AF$3,"High")} -> Medium | AB37: =_xlfn.MINIFS($W$2:$W$632,$G$2:$G$632,G37) -> 44927 | AC37: 2
A38: ORD-2023-281890 | B38: =IF(COUNTIF($A$2:A38,A38)=1,"Original","Duplicate") -> Original | C38: 44998 | D38: 45020 | E38: =D38-C38 -> 22 | F38: Africa | G38: South Africa | H38: Durban | I38: Small Business | J38: Retail | K38: A. Patel | L38: Components | M38: CMP-2574 | N38: 1113.7 | O38: 1620.6 | P38: 0.139 | Q38: 11 | R38: =(O38*Q38)*(1-P38) -> 15348.703 | S38: =N38*Q38 -> 12250.7 | T38: =R38-S38 -> 3098.0026 | U38: =IF(R38=0,0,T38/R38) -> 0.20184133 | V38: =TEXT(C38,"MMM-YYYY") -> Mar-2023 | W38: =DATEVALUE(V38) -> 44986 | X38: ="Q"&ROUNDUP(MONTH(C38)/3,0)&"-"&YEAR(C38) -> Q1-2023 | Y38: =_xlfn.CONCAT(F38," ","→"," ",G38," ","→"," ",H38) -> Africa → South Africa → Durban | Z38: =TRIM(L38) -> Components | AA38: {=_xlfn.IFS(O38<=$AF$2,"Low",AND(O38>$AF$2,O38<$AF$3),"Medium",O38>=$AF$3,"High")} -> Medium | AB38: =_xlfn.MINIFS($W$2:$W$632,$G$2:$G$632,G38) -> 44927 | AC38: 2
A39: ORD-2023-946143 | B39: =IF(COUNTIF($A$2:A39,A39)=1,"Original","Duplicate") -> Original | C39: 44999 | D39: 45015 | E39: =D39-C39 -> 16 | F39: Africa | G39: South Africa | H39: Cape Town | I39: Consumer | J39: Distributor | K39: K. Singh | L39: Components | M39: CMP-8230 | N39: 1309.77 | O39: 1589.07 | P39: 0.102 | Q39: 10 | R39: =(O39*Q39)*(1-P39) -> 14269.849 | S39: =N39*Q39 -> 13097.7 | T39: =R39-S39 -> 1172.1486 | U39: =IF(R39=0,0,T39/R39) -> 0.082141628 | V39: =TEXT(C39,"MMM-YYYY") -> Mar-2023 | W39: =DATEVALUE(V39) -> 44986 | X39: ="Q"&ROUNDUP(MONTH(C39)/3,0)&"-"&YEAR(C39) -> Q1-2023 | Y39: =_xlfn.CONCAT(F39," ","→"," ",G39," ","→"," ",H39) -> Africa → South Africa → Cape Town | Z39: =TRIM(L39) -> Components | AA39: {=_xlfn.IFS(O39<=$AF$2,"Low",AND(O39>$AF$2,O39<$AF$3),"Medium",O39>=$AF$3,"High")} -> Medium | AB39: =_xlfn.MINIFS($W$2:$W$632,$G$2:$G$632,G39) -> 44927 | AC39: 2
A40: ORD-2023-799597 | B40: =IF(COUNTIF($A$2:A40,A40)=1,"Original","Duplicate") -> Original | C40: 44999 | D40: 45003 | E40: =D40-C40 -> 4 | F40: Europe | G40: Germany | H40: Frankfurt | I40: Enterprise | J40: Direct | K40: A. Patel | L40: Components | M40: CMP-8675 | N40: 472.33 | O40: 360.34 | P40: 0.165 | Q40: 14 | R40: =(O40*Q40)*(1-P40) -> 4212.3746 | S40: =N40*Q40 -> 6612.62 | T40: =R40-S40 -> -2400.2454 | U40: =IF(R40=0,0,T40/R40) -> -0.56980816 | V40: =TEXT(C40,"MMM-YYYY") -> Mar-2023 | W40: =DATEVALUE(V40) -> 44986 | X40: ="Q"&ROUNDUP(MONTH(C40)/3,0)&"-"&YEAR(C40) -> Q1-2023 | Y40: =_xlfn.CONCAT(F40," ","→"," ",G40," ","→"," ",H40) -> Europe → Germany → Frankfurt | Z40: =TRIM(L40) -> Components | AA40: {=_xlfn.IFS(O40<=$AF$2,"Low",AND(O40>$AF$2,O40<$AF$3),"Medium",O40>=$AF$3,"High")} -> Low | AB40: =_xlfn.MINIFS($W$2:$W$632,$G$2:$G$632,G40) -> 44927 | AC40: 2
A41: ORD-2023-933238 | B41: =IF(COUNTIF($A$2:A41,A41)=1,"Original","Duplicate") -> Original | C41: 45002 | D41: 45022 | E41: =D41-C41 -> 20 | F41: Europe | G41: Germany | H41: Munich | I41: Consumer | J41: Retail | K41: O. Wang | L41: Phones | M41: PHN-8483 | N41: 692.18 | O41: 1159.35 | P41: 0.112 | Q41: 2 | R41: =(O41*Q41)*(1-P41) -> 2059.0056 | S41: =N41*Q41 -> 1384.36 | T41: =R41-S41 -> 674.6456 | U41: =IF(R41=0,0,T41/R41) -> 0.32765603 | V41: =TEXT(C41,"MMM-YYYY") -> Mar-2023 | W41: =DATEVALUE(V41) -> 44986 | X41: ="Q"&ROUNDUP(MONTH(C41)/3,0)&"-"&YEAR(C41) -> Q1-2023 | Y41: =_xlfn.CONCAT(F41," ","→"," ",G41," ","→"," ",H41) -> Europe → Germany → Munich | Z41: =TRIM(L41) -> Phones | AA41: {=_xlfn.IFS(O41<=$AF$2,"Low",AND(O41>$AF$2,O41<$AF$3),"Medium",O41>=$AF$3,"High")} -> Medium | AB41: =_xlfn.MINIFS($W$2:$W$632,$G$2:$G$632,G41) -> 44927 | AC41: 2
A42: ORD-2023-548874 | B42: =IF(COUNTIF($A$2:A42,A42)=1,"Original","Duplicate") -> Original | C42: 45004 | D42: 45025 | E42: =D42-C42 -> 21 | F42: Europe | G42: United Kingdom | H42: Manchester | I42: Consumer | J42: Retail | K42: L. Okafor | L42: Accessories | M42: ACC-9150 | N42: 1082.17 | O42: 1234.1 | P42: 0.189 | Q42: 16 | R42: =(O42*Q42)*(1-P42) -> 16013.682 | S42: =N42*Q42 -> 17314.72 | T42: =R42-S42 -> -1301.0384 | U42: =IF(R42=0,0,T42/R42) -> -0.081245427 | V42: =TEXT(C42,"MMM-YYYY") -> Mar-2023 | W42: =DATEVALUE(V42) -> 44986 | X42: ="Q"&ROUNDUP(MONTH(C42)/3,0)&"-"&YEAR(C42) -> Q1-2023 | Y42: =_xlfn.CONCAT(F42," ","→"," ",G42," ","→"," ",H42) -> Europe → United Kingdom → Manchester | Z42: =TRIM(L42) -> Accessories | AA42: {=_xlfn.IFS(O42<=$AF$2,"Low",AND(O42>$AF$2,O42<$AF$3),"Medium",O42>=$AF$3,"High")} -> Medium | AB42: =_xlfn.MINIFS($W$2:$W$632,$G$2:$G$632,G42) -> 44927 | AC42: 2
A43: ORD-2023-835010 | B43: =IF(COUNTIF($A$2:A43,A43)=1,"Original","Duplicate") -> Original | C43: 45008 | D43: 45031 | E43: =D43-C43 -> 23 | F43: Africa | G43: Kenya | H43: Mombasa | I43: Small Business | J43: Retail | K43: C. Otieno | L43: Accessories | M43: ACC-2988 | N43: 875.36 | O43: 1178.62 | P43: 0.151 | Q43: 53 | R43: =(O43*Q43)*(1-P43) -> 53034.364 | S43: =N43*Q43 -> 46394.08 | T43: =R43-S43 -> 6640.2841 | U43: =IF(R43=0,0,T43/R43) -> 0.1252072 | V43: =TEXT(C43,"MMM-YYYY") -> Mar-2023 | W43: =DATEVALUE(V43) -> 44986 | X43: ="Q"&ROUNDUP(MONTH(C43)/3,0)&"-"&YEAR(C43) -> Q1-2023 | Y43: =_xlfn.CONCAT(F43," ","→"," ",G43," ","→"," ",H43) -> Africa → Kenya → Mombasa | Z43: =TRIM(L43) -> Accessories | AA43: {=_xlfn.IFS(O43<=$AF$2,"Low",AND(O43>$AF$2,O43<$AF$3),"Medium",O43>=$AF$3,"High")} -> Medium | AB43: =_xlfn.MINIFS($W$2:$W$632,$G$2:$G$632,G43) -> 44927 | AC43: 2
A44: ORD-2023-240507 | B44: =IF(COUNTIF($A$2:A44,A44)=1,"Original","Duplicate") -> Original | C44: 45010 | D44: 45011 | E44: =D44-C44 -> 1 | F44: Asia | G44: Japan | H44: Osaka | I44: Small Business | J44: Distributor | K44: I. Johnson | L44: Monitors | M44: MON-9227 | N44: 135.12 | O44: 301.7 | P44: 0.14 | Q44: 47 | R44: =(O44*Q44)*(1-P44) -> 12194.714 | S44: =N44*Q44 -> 6350.64 | T44: =R44-S44 -> 5844.074 | U44: =IF(R44=0,0,T44/R44) -> 0.4792301 | V44: =TEXT(C44,"MMM-YYYY") -> Mar-2023 | W44: =DATEVALUE(V44) -> 44986 | X44: ="Q"&ROUNDUP(MONTH(C44)/3,0)&"-"&YEAR(C44) -> Q1-2023 | Y44: =_xlfn.CONCAT(F44," ","→"," ",G44," ","→"," ",H44) -> Asia → Japan → Osaka | Z44: =TRIM(L44) -> Monitors | AA44: {=_xlfn.IFS(O44<=$AF$2,"Low",AND(O44>$AF$2,O44<$AF$3),"Medium",O44>=$AF$3,"High")} -> Low | AB44: =_xlfn.MINIFS($W$2:$W$632,$G$2:$G$632,G44) -> 44986 | AC44: 0
A45: ORD-2023-864121 | B45: =IF(COUNTIF($A$2:A45,A45)=1,"Original","Duplicate") -> Original | C45: 45012 | D45: 45038 | E45: =D45-C45 -> 26 | F45: Asia | G45: India | H45: Delhi | I45: Non-Profit | J45: Marketplace | K45: J. Njeri | L45: Printers | M45: PRN-4506 | N45: 178.53 | O45: 199.37 | P45: 0.101 | Q45: 37 | R45: =(O45*Q45)*(1-P45) -> 6631.6443 | S45: =N45*Q45 -> 6605.61 | T45: =R45-S45 -> 26.03431 | U45: =IF(R45=0,0,T45/R45) -> 0.00392577 | V45: =TEXT(C45,"MMM-YYYY") -> Mar-2023 | W45: =DATEVALUE(V45) -> 44986 | X45: ="Q"&ROUNDUP(MONTH(C45)/3,0)&"-"&YEAR(C45) -> Q1-2023 | Y45: =_xlfn.CONCAT(F45," ","→"," ",G45," ","→"," ",H45) -> Asia → India → Delhi | Z45: =TRIM(L45) -> Printers | AA45: {=_xlfn.IFS(O45<=$AF$2,"Low",AND(O45>$AF$2,O45<$AF$3),"Medium",O45>=$AF$3,"High")} -> Low | AB45: =_xlfn.MINIFS($W$2:$W$632,$G$2:$G$632,G45) -> 44958 | AC45: 1
A46: ORD-2023-419187 | B46: =IF(COUNTIF($A$2:A46,A46)=1,"Original","Duplicate") -> Original | C46: 45016 | D46: 45021 | E46: =D46-C46 -> 5 | F46: Africa | G46: Kenya | H46: Nakuru | I46: Education | J46: Marketplace | K46: B. Chen | L46: Laptops | M46: LAP-7819 | N46: 533.26 | O46: 385.72 | P46: 0 | Q46: 15 | R46: =(O46*Q46)*(1-P46) -> 5785.8 | S46: =N46*Q46 -> 7998.9 | T46: =R46-S46 -> -2213.1 | U46: =IF(R46=0,0,T46/R46) -> -0.38250544 | V46: =TEXT(C46,"MMM-YYYY") -> Mar-2023 | W46: =DATEVALUE(V46) -> 44986 | X46: ="Q"&ROUNDUP(MONTH(C46)/3,0)&"-"&YEAR(C46) -> Q1-2023 | Y46: =_xlfn.CONCAT(F46," ","→"," ",G46," ","→"," ",H46) -> Africa → Kenya → Nakuru | Z46: =TRIM(L46) -> Laptops | AA46: {=_xlfn.IFS(O46<=$AF$2,"Low",AND(O46>$AF$2,O46<$AF$3),"Medium",O46>=$AF$3,"High")} -> Low | AB46: =_xlfn.MINIFS($W$2:$W$632,$G$2:$G$632,G46) -> 44927 | AC46: 2
A47: ORD-2023-613287 | B47: =IF(COUNTIF($A$2:A47,A47)=1,"Original","Duplicate") -> Original | C47: 45016 | D47: 45028 | E47: =D47-C47 -> 12 | F47: Africa | G47: Kenya | H47: Mombasa | I47: Small Business | J47: Online | K47: C. Otieno | L47: Phones | M47: PHN-8014 | N47: 304.22 | O47: 393.31 | P47: 0.265 | Q47: 15 | R47: =(O47*Q47)*(1-P47) -> 4336.2427 | S47: =N47*Q47 -> 4563.3 | T47: =R47-S47 -> -227.05725 | U47: =IF(R47=0,0,T47/R47) -> -0.05236267 | V47: =TEXT(C47,"MMM-YYYY") -> Mar-2023 | W47: =DATEVALUE(V47) -> 44986 | X47: ="Q"&ROUNDUP(MONTH(C47)/3,0)&"-"&YEAR(C47) -> Q1-2023 | Y47: =_xlfn.CONCAT(F47," ","→"," ",G47," ","→"," ",H47) -> Africa → Kenya → Mombasa | Z47: =TRIM(L47) -> Phones | AA47: {=_xlfn.IFS(O47<=$AF$2,"Low",AND(O47>$AF$2,O47<$AF$3),"Medium",O47>=$AF$3,"High")} -> Low | AB47: =_xlfn.MINIFS($W$2:$W$632,$G$2:$G$632,G47) -> 44927 | AC47: 2
... A632: ORD-2025-831576 | B632: =IF(COUNTIF($A$2:A632,A632)=1,"Original","Duplicate") -> Original | C632: 45915 | D632: 45925 | E632: =D632-C632 -> 10 | F632: Asia | G632: India | H632: Delhi | I632: Consumer | J632: Retail | K632: A. Patel | L632: Phones | M632: PHN-2859 | N632: 1488.91 | O632: 1483.74 | P632: 0.168 | Q632: 24 | R632: =(O632*Q632)*(1-P632) -> 29627.32 | S632: =N632*Q632 -> 35733.84 | T632: =R632-S632 -> -6106.5197 | U632: =IF(R632=0,0,T632/R632) -> -0.2061111 | V632: =TEXT(C632,"MMM-YYYY") -> Sept-2025 | W632: =DATEVALUE(V632) -> 45901 | X632: ="Q"&ROUNDUP(MONTH(C632)/3,0)&"-"&YEAR(C632) -> Q3-2025 | Y632: =_xlfn.CONCAT(F632," ","→"," ",G632," ","→"," ",H632) -> Asia → India → Delhi | Z632: =TRIM(L632) -> Phones | AA632: {=_xlfn.IFS(O632<=$AF$2,"Low",AND(O632>$AF$2,O632<$AF$3),"Medium",O632>=$AF$3,"High")} -> Medium | AB632: =_xlfn.MINIFS($W$2:$W$632,$G$2:$G$632,G632) -> 44958 | AC632: 31
E633: =COUNTIF(E2:E632, "<=7")/COUNT(E2:E632) -> 0.2725832 | Q633: =AVERAGE(Q2:Q632) -> 15.210777 | R633: =SUM(R2:R632) -> 11033837 | T633: =SUM(T2:T632) -> 3537641.8 | U633: =IF(R633=0,0,T633/R633) -> 0.32061755

Sheet What if Analysis
A1: Slide Control | B1: Label | C1: Value | D1: Helper Cells | E1: DiscountPct | F1: ScenarioDiscount | G1: UnitCost | H1: ScenarioUnitCost | I1: Quantity | J1: Quantity Uplift | K1: UnitPrice | L1: Scenario Revenue | M1: Scenario Profit | O1: RevenueDifference | P1: ProfitDifference | S1: BaseLine | T1: Scenario | U1: Difference
B2: Global Discount Cap | C2: =D2/100 -> 0.12 | D2: 12 | E2: 0 | F2: =MIN(E2,$C$2) -> 0 | G2: 315.87 | H2: =G2*(1+$C$3) -> 344.2983 | I2: 7 | J2: =I2*(1+$C$4) -> 7.98 | K2: 591.68 | L2: =K2*(1-F2)*J2 -> 4721.6064 | M2: =L2-(H2*J2) -> 1974.106 | O2: =L2-'Part A (2&3)'!R2 -> 579.8464 | P2: =M2-'Part A (2&3)'!T2 -> 43.435966 | R2: Total Revenue | S2: =SUM('Part A (2&3)'!R2:R632) -> 11033837 | T2: =SUM(L2:L632) -> 13037901 | U2: =SUM(O2:O632) -> 2004064.4
B3: Unit Cost Inflation | C3: =D3/100 -> 0.09 | D3: 9 | E3: 0.14 | F3: =MIN(E3,$C$2) -> 0.12 | G3: 299.02 | H3: =G3*(1+$C$3) -> 325.9318 | I3: 5 | J3: =I3*(1+$C$4) -> 5.7 | K3: 724.7 | L3: =K3*(1-F3)*J3 -> 3635.0952 | M3: =L3-(H3*J3) -> 1777.2839 | O3: =L3-'Part A (2&3)'!R3 -> 518.8852 | P3: =M3-'Part A (2&3)'!T3 -> 156.17394 | R3: TotalProfit | S3: =SUM('Part A (2&3)'!T2:T632) -> 3537641.8 | T3: =SUM(M2:M632) -> 3723129.2 | U3: =SUM(P2:P632) -> 185487.42
B4: Quantity Uplift | C4: =D4/100 -> 0.14 | D4: 14 | E4: 0.089 | F4: =MIN(E4,$C$2) -> 0.089 | G4: 401.66 | H4: =G4*(1+$C$3) -> 437.8094 | I4: 14 | J4: =I4*(1+$C$4) -> 15.96 | K4: 772.09 | L4: =K4*(1-F4)*J4 -> 11225.849 | M4: =L4-(H4*J4) -> 4238.4109 | O4: =L4-'Part A (2&3)'!R4 -> 1378.613 | P4: =M4-'Part A (2&3)'!T4 -> 14.414996
E5: 0 | F5: =MIN(E5,$C$2) -> 0 | G5: 1083.09 | H5: =G5*(1+$C$3) -> 1180.5681 | I5: 8 | J5: =I5*(1+$C$4) -> 9.12 | K5: 1425.87 | L5: =K5*(1-F5)*J5 -> 13003.934 | M5: =L5-(H5*J5) -> 2237.1533 | O5: =L5-'Part A (2&3)'!R5 -> 1596.9744 | P5: =M5-'Part A (2&3)'!T5 -> -505.08667
E6: 0.057 | F6: =MIN(E6,$C$2) -> 0.057 | G6: 833.57 | H6: =G6*(1+$C$3) -> 908.5913 | I6: 18 | J6: =I6*(1+$C$4) -> 20.52 | K6: 881.57 | L6: =K6*(1-F6)*J6 -> 17058.697 | M6: =L6-(H6*J6) -> -1585.5966 | O6: =L6-'Part A (2&3)'!R6 -> 2094.9277 | P6: =M6-'Part A (2&3)'!T6 -> -1545.1058
E7: 0.194 | F7: =MIN(E7,$C$2) -> 0.12 | G7: 28.38 | H7: =G7*(1+$C$3) -> 30.9342 | I7: 18 | J7: =I7*(1+$C$4) -> 20.52 | K7: 47.22 | L7: =K7*(1-F7)*J7 -> 852.67987 | M7: =L7-(H7*J7) -> 217.91009 | O7: =L7-'Part A (2&3)'!R7 -> 167.61211 | P7: =M7-'Part A (2&3)'!T7 -> 43.682328
E8: 0.066 | F8: =MIN(E8,$C$2) -> 0.066 | G8: 873.06 | H8: =G8*(1+$C$3) -> 951.6354 | I8: 10 | J8: =I8*(1+$C$4) -> 11.4 | K8: 2101.55 | L8: =K8*(1-F8)*J8 -> 22376.464 | M8: =L8-(H8*J8) -> 11527.82 | O8: =L8-'Part A (2&3)'!R8 -> 2747.9868 | P8: =M8-'Part A (2&3)'!T8 -> 629.94322
E9: 0.243 | F9: =MIN(E9,$C$2) -> 0.12 | G9: 884.36 | H9: =G9*(1+$C$3) -> 963.9524 | I9: 41 | J9: =I9*(1+$C$4) -> 46.74 | K9: 1545.34 | L9: =K9*(1-F9)*J9 -> 63561.689 | M9: =L9-(H9*J9) -> 18506.553 | O9: =L9-'Part A (2&3)'!R9 -> 15598.971 | P9: =M9-'Part A (2&3)'!T9 -> 6802.5959
E10: 0.111 | F10: =MIN(E10,$C$2) -> 0.111 | G10: 413.52 | H10: =G10*(1+$C$3) -> 450.7368 | I10: 18 | J10: =I10*(1+$C$4) -> 20.52 | K10: 1004.34 | L10: =K10*(1-F10)*J10 -> 18321.451 | M10: =L10-(H10*J10) -> 9072.3324 | O10: =L10-'Part A (2&3)'!R10 -> 2250.0028 | P10: =M10-'Part A (2&3)'!T10 -> 444.24368
E11: 0.196 | F11: =MIN(E11,$C$2) -> 0.12 | G11: 150.86 | H11: =G11*(1+$C$3) -> 164.4374 | I11: 8 | J11: =I11*(1+$C$4) -> 9.12 | K11: 346.96 | L11: =K11*(1-F11)*J11 -> 2784.5622 | M11: =L11-(H11*J11) -> 1284.8931 | O11: =L11-'Part A (2&3)'!R11 -> 552.91546 | P11: =M11-'Part A (2&3)'!T11 -> 260.12637
E12: 0.089 | F12: =MIN(E12,$C$2) -> 0.089 | G12: 492.62 | H12: =G12*(1+$C$3) -> 536.9558 | I12: 10 | J12: =I12*(1+$C$4) -> 11.4 | K12: 366.7 | L12: =K12*(1-F12)*J12 -> 3808.3262 | M12: =L12-(H12*J12) -> -2312.9699 | O12: =L12-'Part A (2&3)'!R12 -> 467.68918 | P12: =M12-'Part A (2&3)'!T12 -> -727.40694
E13: 0.22 | F13: =MIN(E13,$C$2) -> 0.12 | G13: 941.2 | H13: =G13*(1+$C$3) -> 1025.908 | I13: 16 | J13: =I13*(1+$C$4) -> 18.24 | K13: 668.02 | L13: =K13*(1-F13)*J13 -> 10722.523 | M13: =L13-(H13*J13) -> -7990.0393 | O13: =L13-'Part A (2&3)'!R13 -> 2385.633 | P13: =M13-'Part A (2&3)'!T13 -> -1267.7289
E14: 0.226 | F14: =MIN(E14,$C$2) -> 0.12 | G14: 41.84 | H14: =G14*(1+$C$3) -> 45.6056 | I14: 27 | J14: =I14*(1+$C$4) -> 30.78 | K14: 86.2 | L14: =K14*(1-F14)*J14 -> 2334.8477 | M14: =L14-(H14*J14) -> 931.10731 | O14: =L14-'Part A (2&3)'!R14 -> 533.44008 | P14: =M14-'Part A (2&3)'!T14 -> 259.37971
E15: 0.186 | F15: =MIN(E15,$C$2) -> 0.12 | G15: 1142.88 | H15: =G15*(1+$C$3) -> 1245.7392 | I15: 7 | J15: =I15*(1+$C$4) -> 7.98 | K15: 1465.29 | L15: =K15*(1-F15)*J15 -> 10289.852 | M15: =L15-(H15*J15) -> 348.85368 | O15: =L15-'Part A (2&3)'!R15 -> 1940.6301 | P15: =M15-'Part A (2&3)'!T15 -> -0.20874
E16: 0 | F16: =MIN(E16,$C$2) -> 0 | G16: 1214.49 | H16: =G16*(1+$C$3) -> 1323.7941 | I16: 11 | J16: =I16*(1+$C$4) -> 12.54 | K16: 1533.95 | L16: =K16*(1-F16)*J16 -> 19235.733 | M16: =L16-(H16*J16) -> 2635.355 | O16: =L16-'Part A (2&3)'!R16 -> 2362.283 | P16: =M16-'Part A (2&3)'!T16 -> -878.70501
... E632: 0.168 | F632: =MIN(E632,$C$2) -> 0.12 | G632: 1488.91 | H632: =G632*(1+$C$3) -> 1622.9119 | I632: 24 | J632: =I632*(1+$C$4) -> 27.36 | K632: 1483.74 | L632: =K632*(1-F632)*J632 -> 35723.711 | M632: =L632-(H632*J632) -> -8679.1584 | O632: =L632-'Part A (2&3)'!R632 -> 6096.3909 | P632: =M632-'Part A (2&3)'!T632 -> -2572.6387
I633: =AVERAGE(I2:I632) -> 15.210777

Sheet PART B(4)
A3: Sum of GrossRevenue | B3: Column Labels
A4: Row Labels | B4: 0 | C4: 1 | D4: 2 | E4: 3 | F4: 4 | G4: 5 | H4: 6 | I4: 7 | J4: 8 | K4: 9 | L4: 10 | M4: 11 | N4: 12 | O4: 13 | P4: 14 | Q4: 15 | R4: 16 | S4: 17 | T4: 18 | U4: 19 | V4: 20 | W4: 21 | X4: 22 | Y4: 23 | Z4: 24 | AA4: 25 | AB4: 26 | AC4: 27 | AD4: 28 | AE4: 29 | AF4: 30 | AG4: 31 | AH4: 32 | AI4: Grand Total
A5: Brazil | B5: 1801.4076 | C5: 24894.431 | D5: 24523.007 | E5: 12248.676 | F5: 27194.152 | G5: 46991.747 | H5: 93430.735 | I5: 37330.003 | J5: 7071.6331 | K5: 16213.633 | L5: 24161.263 | M5: 61471.697 | N5: 8567.3925 | O5: 39239.198 | P5: 110.1492 | Q5: 57491.063 | R5: 9469.7678 | S5: 41658.527 | T5: 10937.52 | U5: 41358.42 | V5: 85419.018 | X5: 11939.431 | Z5: 22987.328 | AA5: 70563.592 | AB5: 16257.34 | AC5: 68920.107 | AD5: 67596.422 | AF5: 38096.184 | AG5: 45754.744 | AH5: 24172.045 | AI5: 1037870.6
A6: Canada | B6: 4141.76 | C6: 26150.364 | D6: 17453.344 | E6: 15618.845 | G6: 46226.12 | H6: 29536.716 | I6: 52625.804 | J6: 15530.93 | K6: 27756.432 | M6: 14466.951 | N6: 19139.594 | O6: 9774.3888 | P6: 21931.504 | R6: 17930.495 | S6: 55516.604 | T6: 79082.507 | U6: 7466.3064 | V6: 64160.245 | X6: 60697.471 | Y6: 20713.04 | AA6: 8128.5187 | AC6: 7901.5042 | AD6: 76122.593 | AE6: 5335.5655 | AF6: 141645.57 | AG6: 24972.288 | AH6: 12597.522 | AI6: 882622.98
A7: China | B7: 11406.96 | C7: 10869.183 | D7: 13437.3 | E7: 23379.011 | F7: 49097.717 | G7: 5769.2758 | I7: 64096.735 | J7: 14108.168 | K7: 66630.072 | M7: 23668.56 | O7: 79081.561 | P7: 45749.976 | Q7: 14197.064 | S7: 70180.56 | T7: 50774.407 | V7: 21270.483 | W7: 68861.98 | X7: 4071.8 | Y7: 77129.274 | Z7: 56274.474 | AB7: 9378.6258 | AD7: 9684.8756 | AE7: 55548.647 | AF7: 20703.052 | AG7: 33684.351 | AI7: 899054.11
A8: France | B8: 9847.2359 | C8: 39546.775 | E8: 40811.052 | G8: 10388.43 | H8: 60768.603 | I8: 36549.429 | J8: 14877.464 | K8: 5159.7894 | L8: 22983.346 | M8: 28412.1 | N8: 29263.361 | O8: 20654.545 | P8: 45104.931 | Q8: 16219.345 | R8: 43635.435 | T8: 27907.425 | U8: 9189.1635 | W8: 41419.524 | X8: 67281.057 | Y8: 32011.667 | Z8: 20050.102 | AA8: 12040.644 | AC8: 33208.325 | AD8: 5331.6696 | AE8: 93323.681 | AG8: 68199.913 | AI8: 834185.01
A9: Germany | B9: 13921.506 | C9: 142962.67 | D9: 6271.3802 | E9: 104633.05 | F9: 17964.404 | G9: 5189.8836 | H9: 14114.069 | I9: 215.1984 | L9: 7643.265 | M9: 56963.241 | N9: 41020.91 | O9: 321.93291 | P9: 68292.728 | Q9: 37482.346 | R9: 32187.988 | S9: 65111.386 | U9: 47066.844 | X9: 12955.825 | Y9: 78869.294 | AA9: 30546.068 | AB9: 16870.42 | AC9: 5810.4845 | AD9: 10666.229 | AE9: 56166.984 | AG9: 56176.778 | AI9: 929424.89
A10: India | B10: 22044.871 | C10: 6631.6443 | D10: 32506.559 | E10: 249678.14 | F10: 4577.148 | G10: 12462.651 | H10: 7105.3528 | I10: 42824.197 | J10: 34805.041 | K10: 39388.574 | L10: 35984.637 | M10: 33792.866 | N10: 24305.883 | O10: 12668.507 | Q10: 35554.1 | R10: 31513.423 | S10: 30229.995 | T10: 44186.459 | U10: 20028.787 | V10: 599.532 | W10: 91856.869 | X10: 40695.915 | Y10: 33308.55 | Z10: 7120.6486 | AA10: 24075.09 | AB10: 4856.3573 | AC10: 62421.225 | AD10: 39717.144 | AF10: 11006.648 | AG10: 29627.32 | AI10: 1065574.1
A11: Japan | B11: 31024.839 | C11: 21196.913 | D11: 9062.3469 | E11: 4603.0824 | F11: 32142.114 | H11: 31130.742 | I11: 14527.748 | J11: 14268.608 | K11: 38506.529 | L11: 67110.666 | M11: 15253.07 | P11: 14287.896 | Q11: 68665.574 | R11: 23449.834 | S11: 82602.55 | T11: 50582.706 | U11: 29808.425 | W11: 18641.222 | X11: 15705.464 | Y11: 7955.6342 | Z11: 49818.787 | AA11: 20606.464 | AB11: 63856.507 | AC11: 11984.891 | AD11: 9315.4974 | AE11: 34082.865 | AF11: 74882.386 | AI11: 855073.36
A12: Kenya | B12: 47962.718 | C12: 21075.005 | D12: 70602.928 | E12: 11003.767 | F12: 10946.712 | G12: 3799.8031 | H12: 47047.518 | I12: 667.74 | J12: 1030.7574 | K12: 38264.51 | M12: 16061.973 | O12: 66852.129 | P12: 4866.3288 | Q12: 24447.959 | R12: 13108.786 | S12: 181608.7 | T12: 27763.018 | U12: 3823.6152 | V12: 52863.981 | W12: 51457.54 | X12: 123535.74 | Z12: 52609.066 | AA12: 15860.782 | AB12: 13669.81 | AC12: 17731.623 | AD12: 4569.8508 | AF12: 17867.219 | AG12: 15174.426 | AH12: 9050.5053 | AI12: 965324.51
A13: Nigeria | B13: 685.06776 | C13: 4737.2198 | E13: 32280.325 | F13: 43539.233 | G13: 7135.57 | H13: 112088.82 | I13: 24833.098 | K13: 10786.321 | M13: 27158.894 | P13: 28041.025 | Q13: 48850.807 | R13: 68626.652 | S13: 15009.057 | V13: 2879.9836 | W13: 100069.72 | Y13: 12967.959 | AA13: 23687.576 | AB13: 52727.976 | AC13: 40139.875 | AD13: 1010.3759 | AE13: 55110.62 | AF13: 119970.85 | AG13: 49501.66 | AI13: 881838.68
A14: South Africa | B14: 3116.21 | C14: 86597.081 | D14: 29618.551 | F14: 15476.944 | H14: 78566.393 | I14: 58520.37 | K14: 434.45248 | L14: 12954.358 | M14: 79406.785 | N14: 54214.972 | P14: 4826.5396 | Q14: 20171.633 | R14: 14032.851 | S14: 39907.476 | U14: 27331.83 | V14: 12972.002 | W14: 18061.204 | Z14: 6576.299 | AB14: 5565.3273 | AC14: 1886.9916 | AD14: 31556.188 | AE14: 88311.187 | AF14: 76636.156 | AH14: 13185.543 | AI14: 779927.34
A15: United Kingdom | B15: 27965.367 | C15: 4132.0325 | D15: 16013.682 | E15: 66551.125 | F15: 19800.889 | G15: 29905.538 | H15: 48616.566 | I15: 31801.901 | K15: 26003.218 | L15: 5610.0924 | N15: 27424.45 | P15: 33938.143 | Q15: 20646.611 | R15: 114279.15 | S15: 65319.42 | U15: 23687.524 | V15: 25249.613 | W15: 91431.438 | X15: 44605.989 | Y15: 82283.74 | Z15: 11332.143 | AA15: 35720.318 | AB15: 21062.612 | AC15: 96832.738 | AD15: 39263.703 | AE15: 52414.751 | AF15: 62736.309 | AG15: 853.32277 | AH15: 8764.4066 | AI15: 1134246.8
A16: USA | B16: 31035.218 | C16: 68738.647 | E16: 11375.258 | F16: 27431.638 | G16: 71887.464 | H16: 32086.376 | I16: 25299.04 | J16: 14692.623 | K16: 5533.623 | N16: 18566.16 | O16: 52311.008 | P16: 108770.28 | R16: 53872.641 | T16: 25483.915 | U16: 97443.478 | V16: 12186.369 | W16: 16023.123 | Y16: 12031.492 | Z16: 4654.7743 | AA16: 9984.7161 | AC16: 38240.697 | AD16: 3644.3213 | AG16: 27401.728 | AI16: 768694.59
A17: Grand Total | B17: 204953.16 | C17: 457531.97 | D17: 219489.1 | E17: 572182.33 | F17: 248170.95 | G17: 239756.48 | H17: 554491.89 | I17: 389291.26 | J17: 116385.22 | K17: 274677.15 | L17: 176447.63 | M17: 356656.14 | N17: 222502.72 | O17: 280903.27 | P17: 375919.5 | Q17: 343726.5 | R17: 422107.03 | S17: 647144.27 | T17: 316717.96 | U17: 307204.39 | V17: 277601.23 | W17: 497822.62 | X17: 381488.7 | Y17: 357270.65 | Z17: 231423.62 | AA17: 251213.77 | AB17: 204244.98 | AC17: 385078.46 | AD17: 298478.87 | AE17: 440294.3 | AF17: 563544.37 | AG17: 351346.53 | AH17: 67770.022 | AI17: 11033837

Sheet PART B(5)
A3: Row Labels | B3: Sum of GrossRevenue2 | C3: Sum of GrossRevenue | D3: ABC Category
A4: Accessories | B4: 1391191.4
A5: ACC-6626 | B5: 79082.507 | C5: 0.056845165 | D5: =IF(C5<=0.85,"A",IF(C5<=0.95,"B","C")) -> A
A6: ACC-1770 | B6: 76177.08 | C6: 0.11160189 | D6: =IF(C6<=0.85,"A",IF(C6<=0.95,"B","C")) -> A
A7: ACC-2988 | B7: 53034.364 | C7: 0.14972343 | D7: =IF(C7<=0.85,"A",IF(C7<=0.95,"B","C")) -> A
A8: ACC-9283 | B8: 46450.26 | C8: 0.18311226 | D8: =IF(C8<=0.85,"A",IF(C8<=0.95,"B","C")) -> A
A9: ACC-9533 | B9: 43084.872 | C9: 0.21408203 | D9: =IF(C9<=0.85,"A",IF(C9<=0.95,"B","C")) -> A
A10: ACC-8098 | B10: 38096.184 | C10: 0.24146588 | D10: =IF(C10<=0.85,"A",IF(C10<=0.95,"B","C")) -> A
A11: ACC-4490 | B11: 35396.278 | C11: 0.26690902 | D11: =IF(C11<=0.85,"A",IF(C11<=0.95,"B","C")) -> A
A12: ACC-7838 | B12: 35167.745 | C12: 0.29218789 | D12: =IF(C12<=0.85,"A",IF(C12<=0.95,"B","C")) -> A
A13: ACC-5177 | B13: 34139.16 | C13: 0.3167274 | D13: =IF(C13<=0.85,"A",IF(C13<=0.95,"B","C")) -> A
A14: ACC-9162 | B14: 33062.236 | C14: 0.34049281 | D14: =IF(C14<=0.85,"A",IF(C14<=0.95,"B","C")) -> A
A15: ACC-7078 | B15: 32086.376 | C15: 0.36355677 | D15: =IF(C15<=0.85,"A",IF(C15<=0.95,"B","C")) -> A
A16: ACC-1375 | B16: 31513.085 | C16: 0.38620864 | D16: =IF(C16<=0.85,"A",IF(C16<=0.95,"B","C")) -> A
... A91: ACC-6777 | B91: 18.65984 | C91: 1 | D91: =IF(C91<=0.85,"A",IF(C91<=0.95,"B","C")) -> C
A92: Components | B92: 1550200.5
A93: CMP-8851 | B93: 139277.83 | C93: 0.089845041 | D93: =IF(C93<=0.85,"A",IF(C93<=0.95,"B","C")) -> A
A94: CMP-3938 | B94: 84136.12 | C94: 0.14411939 | D94: =IF(C94<=0.85,"A",IF(C94<=0.95,"B","C")) -> A
A95: CMP-2040 | B95: 65111.386 | C95: 0.1861213 | D95: =IF(C95<=0.85,"A",IF(C95<=0.95,"B","C")) -> A
A96: CMP-3731 | B96: 60928.502 | C96: 0.22542492 | D96: =IF(C96<=0.85,"A",IF(C96<=0.95,"B","C")) -> A
A97: CMP-2096 | B97: 52361.645 | C97: 0.25920226 | D97: =IF(C97<=0.85,"A",IF(C97<=0.95,"B","C")) -> A
A98: CMP-8127 | B98: 50296.415 | C98: 0.29164736 | D98: =IF(C98<=0.85,"A",IF(C98<=0.95,"B","C")) -> A
A99: CMP-5006 | B99: 41419.524 | C99: 0.31836618 | D99: =IF(C99<=0.85,"A",IF(C99<=0.95,"B","C")) -> A
A100: CMP-1940 | B100: 40476.013 | C100: 0.34447636 | D100: =IF(C100<=0.85,"A",IF(C100<=0.95,"B","C")) -> A
A101: CMP-8002 | B101: 33687.502 | C101: 0.36620742 | D101: =IF(C101<=0.85,"A",IF(C101<=0.95,"B","C")) -> A
A102: CMP-1156 | B102: 33308.55 | C102: 0.38769403 | D102: =IF(C102<=0.85,"A",IF(C102<=0.95,"B","C")) -> A
A103: CMP-6529 | B103: 32335.218 | C103: 0.40855276 | D103: =IF(C103<=0.85,"A",IF(C103<=0.95,"B","C")) -> A
A104: CMP-6971 | B104: 27701.57 | C104: 0.42642243 | D104: =IF(C104<=0.85,"A",IF(C104<=0.95,"B","C")) -> A
... A182: CMP-1632 | B182: 97.0154 | C182: 1 | D182: =IF(C182<=0.85,"A",IF(C182<=0.95,"B","C")) -> C
A183: Laptops | B183: 1711094.4
A184: LAP-8910 | B184: 102122.94 | C184: 0.059682823 | D184: =IF(C184<=0.85,"A",IF(C184<=0.95,"B","C")) -> A
A185: LAP-3904 | B185: 82514.712 | C185: 0.10790618 | D185: =IF(C185<=0.85,"A",IF(C185<=0.95,"B","C")) -> A
A186: LAP-8214 | B186: 65119.33 | C186: 0.1459633 | D186: =IF(C186<=0.85,"A",IF(C186<=0.95,"B","C")) -> A
A187: LAP-5763 | B187: 65066.934 | C187: 0.1839898 | D187: =IF(C187<=0.85,"A",IF(C187<=0.95,"B","C")) -> A
A188: LAP-6499 | B188: 64192.977 | C188: 0.22150555 | D188: =IF(C188<=0.85,"A",IF(C188<=0.95,"B","C")) -> A
A189: LAP-1739 | B189: 58526.831 | C189: 0.25570987 | D189: =IF(C189<=0.85,"A",IF(C189<=0.95,"B","C")) -> A
A190: LAP-8825 | B190: 58057.65 | C190: 0.28964 | D190: =IF(C190<=0.85,"A",IF(C190<=0.95,"B","C")) -> A
A191: LAP-7523 | B191: 44173.628 | C191: 0.31545601 | D191: =IF(C191<=0.85,"A",IF(C191<=0.95,"B","C")) -> A
A192: LAP-1308 | B192: 42433.254 | C192: 0.34025491 | D192: =IF(C192<=0.85,"A",IF(C192<=0.95,"B","C")) -> A
A193: LAP-1178 | B193: 41914.216 | C193: 0.36475047 | D193: =IF(C193<=0.85,"A",IF(C193<=0.95,"B","C")) -> A
A194: LAP-4483 | B194: 40563.322 | C194: 0.38845654 | D194: =IF(C194<=0.85,"A",IF(C194<=0.95,"B","C")) -> A
A195: LAP-3490 | B195: 40139.875 | C195: 0.41191513 | D195: =IF(C195<=0.85,"A",IF(C195<=0.95,"B","C")) -> A
... A264: LAP-3017 | B264: 266.17822 | C264: 1 | D264: =IF(C264<=0.85,"A",IF(C264<=0.95,"B","C")) -> C
A265: Monitors | B265: 1572555.5
A266: MON-6962 | B266: 92715.25 | C266: 0.058958331 | D266: =IF(C266<=0.85,"A",IF(C266<=0.95,"B","C")) -> A
A267: MON-2266 | B267: 87404.93 | C267: 0.11453979 | D267: =IF(C267<=0.85,"A",IF(C267<=0.95,"B","C")) -> A
A268: MON-6699 | B268: 85637.74 | C268: 0.16899748 | D268: =IF(C268<=0.85,"A",IF(C268<=0.95,"B","C")) -> A
A269: MON-5188 | B269: 72665.817 | C269: 0.21520622 | D269: =IF(C269<=0.85,"A",IF(C269<=0.95,"B","C")) -> A
A270: MON-9662 | B270: 56176.778 | C270: 0.25092946 | D270: =IF(C270<=0.85,"A",IF(C270<=0.95,"B","C")) -> A
A271: MON-5386 | B271: 45547.183 | C271: 0.27989326 | D271: =IF(C271<=0.85,"A",IF(C271<=0.95,"B","C")) -> A
A272: MON-9967 | B272: 41106.801 | C272: 0.30603339 | D272: =IF(C272<=0.85,"A",IF(C272<=0.95,"B","C")) -> A
A273: MON-9733 | B273: 38818.76 | C273: 0.33071853 | D273: =IF(C273<=0.85,"A",IF(C273<=0.95,"B","C")) -> A
A274: MON-8651 | B274: 34632.106 | C274: 0.35274135 | D274: =IF(C274<=0.85,"A",IF(C274<=0.95,"B","C")) -> A
A275: MON-4373 | B275: 32280.325 | C275: 0.37326865 | D275: =IF(C275<=0.85,"A",IF(C275<=0.95,"B","C")) -> A
A276: MON-4925 | B276: 31680.795 | C276: 0.39341471 | D276: =IF(C276<=0.85,"A",IF(C276<=0.95,"B","C")) -> A
A277: MON-6341 | B277: 31191.647 | C277: 0.41324972 | D277: =IF(C277<=0.85,"A",IF(C277<=0.95,"B","C")) -> A
... A359: MON-5444 | B359: 66.92076 | C359: 1 | D359: =IF(C359<=0.85,"A",IF(C359<=0.95,"B","C")) -> C
A360: Networking | B360: 1792642.7
A361: NET-2365 | B361: 109244 | C361: 0.060940196 | D361: =IF(C361<=0.85,"A",IF(C361<=0.95,"B","C")) -> A
A362: NET-5987 | B362: 82141.34 | C362: 0.10676156 | D362: =IF(C362<=0.85,"A",IF(C362<=0.95,"B","C")) -> A
A363: NET-5523 | B363: 79548.756 | C363: 0.15113669 | D363: =IF(C363<=0.85,"A",IF(C363<=0.95,"B","C")) -> A
A364: NET-1612 | B364: 66988.771 | C364: 0.18850542 | D364: =IF(C364<=0.85,"A",IF(C364<=0.95,"B","C")) -> A
A365: NET-5018 | B365: 60292.805 | C365: 0.22213889 | D365: =IF(C365<=0.85,"A",IF(C365<=0.95,"B","C")) -> A
A366: NET-1282 | B366: 51768.182 | C366: 0.25101703 | D366: =IF(C366<=0.85,"A",IF(C366<=0.95,"B","C")) -> A
A367: NET-4735 | B367: 50090.397 | C367: 0.27895924 | D367: =IF(C367<=0.85,"A",IF(C367<=0.95,"B","C")) -> A
A368: NET-3850 | B368: 49336.511 | C368: 0.3064809 | D368: =IF(C368<=0.85,"A",IF(C368<=0.95,"B","C")) -> A
A369: NET-6036 | B369: 47962.718 | C369: 0.33323622 | D369: =IF(C369<=0.85,"A",IF(C369<=0.95,"B","C")) -> A
A370: NET-3828 | B370: 47693.373 | C370: 0.35984128 | D370: =IF(C370<=0.85,"A",IF(C370<=0.95,"B","C")) -> A
A371: NET-3535 | B371: 43553.493 | C371: 0.38413697 | D371: =IF(C371<=0.85,"A",IF(C371<=0.95,"B","C")) -> A
A372: NET-1893 | B372: 40488.793 | C372: 0.40672306 | D372: =IF(C372<=0.85,"A",IF(C372<=0.95,"B","C")) -> A
... A446: NET-4241 | B446: 34.68906 | C446: 1 | D446: =IF(C446<=0.85,"A",IF(C446<=0.95,"B","C")) -> C
A447: Phones | B447: 1399242.2
A448: PHN-9677 | B448: 68665.574 | C448: 0.049073401 | D448: =IF(C448<=0.85,"A",IF(C448<=0.95,"B","C")) -> A
A449: PHN-8368 | B449: 52780.07 | C449: 0.086793868 | D449: =IF(C449<=0.85,"A",IF(C449<=0.95,"B","C")) -> A
A450: PHN-4568 | B450: 42495.805 | C450: 0.11716445 | D450: =IF(C450<=0.85,"A",IF(C450<=0.95,"B","C")) -> A
A451: PHN-7488 | B451: 41352.246 | C451: 0.14671777 | D451: =IF(C451<=0.85,"A",IF(C451<=0.95,"B","C")) -> A
A452: PHN-5683 | B452: 41138.262 | C452: 0.17611815 | D452: =IF(C452<=0.85,"A",IF(C452<=0.95,"B","C")) -> A
A453: PHN-4915 | B453: 38422.022 | C453: 0.20357732 | D453: =IF(C453<=0.85,"A",IF(C453<=0.95,"B","C")) -> A
A454: PHN-8804 | B454: 37038.582 | C454: 0.23004778 | D454: =IF(C454<=0.85,"A",IF(C454<=0.95,"B","C")) -> A
A455: PHN-1197 | B455: 35367.211 | C455: 0.25532375 | D455: =IF(C455<=0.85,"A",IF(C455<=0.95,"B","C")) -> A
A456: PHN-6832 | B456: 34840.344 | C456: 0.28022319 | D456: =IF(C456<=0.85,"A",IF(C456<=0.95,"B","C")) -> A
A457: PHN-8776 | B457: 34800.431 | C457: 0.3050941 | D457: =IF(C457<=0.85,"A",IF(C457<=0.95,"B","C")) -> A
A458: PHN-6111 | B458: 33551.927 | C458: 0.32907274 | D458: =IF(C458<=0.85,"A",IF(C458<=0.95,"B","C")) -> A
A459: PHN-1919 | B459: 33071.315 | C459: 0.3527079 | D459: =IF(C459<=0.85,"A",IF(C459<=0.95,"B","C")) -> A
... A535: PHN-3803 | B535: 76.13872 | C535: 1 | D535: =IF(C535<=0.85,"A",IF(C535<=0.95,"B","C")) -> C
A536: Printers | B536: 1616910.2
A537: PRN-1654 | B537: 66260.314 | C537: 0.040979589 | D537: =IF(C537<=0.85,"A",IF(C537<=0.95,"B","C")) -> A
A538: PRN-6308 | B538: 58091.635 | C538: 0.076907147 | D538: =IF(C538<=0.85,"A",IF(C538<=0.95,"B","C")) -> A
A539: PRN-7019 | B539: 55880.484 | C539: 0.11146719 | D539: =IF(C539<=0.85,"A",IF(C539<=0.95,"B","C")) -> A
A540: PRN-2407 | B540: 50545.319 | C540: 0.14272763 | D540: =IF(C540<=0.85,"A",IF(C540<=0.95,"B","C")) -> A
A541: PRN-9490 | B541: 43907.94 | C541: 0.16988309 | D541: =IF(C541<=0.85,"A",IF(C541<=0.95,"B","C")) -> A
A542: PRN-8970 | B542: 43209.006 | C542: 0.19660628 | D542: =IF(C542<=0.85,"A",IF(C542<=0.95,"B","C")) -> A
A543: PRN-2293 | B543: 40325.31 | C543: 0.22154601 | D543: =IF(C543<=0.85,"A",IF(C543<=0.95,"B","C")) -> A
A544: PRN-6131 | B544: 39810.328 | C544: 0.24616725 | D544: =IF(C544<=0.85,"A",IF(C544<=0.95,"B","C")) -> A
A545: PRN-5384 | B545: 38535.955 | C545: 0.27000033 | D545: =IF(C545<=0.85,"A",IF(C545<=0.95,"B","C")) -> A
A546: PRN-5876 | B546: 37562.28 | C546: 0.29323123 | D546: =IF(C546<=0.85,"A",IF(C546<=0.95,"B","C")) -> A
A547: PRN-7079 | B547: 36549.429 | C547: 0.31583572 | D547: =IF(C547<=0.85,"A",IF(C547<=0.95,"B","C")) -> A
A548: PRN-4911 | B548: 35567.738 | C548: 0.33783307 | D548: =IF(C548<=0.85,"A",IF(C548<=0.95,"B","C")) -> A
... A639: PRN-6276 | B639: 685.06776 | C639: 1 | D639: =IF(C639<=0.85,"A",IF(C639<=0.95,"B","C")) -> C
A640: Grand Total | B640: 11033837

Sheet Revenue per Order
A3: Row Labels | B3: Sum of GrossRevenue
A4: ORD-2023-107265 | B4: 13856.524
A5: ORD-2023-109927 | B5: 12462.651
A6: ORD-2023-112666 | B6: 685.06776
A7: ORD-2023-125739 | B7: 855.72882
A8: ORD-2023-126505 | B8: 14466.951
A9: ORD-2023-128295 | B9: 7135.57
A10: ORD-2023-132101 | B10: 13784.586
A11: ORD-2023-133848 | B11: 25299.04
A12: ORD-2023-139236 | B12: 18830.125
A13: ORD-2023-144816 | B13: 9829.0483
A14: ORD-2023-156396 | B14: 2795.6384
A15: ORD-2023-157993 | B15: 14448.299
... A635: Grand Total | B635: 11033837

Sheet Orders per Month
A3: Row Labels | B3: Number of Orders
A4: Jan | B4: 53
A5: Feb | B5: 51
A6: Mar | B6: 58
A7: Apr | B7: 63
A8: May | B8: 67
A9: Jun | B9: 68
A10: Jul | B10: 53
A11: Aug | B11: 65
A12: Sept | B12: 42
A13: Oct | B13: 39
A14: Nov | B14: 30
A15: Dec | B15: 42
A16: Grand Total | B16: 631

Sheet Order_Gross Profit_by_SP
A3: Row Labels | B3: Sum of GrossProfit
A4: A. Patel | B4: 282234.27
A5: ORD-2023-159821 | B5: 43304.492
A6: ORD-2023-974506 | B6: 29722.714
A7: ORD-2025-677880 | B7: 28223.378
A8: ORD-2025-997421 | B8: 19655.722
A9: ORD-2025-929414 | B9: 17260.178
A10: ORD-2024-129345 | B10: 15439.445
A11: ORD-2024-371409 | B11: 13734.075
A12: ORD-2023-290237 | B12: 12897.699
A13: ORD-2024-594527 | B13: 11831.752
A14: ORD-2025-922513 | B14: 9686.9653
A15: ORD-2023-308124 | B15: 9363.1594
... A651: Grand Total | B651: 3537641.8

Sheet Part B(7)
A3: Sum of GrossRevenue | B3: Column Labels
A4: Row Labels | B4: Direct | C4: Distributor | D4: Marketplace | E4: Online | F4: Retail | G4: Unknown | H4: Grand Total
A5: Americas | B5: 751887.69 | C5: 568863.41 | D5: 366375.93 | E5: 689951.45 | F5: 302853.58 | G5: 9256.14 | H5: 2689188.2
A6: Europe | B6: 842614.45 | C6: 318736.67 | D6: 645580.62 | E6: 585406.72 | F6: 487467.78 | G6: 18050.446 | H6: 2897856.7
A7: Africa | B7: 462236.49 | C7: 634581.62 | D7: 527467.87 | E7: 433406.34 | F7: 536681.28 | G7: 32716.924 | H7: 2627090.5
A8: Asia | B8: 642753.26 | C8: 509418.81 | D8: 546106.24 | E8: 413661.51 | F8: 666382.39 | G8: 41379.395 | H8: 2819701.6
A9: Grand Total | B9: 2699491.9 | C9: 2031600.5 | D9: 2085530.7 | E9: 2122426 | F9: 1993385 | G9: 101402.91 | H9: 11033837

Sheet Profit By Region
A3: Sum of GrossProfit | B3: Column Labels
A4: Row Labels | B4: Direct | C4: Distributor | D4: Marketplace | E4: Online | F4: Retail | G4: Unknown | H4: Grand Total
A5: Africa | B5: 178727.35 | C5: 202729.86 | D5: 164839.3 | E5: 145453.95 | F5: 159130.73 | G5: 16237.344 | H5: 867118.54
A6: Americas | B6: 258674.93 | C6: 175736.86 | D6: 96609.648 | E6: 261943.84 | F6: 69035.709 | G6: 777.96 | H6: 862778.95
A7: Asia | B7: 229541.95 | C7: 151146.75 | D7: 132709.51 | E7: 149042.39 | F7: 158051.77 | G7: 20547.545 | H7: 841039.91
A8: Europe | B8: 292716.95 | C8: 105550.85 | D8: 187596.9 | E8: 200067.16 | F8: 172743.84 | G8: 8028.7065 | H8: 966704.41
A9: Grand Total | B9: 959661.18 | C9: 635164.32 | D9: 581755.37 | E9: 756507.34 | F9: 558962.05 | G9: 45591.556 | H9: 3537641.8

Sheet Monthly Revenue
A3: Row Labels | B3: Sum of GrossRevenue
A4: Jan | B4: 674482.02
A5: Feb | B5: 981150.5
A6: Mar | B6: 799302.77
A7: Apr | B7: 947246.58
A8: May | B8: 1262901.9
A9: Jun | B9: 1328878.3
A10: Jul | B10: 1323460
A11: Aug | B11: 1090009.6
A12: Sept | B12: 661159.43
A13: Oct | B13: 663847.32
A14: Nov | B14: 543953.69
A15: Dec | B15: 757444.97
A16: Grand Total | B16: 11033837

Sheet Top 10 SKUs
A3: Row Labels | B3: Sum of GrossRevenue
A4: CMP-8851 | B4: 139277.83
A5: NET-2365 | B5: 109244
A6: LAP-8910 | B6: 102122.94
A7: MON-6962 | B7: 92715.25
A8: MON-2266 | B8: 87404.93
A9: MON-6699 | B9: 85637.74
A10: CMP-3938 | B10: 84136.12
A11: LAP-3904 | B11: 82514.712
A12: NET-5987 | B12: 82141.34
A13: NET-5523 | B13: 79548.756
A14: Grand Total | B14: 944743.62
